Workbook

Sheet PEMBELIAN KREDIT
A5: LAPORAN PEMBELIAN BAHAN ( KREDIT )
H7: CABANG | I7: : | J7: =LPKK!Q4 -> SC MARABAHAN
H8: PERIODE | I8: : | J8: =LPKK!Q5 -> 1-7 JULI 2026
A10: TANGGAL | B10: NAMA SUPLIER | C10: NAMA BAHAN | D10: NOMOR | E10: JUMLAH | F10: HARGA | G10: TOTAL | H10: TOTAL PPN | I10: UNIT PPN | J10: TANGGAL | K10: TANGGAL
D11: FAKTUR | E11: ( UNIT ) | F11: ( UNIT ) | H11: 0.11 | J11: JTH TEMPO | K11: DIBAYAR
A13: 46209 | B13: BERKAH MARKET | C13: BERAS | E13: 175 | F13: 16600 | G13: =F13*E13 -> 2905000
C14: TEPUNG | E14: 75 | F14: 10080 | G14: =F14*E14 -> 756000
A15: 46205 | B15: PT AMANAH BAGUS INDONRSIA | C15: BARGUD | E15: 1 | F15: 7994348 | G15: =F15*E15 -> 7994348
G16: =F16*E16 -> 0
G17: =F17*E17 -> 0
G18: =F18*E18 -> 0
G19: =F19*E19 -> 0
G20: =F20*E20 -> 0
G21: =F21*E21 -> 0
G22: =F22*E22 -> 0
G23: =F23*E23 -> 0
G24: =F24*E24 -> 0
G25: =F25*E25 -> 0
G26: =F26*E26 -> 0
A27: SUB TOTAL KREDIT BARGUD | G27: =SUM(G13:G26) -> 11655348
C28: MARINADE | D28: KARKAS | F28: 2273 | G28: =F28*E28 -> 0
D29: WHOLE | F29: 1855 | G29: =F29*E29 -> 0
A30: SUB TOTAL MARINADE | G30: =SUM(G28:G29) -> 0
A31: TANGGAL | B31: NAMA SUPLIER | C31: NOMER FAKTUR | D31: NAMA UNIT | E31: BERAT PCS | F31: BERAT EKOR | G31: HARGA TOTAL | H31: HARGA PER UNIT | I31: UNIT | J31: HARGA PER PCS
A32: 46205 | B32: CHICKEN GO | C32: PJL74773 | D32: MENTOK | E32: 130 | F32: 1200 | G32: 4111875 | H32: =E32/F32*G32 -> 445453.12 | I32: 85 | J32: =H32/I32 -> 5240.625
A33: 46209 | B33: CHICKEN GO | C33: PJL75242 | D33: DADA | E33: 310 | F33: 1200 | G33: 4111875 | H33: =E33/F33*G33 -> 1062234.4 | I33: 170 | J33: =H33/I33 -> 6248.4375
D34: PAHA ATAS | E34: 320 | F34: 1200 | G34: 4111875 | H34: =E34/F34*G34 -> 1096500 | I34: 170 | J34: =H34/I34 -> 6450
D35: PAHA BAWAH | E35: 230 | F35: 1200 | G35: 4111875 | H35: =E35/F35*G35 -> 788109.38 | I35: 170 | J35: =H35/I35 -> 4635.9375
D36: SAYAP | E36: 210 | F36: 1200 | G36: 4118875 | H36: =E36/F36*G36 -> 720803.12 | I36: 170 | J36: =H36/I36 -> 4240.0184
D37: SAYAP FULL | E37: 1200 | F37: 1200 | G37: 204085 | H37: =E37/F37*G37 -> 204085 | I37: 70 | J37: =H37/I37 -> 2915.5
D38: KULIT | E38: 1200 | F38: 1200 | G38: 369250 | H38: =E38/F38*G38 -> 369250 | I38: 10.55 | J38: =H38/I38 -> 35000
D39: P.BAWAH FULL | E39: 1200 | F39: 1200 | G39: 292600 | H39: =E39/F39*G39 -> 292600 | I39: 70 | J39: =H39/I39 -> 4180
D40: CUT 10 | E40: 1000 | F40: 1000 | G40: 204375 | H40: =E40/F40*G40 -> 204375 | I40: 50 | J40: =H40/I40 -> 4087.5
D41: WHOLE | E41: 1200 | F41: 1200 | G41: 1925600 | H41: =E41/F41*G41 -> 1925600 | I41: 80 | J41: =H41/I41 -> 24070
A42: SUB TOTAL KREDIT SUPLAYER | G42: =G36+G41-H42 -> -1064535 | H42: =SUM(H32:H41) -> 7109010
A43: SUB TOTAL KREDIT BARGUD & AYAM | G43: =SUM(H42+G30+G27) -> 18764358
J44: Paraf Supervisor

Sheet TO-TI
A2: TO / TI PERKEDEL | F2: TO / TI CATTERING STAFF | K2: TO / TI FREE | P2: TO / TI CHICKEN PATTY
C3: CABANG : | D3: =LPKK!Q4 -> SC MARABAHAN | H3: CABANG : | I3: =D3 -> SC MARABAHAN | M3: CABANG : | N3: =I3 -> SC MARABAHAN | R3: CABANG : | S3: =D3 -> SC MARABAHAN
C4: PERIODE / TGL : | D4: =LPKK!Q5 -> 1-7 JULI 2026 | H4: PERIODE / TGL : | I4: =D4 -> 1-7 JULI 2026 | M4: PERIODE / TGL : | N4: =I4 -> 1-7 JULI 2026 | R4: PERIODE / TGL : | S4: =D4 -> 1-7 JULI 2026
K5: FREE + VOUCER
A6: NAMA BAHAN | B6: QTY | C6: HARGA BELI | D6: TOTAL | F6: NAMA PRODUCT | G6: QTY | H6: HARGA JUAL | I6: TOTAL | K6: NAMA PRODUCT | L6: QTY | M6: HARGA JUAL | N6: TOTAL | P6: NAMA BAHAN | Q6: QTY | R6: HARGA BELI | S6: TOTAL
A7: KENTANG MANUAL | B7: =H34 -> 5000 | C7: =WEEKLY!E275 -> 25000 | D7: =B7/1000*C7 -> 125000 | F7: DADA | G7: 14 | H7: ='LAP. PENJUALAN REGULER'!S8 -> 15000 | I7: =H7*G7*G20 -> 120500.97 | K7: DADA | M7: =H7 -> 15000 | N7: =L7*M7*L21 -> 0 | P7: DAGING / MENTOK | Q7: 15 | R7: =WEEKLY!E11 -> 5240.625 | S7: =R7*Q7 -> 78609.375
A8: DAGING AYAM/MENTOK | C8: =WEEKLY!E11 -> 5240.625 | D8: =B8*C8 -> 0 | F8: P.ATAS | H8: ='LAP. PENJUALAN REGULER'!S9 -> 15000 | I8: =H8*G8*G20 -> 0 | K8: P.ATAS | M8: =H8 -> 15000 | N8: =L8*M8*L21 -> 0 | P8: PAHA BAWAH | R8: =WEEKLY!E14 -> 4635.9375 | S8: =R8*Q8 -> 0
A9: BATANG SLEDRI | B9: =H36 -> 100 | C9: =WEEKLY!E278 -> 10000 | D9: =B9/1000*C9 -> 1000 | F9: P.BAWAH | H9: ='LAP. PENJUALAN REGULER'!S10 -> 13500 | I9: =H9*G9*G20 -> 0 | K9: P.BAWAH | M9: =H9 -> 13500 | N9: =L9*M9*L21 -> 0 | P9: DAGING GILING | S9: =R9*Q9 -> 0
A10: KUNING TELUR | B10: =H37 -> 4 | C10: =WEEKLY!E282 -> 2322 | D10: =B10/16*C10 -> 580.5 | F10: SAYAP | H10: ='LAP. PENJUALAN REGULER'!S11 -> 12500 | I10: =H10*G10*G20 -> 0 | K10: SAYAP | M10: =H10 -> 12500 | N10: =L10*M10*L21 -> 0 | P10: ROTI TAWAR | Q10: =R37 -> 8 | R10: =WEEKLY!E48 -> 900 | S10: =R10/12*Q10 -> 600
A11: BAWANG MERAH | B11: =H38 -> 40 | C11: =WEEKLY!E280 -> 50000 | D11: =B11/1000*C11 -> 2000 | F11: NASI | G11: 14 | H11: ='LAP. PENJUALAN REGULER'!S16 -> 5000 | I11: =H11*G11*G20 -> 40166.99 | K11: NASI | M11: =H11 -> 5000 | N11: =L11*M11*L21 -> 0 | P11: SUSU ULTRA | Q11: =R38 -> 25 | R11: =WEEKLY!E51 -> 6000 | S11: =Q11/150*R11 -> 1000
A12: BAWANG PUTIH | B12: =H39 -> 10 | C12: =WEEKLY!E279 -> 40000 | D12: =B12/1000*C12 -> 400 | I12: =H12*G12*G20 -> 0 | M12: =H12 -> 0 | N12: =L12*M12*L21 -> 0 | P12: BAWANG BOMBAY | Q12: =R39 -> 50 | R12: =WEEKLY!E44 -> 40000 | S12: =Q12/1000*R12 -> 2000
A13: PREMIK PERKEDEL | I13: =H13*G13*G20 -> 0 | M13: =H13 -> 0 | N13: =M13*L13*L21 -> 0 | P13: TELUR | Q13: =R40 -> 4 | R13: =WEEKLY!E282 -> 2322 | S13: =Q13/16*R13 -> 580.5
A14: VETSIN | B14: =H41 -> 20 | C14: =WEEKLY!E274 -> 14000 | D14: =B14/250*C14 -> 1120 | I14: =H14*G14*G20 -> 0 | M14: =H14 -> 0 | N14: =M14*L14*L21 -> 0 | P14: MARGARIN | Q14: =R41 -> 10 | R14: =WEEKLY!E46 -> 7000 | S14: =Q14/200*R14 -> 350
A15: LADA | B15: =H42 -> 6 | C15: =WEEKLY!E277 -> 1500 | D15: =B15*C15 -> 9000 | I15: =H15*G15*G20 -> 0 | M15: =H15 -> 0 | N15: =M15*L15*L21 -> 0 | P15: VETSIN | Q15: =R42 -> 30 | R15: =WEEKLY!E274 -> 14000 | S15: =Q15/250*R15 -> 1680
A16: GARAM | B16: =H43 -> 10 | C16: =WEEKLY!E276 -> 8000 | D16: =C16/250*B16 -> 320 | I16: =H16*G16*G20 -> 0 | M16: =H16 -> 0 | N16: =M16*L16*L21 -> 0 | P16: LADA | Q16: =R43 -> 15 | R16: =WEEKLY!E277 -> 1500 | S16: =Q16/250*R16 -> 90
I17: =H17*G17*G20 -> 0 | M17: =H17 -> 0 | N17: =M17*L17*L21 -> 0 | P17: GARAM | Q17: =R44 -> 18 | R17: =WEEKLY!E276 -> 8000 | S17: =R17/250*Q17 -> 576
C18: SUB TOTAL | D18: =SUM(D7:D17) -> 139420.5 | I18: =H18*G18*G20 -> 0 | M18: =H18 -> 0 | N18: =M18*L18*L21 -> 0
I19: =H19*G19*G20 -> 0 | M19: =H19 -> 0 | N19: =M19*L19*L21 -> 0 | R19: SUB TOTAL | S19: =S7+S8+S10+S11+S12+S14+S15+S16+S17+S18+S9+S13 -> 85485.875
A20: Perkedel Jadi | B20: 72 | C20: HPP | D20: =D18/B20 -> 1936.3958 | F20: FOOD COST | G20: =H29 -> 0.57381414 | I20: =SUM(I7:I19) -> 160667.96
K21: FOOD COST | L21: =H29 -> 0.57381414 | M21: TOTAL | N21: =SUM(N7:N20) -> 0 | P21: Chicken Patty Jadi | Q21: 36 | S21: =S19/Q21 -> 2374.6076 | Y21: =SUM(V7:V20) -> 0
D22: PARAF | I22: PARAF | N22: PARAF | S22: PARAF
A29: BUAT BERAPA RESEP | B29: 2 | F29: FOOD COST PERIODE KEMARIN | H29: 0.57381414 | P29: BUAT BERAPA RESEP | Q29: 1
A32: TOLONG DIBACA SEBELUM MENGISI TO/TI | F32: RUMUS PERKEDEL | P32: RUMUS C. PATTY
A34: CATATAN : | F34: KENTANG MANUAL | G34: 2500 | H34: =G34*B29 -> 5000 | P34: DAGING / MENTOK
A35: 1. TO/TI PERKEDEL TINGGAL MENGISI MANUAL KOLOM | F35: DAGING AYAM/MENTOK | H35: =G35*B29 -> 0 | P35: PAHA BAWAH
A36: BUAT BERPA RESEP DAN PERKEDEL JADI . | F36: BATANG SLEDRI | G36: 50 | H36: =G36*B29 -> 100 | P36: DAGING GILING
A37: 2. TO/TI PERKEDEL KOLOM AYAM DI ISI MANUAL | F37: KUNING TELUR | G37: 2 | H37: =G37*B29 -> 4 | P37: ROTI TAWAR | Q37: 8 | R37: =Q37*Q29 -> 8
A38: 3. TO/TI FREE DIISI MANUAL | F38: BAWANG MERAH | G38: 20 | H38: =G38*B29 -> 40 | P38: SUSU ULTRA | Q38: 25 | R38: =Q38*Q29 -> 25
A39: 4. FOOD COST PERIODE KEMARIN DIISI DAN DISESUAIKAN | F39: BAWANG PUTIH | G39: 5 | H39: =G39*B29 -> 10 | P39: BAWANG BOMBAY | Q39: 50 | R39: =Q39*Q29 -> 50
A40: 5. TO/TI CATTERING STAFF DIISI MANUAL | F40: PREMIK PERKEDEL | H40: =G40*B29 -> 0 | P40: TELUR | Q40: 4 | R40: =Q40*Q29 -> 4
A41: 6. TO/TI CHICKEN PATTY DIISI MANUAL PAHA BAWAH ATAU | F41: VETSIN | G41: 10 | H41: =G41*B29 -> 20 | P41: MARGARIN | Q41: 10 | R41: =Q41*Q29 -> 10
A42: MENTOK YG DIGUNAKAN DAN BERAPA RESEP | F42: LADA | G42: 3 | H42: =G42*B29 -> 6 | P42: VETSIN | Q42: 30 | R42: =Q42*Q29 -> 30
A43: 7. TO/TI JUAL BARANG GUDANG DAN TO/TI FREE DIMASUKAN | F43: GARAM | G43: 5 | H43: =G43*B29 -> 10 | P43: LADA | Q43: 15 | R43: =Q43*Q29 -> 15
A44: MANUAL DI VENDOR | H44: =G44*B29 -> 0 | P44: GARAM | Q44: 18 | R44: =Q44*Q29 -> 18
A45: 8. KALO TIDAK BIKIN TO/TI PERKEDEL DAN CHCIKEN PATTY
A46: MAKA KOLOM BUAT BERAPA RESEP DI HAPUS SAJA
A59: 0

Sheet LPKK
A2: LAPORAN PENGELUARAN KAS KECIL
P4: CABANG : | Q4: SC MARABAHAN
P5: PERIODE : | Q5: 1-7 JULI 2026
A8: TGL | B8: NO | C8: BAHAN | D8: BAHAN | E8: BAHAN | F8: BAHAN | G8: BAHAN | H8: BAHAN | I8: MINYAK | J8: GROCERIES / | K8: BAHAN | L8: BAHAN | M8: TRANSPORT | N8: FOTO COPY / | O8: NO ACC | P8: LAIN - LAIN | S8: SALDO
B9: NOTA | C9: AYAM | D9: PELENGKAP | E9: ROTI | F9: ES | G9: MINUMAN | H9: PEMBUNGKUS | I9: GORENG | J9: BUMBU | K9: PERKEDEL | L9: PEMBERSIH | N9: ATK | P9: ( Rp ) | Q9: KETERANGAN | R9: JUMLAH
A10: 46204 | B10: 1 | D10: 84000 | Q10: FRENCH FRIES | R10: =SUM(C10:P10) -> 84000
B11: 2 | F11: 70000 | Q11: ES KRISTAL | R11: =SUM(C11:P11) -> 70000
B12: 3 | J12: 79500 | Q12: MIE TELUR, SAMSET | R12: =SUM(C12:P12) -> 79500
B13: 4 | J13: 4000 | Q13: TELUR | R13: =SUM(C13:P13) -> 4000
B14: 5 | E14: 4000 | J14: 12000 | K14: 10000 | Q14: SAYURAN | R14: =SUM(C14:P14) -> 26000
B15: 6 | P15: 260000 | Q15: GAS ELPIJI | R15: =SUM(C15:P15) -> 260000
B16: 7 | E16: 9000 | Q16: SELADA | R16: =SUM(C16:P16) -> 9000
B17: 8 | N17: 7000 | Q17: PRINT | R17: =SUM(C17:P17) -> 7000
B18: 9 | P18: 260000 | Q18: GAS ELPIJI | R18: =SUM(C18:P18) -> 260000
B19: 10 | E19: 10000 | F19: 100000 | H19: 20000 | J19: 31000 | Q19: GULA DLL | R19: =SUM(C19:P19) -> 161000
B20: 11 | P20: 203000 | Q20: TOKEN LISTRIK | R20: =SUM(C20:P20) -> 203000
B21: 12 | P21: 830500 | Q21: QRIS BRI | R21: =SUM(C21:P21) -> 830500
B22: 11 | R22: =SUM(C22:P22) -> 0
B23: 12 | R23: =SUM(C23:P23) -> 0
B24: 13 | R24: =SUM(C24:P24) -> 0
B25: 14 | R25: =SUM(C25:P25) -> 0
B26: 15 | R26: =SUM(C26:P26) -> 0
B27: 16 | R27: =SUM(C27:P27) -> 0
B28: 17 | R28: =SUM(C28:P28) -> 0
B29: 18 | R29: =SUM(C29:P29) -> 0
B30: 19 | R30: =SUM(C30:P30) -> 0
B31: 20 | R31: =SUM(C31:P31) -> 0
B32: 21 | R32: =SUM(C32:P32) -> 0
B33: 22 | R33: =SUM(C33:P33) -> 0
... B36: 25 | R36: =SUM(C36:P36) -> 0
A37: SUB TOTAL | C37: =SUM(C10:C36) -> 0 | D37: =SUM(D10:D36) -> 84000 | E37: =SUM(E10:E36) -> 23000 | F37: =SUM(F10:F36) -> 170000 | G37: =SUM(G10:G36) -> 0 | H37: =SUM(H10:H36) -> 20000 | I37: =SUM(I10:I36) -> 0 | J37: =SUM(J10:J36) -> 126500 | ... P37: =SUM(P10:P36) -> 1553500 | R37: =SUM(R10:R36) -> 1994000 | S37: =R37 -> 1994000
A38: 46205 | B38: 13 | E38: 15000 | J38: 16000 | K38: 10000 | Q38: SMSET,KEJU BATANG,LADA | R38: =SUM(C38:P38) -> 41000
B39: 14 | J39: 45000 | Q39: SAMSET | R39: =SUM(C39:P39) -> 45000
B40: 15 | D40: 64000 | Q40: RITI BURGER + SOSIS NASGOR | R40: =SUM(C40:P40) -> 64000
B41: 16 | E41: 20000 | Q41: ROTI TAWAR+SUSU | R41: =SUM(C41:P41) -> 20000
B42: 17 | F42: 100000 | Q42: GULA | R42: =SUM(C42:P42) -> 100000
B43: 18 | H43: 30000 | Q43: CUP SAMBAL | R43: =SUM(C43:P43) -> 30000
B44: 19 | P44: 117000 | Q44: APRON COOK+ CELEMEK KASIR | R44: =SUM(C44:P44) -> 117000
B45: 20 | J45: 21000 | K45: 5000 | Q45: SAYURAN | R45: =SUM(C45:P45) -> 26000
B46: 21 | M46: 500000 | Q46: ONGKIR BARGUD | R46: =SUM(C46:P46) -> 500000
B47: 22 | P47: 1042500 | Q47: QRIS BRI | R47: =SUM(C47:P47) -> 1042500
B48: 15 | R48: =SUM(C48:P48) -> 0
B49: 16 | R49: =SUM(C49:P49) -> 0
B50: 17 | R50: =SUM(C50:P50) -> 0
B51: 18 | R51: =SUM(C51:P51) -> 0
B52: 19 | R52: =SUM(C52:P52) -> 0
B53: 20 | R53: =SUM(C53:P53) -> 0
B54: 21 | R54: =SUM(C54:P54) -> 0
B55: 22 | R55: =SUM(C55:P55) -> 0
B56: 23 | R56: =SUM(C56:P56) -> 0
B57: 24 | R57: =SUM(C57:P57) -> 0
B58: 25 | R58: =SUM(C58:P58) -> 0
B59: 26 | R59: =SUM(C59:P59) -> 0
... B61: 28 | R61: =SUM(C61:P61) -> 0
A62: SUB TOTAL | C62: =SUM(C38:C61) -> 0 | D62: =SUM(D38:D61) -> 64000 | E62: =SUM(E38:E61) -> 35000 | F62: =SUM(F38:F61) -> 100000 | G62: =SUM(G38:G61) -> 0 | H62: =SUM(H38:H61) -> 30000 | I62: =SUM(I38:I61) -> 0 | J62: =SUM(J38:J61) -> 82000 | ... P62: =SUM(P38:P61) -> 1159500 | R62: =SUM(R38:R61) -> 1985500 | S62: =S37+R62 -> 3979500
A63: 46206 | B63: 23 | P63: 2468000 | Q63: NYICIL GROCERIES 25/6/26 | R63: =SUM(C63:P63) -> 2468000
B64: 24 | F64: 70000 | Q64: ES KRISTAL | R64: =SUM(C64:P64) -> 70000
B65: 25 | H65: 19500 | J65: 86100 | M65: 55400 | Q65: PEMBERSIH | R65: =SUM(C65:P65) -> 161000
B66: 26 | E66: 9000 | Q66: SELADA | R66: =SUM(C66:P66) -> 9000
B67: 27 | N67: 52000 | Q67: PRINT LAPORAN | R67: =SUM(C67:P67) -> 52000
B68: 28 | E68: 6000 | J68: 51000 | K68: 16000 | Q68: SAYURAN | R68: =SUM(C68:P68) -> 73000
B69: 29 | H69: 30000 | Q69: SEDOTAN | R69: =SUM(C69:P69) -> 30000
B70: 30 | H70: 50000 | Q70: COVER NASI | R70: =SUM(C70:P70) -> 50000
B71: 31 | K71: 131000 | Q71: SAYURAN | R71: =SUM(C71:P71) -> 131000
B72: 32 | G72: 178438 | Q72: LEMON TEA | R72: =SUM(C72:P72) -> 178438
B73: 33 | P73: 787000 | Q73: QRIS BRI | R73: =SUM(C73:P73) -> 787000
R74: =SUM(C74:P74) -> 0
R75: =SUM(C75:P75) -> 0
R76: =SUM(C76:P76) -> 0
R77: =SUM(C77:P77) -> 0
R78: =SUM(C78:P78) -> 0
R79: =SUM(C79:P79) -> 0
R80: =SUM(C80:P80) -> 0
R81: =SUM(C81:P81) -> 0
R82: =SUM(C82:P82) -> 0
R83: =SUM(C83:P83) -> 0
R84: =SUM(C84:P84) -> 0
R85: =SUM(C85:P85) -> 0
... R94: =SUM(C94:P94) -> 0
A95: SUB TOTAL | C95: =SUM(C63:C94) -> 0 | D95: =SUM(D63:D94) -> 0 | E95: =SUM(E63:E94) -> 15000 | F95: =SUM(F63:F94) -> 70000 | G95: =SUM(G63:G94) -> 178438 | H95: =SUM(H63:H94) -> 99500 | I95: =SUM(I63:I94) -> 0 | J95: =SUM(J63:J94) -> 137100 | ... P95: =SUM(P63:P94) -> 3255000 | R95: =SUM(R63:R94) -> 4009438 | S95: =S62+R95 -> 7988938
A96: 46207 | B96: 34 | M96: 9000 | Q96: ONGKIR LAPORAN | R96: =SUM(C96:P96) -> 9000
B97: 35 | F97: 87500 | Q97: GULA 5 KG | R97: =SUM(C97:P97) -> 87500
B98: 36 | F98: 262500 | Q98: GULA 10 KG | R98: =SUM(C98:P98) -> 262500
B99: 37 | J99: 36000 | Q99: SAMSET | R99: =SUM(C99:P99) -> 36000
B100: 38 | J100: 174000 | Q100: TOMSET | R100: =SUM(C100:P100) -> 174000
B101: 39 | J101: 58000 | Q101: TOMSET | R101: =SUM(C101:P101) -> 58000
B102: 40 | P102: 25000 | Q102: SAPU LANTAI | R102: =SUM(C102:P102) -> 25000
B103: 41 | P103: 520000 | Q103: GAS ELPIJI | R103: =SUM(C103:P103) -> 520000
B104: 42 | H104: 15000 | J104: 32000 | Q104: TELOR, P.KLIP DLL | R104: =SUM(C104:P104) -> 47000
B105: 43 | P105: 663000 | Q105: MIKAS | R105: =SUM(C105:P105) -> 663000
B106: 44 | P106: 607000 | Q106: QRIS BRI | R106: =SUM(C106:P106) -> 607000
B107: 18 | R107: =SUM(C107:P107) -> 0
B108: 19 | R108: =SUM(C108:P108) -> 0
B109: 20 | R109: =SUM(C109:P109) -> 0
B110: 21 | R110: =SUM(C110:P110) -> 0
B111: 22 | R111: =SUM(C111:P111) -> 0
B112: 23 | R112: =SUM(C112:P112) -> 0
B113: 24 | R113: =SUM(C113:P113) -> 0
B114: 25 | R114: =SUM(C114:P114) -> 0
B115: 26 | R115: =SUM(C115:P115) -> 0
...

Sheet VENDOR
M2: VENDOR REPORT | AI2: CABANG : | AJ2: =LPKK!Q4 -> SC MARABAHAN
AI3: PERIODE : | AJ3: =LPKK!Q5 -> 1-7 JULI 2026 | AQ3: PENCATATAN PEMBELIAN AYAM KREDIT
B5: TGL FAKTUR | C5: NO | E5: PEMAKAIAN | G5: PERSEDIAAN | I5: 46204 | K5: 46205 | M5: 46206 | O5: 46207 | Q5: 46208 | S5: 46209 | U5: 46210 | AC5: KHUSUS TO/TI ( - ) | AE5: KREDIT BARGUD | AG5: KREDIT BAHAN BAKU | AI5: TOTAL | AK5: PERSEDIAAN | AM5: PEMAKAIAN
D6: KETERANGAN BAHAN | E6: MINGGU LALU | G6: AWAL | AC6: C.PATTY/CATTERING STAFF( - ) | AI6: PEMBELIAN | AK6: AKHIR | AM6: MINGGU INI | AP6: TGL FAKTUR | AQ6: 44947
B7: HARI | E7: DLM SATUAN | G7: DLM SATUAN | I7: RABU | K7: KAMIS | M7: JUM'AT | O7: SABTU | Q7: MINGGU | S7: SENIN | U7: SELASA | AC7: PERKEDEL/BARGUD | AG7: AYAM DLL | AI7: DLM SATUAN | AK7: DLM SATUAN | AM7: DLM SATUAN | AP7: HARI | AQ7: SABTU
E8: Rp | F8: Unit | G8: Rp | H8: Unit | I8: Rp | J8: Unit | K8: Rp | L8: Unit | M8: Rp | N8: Unit | O8: Rp | P8: Unit | Q8: Rp | R8: Unit | S8: Rp | T8: Unit | U8: Rp | V8: Unit | W8: Rp | X8: Unit | Y8: Rp | Z8: Unit | AA8: Rp | AB8: Unit | AC8: Rp | AD8: Unit | AE8: Rp | AF8: Unit | AG8: Rp | AH8: Unit | AI8: Rp | AJ8: Unit | AK8: Rp | AL8: Unit | AM8: Rp | AN8: Unit | AQ8: RP. | AR8: UNIT | AS8: RP. | AT8: UNIT | AU8: RP. | AV8: UNIT | AW8: RP. | AX8: UNIT | AY8: RP. | AZ8: UNIT | BA8: RP. | BB8: UNIT | BC8: RP. | BD8: UNIT
D9: AYAM | AG9: =SUM(AG10,AG11,AG12,AG13,AG14,AG16)+AG18+AG20 -> 7109010 | AP9: AYAM | AQ9: =SUM(AQ10:AQ15) -> 0 | AS9: =SUM(AS10:AS14) -> 0 | AU9: =SUM(AU10:AU14) -> 0 | AW9: =SUM(AW10:AW14) -> 0 | AY9: =SUM(AY10:AY14) -> 0 | BA9: =SUM(BA10:BA14) -> 0 | BC9: =SUM(BC10:BC14) -> 0
C10: 1 | D10: =WEEKLY!B11 -> DADA MENTOK | E10: 730095.93 | F10: 136.8 | G10: 185867.5 | H10: 35 | AC10: =-('TO-TI'!S7+'TO-TI'!D8) -> -78609.375 | AD10: =-('TO-TI'!Q7+'TO-TI'!B8) -> -15 | AG10: ='PEMBELIAN KREDIT'!H32 -> 445453.12 | AH10: ='PEMBELIAN KREDIT'!I32 -> 85 | AI10: =SUM(I10,K10,M10,O10,Q10,S10,U10,W10,Y10,AA10,AC10,AE10,AG10) -> 366843.75 | AJ10: =SUM(J10,L10,N10,P10,R10,T10,V10,X10,Z10,AB10,AD10,AF10,AH10) -> 70 | AK10: =WEEKLY!F11 -> 178181.25 | AL10: =WEEKLY!D11 -> 34 | AM10: =G10+AI10-AK10 -> 374530 | AN10: =H10+AJ10-AL10 -> 71 | AO10: =AM10-E10 -> -355565.93 | AP10: DADA MENTOK
C11: 2 | D11: =WEEKLY!B12 -> DADA | E11: 1471060 | F11: 229 | G11: 379905 | H11: 60 | AC11: =-('TO-TI'!N7+'TO-TI'!I7) -> -120500.97 | AD11: =-('TO-TI'!L7+'TO-TI'!G7) -> -14 | AG11: ='PEMBELIAN KREDIT'!H33 -> 1062234.4 | AH11: ='PEMBELIAN KREDIT'!I33 -> 170 | AI11: =SUM(I11,K11,M11,O11,Q11,S11,U11,W11,Y11,AA11,AC11,AE11,AG11) -> 941733.41 | AJ11: =SUM(J11,L11,N11,P11,R11,T11,V11,X11,Z11,AB11,AD11,AF11,AH11) -> 156 | AK11: =WEEKLY!F12 -> 318670.31 | AL11: =WEEKLY!D12 -> 51 | AM11: =G11+AI11-AK11 -> 1002968.1 | AN11: =H11+AJ11-AL11 -> 165 | AO11: =AM11-E11 -> -468091.89 | AP11: DADA
C12: 3 | D12: =WEEKLY!B13 -> PAHA ATAS | E12: 1638816 | F12: 240 | G12: 300656 | H12: 46 | AC12: =-('TO-TI'!N8+'TO-TI'!I8) -> 0 | AD12: =-('TO-TI'!L8+'TO-TI'!G8) -> 0 | AG12: ='PEMBELIAN KREDIT'!H34 -> 1096500 | AH12: ='PEMBELIAN KREDIT'!I34 -> 170 | AI12: =SUM(I12,K12,M12,O12,Q12,S12,U12,W12,Y12,AA12,AC12,AE12,AG12) -> 1096500 | AJ12: =SUM(J12,L12,N12,P12,R12,T12,V12,X12,Z12,AB12,AD12,AF12,AH12) -> 170 | AK12: =WEEKLY!F13 -> 380550 | AL12: =WEEKLY!D13 -> 59 | AM12: =G12+AI12-AK12 -> 1016606 | AN12: =H12+AJ12-AL12 -> 157 | AO12: =AM12-E12 -> -622210 | AP12: PAHA ATAS
C13: 4 | D13: =WEEKLY!B14 -> PAHA BAWAH | E13: 2222090.6 | F13: 496 | G13: 540241.25 | H13: 115 | AC13: =-('TO-TI'!N9+'TO-TI'!I9) -> 0 | AD13: =-('TO-TI'!L9+'TO-TI'!G9) -> 0 | AG13: ='PEMBELIAN KREDIT'!H35+'PEMBELIAN KREDIT'!H39 -> 1080709.4 | AH13: ='PEMBELIAN KREDIT'!I35+'PEMBELIAN KREDIT'!I39 -> 240 | AI13: =SUM(I13,K13,M13,O13,Q13,S13,U13,W13,Y13,AA13,AC13,AE13,AG13) -> 1080709.4 | AJ13: =SUM(J13,L13,N13,P13,R13,T13,V13,X13,Z13,AB13,AD13,AF13,AH13) -> 240 | AK13: =WEEKLY!F14 -> 593400 | AL13: =WEEKLY!D14 -> 128 | AM13: =G13+AI13-AK13 -> 1027550.6 | AN13: =H13+AJ13-AL13 -> 227 | AO13: =AM13-E13 -> -1194540 | AP13: PAHA BAWAH
B14: A | C14: 5 | D14: =WEEKLY!B15 -> SAYAP | E14: 2370220.6 | F14: 674 | G14: 784932.75 | H14: 183 | AC14: =-('TO-TI'!N10+'TO-TI'!I10) -> 0 | AD14: =-('TO-TI'!L10+'TO-TI'!G10) -> 0 | AG14: ='PEMBELIAN KREDIT'!H36+'PEMBELIAN KREDIT'!H37 -> 924888.12 | AH14: ='PEMBELIAN KREDIT'!I36+'PEMBELIAN KREDIT'!I37 -> 240 | AI14: =SUM(I14,K14,M14,O14,Q14,S14,U14,W14,Y14,AA14,AC14,AE14,AG14) -> 924888.12 | AJ14: =SUM(J14,L14,N14,P14,R14,T14,V14,X14,Z14,AB14,AD14,AF14,AH14) -> 240 | AK14: =WEEKLY!F15 -> 576642.5 | AL14: =WEEKLY!D15 -> 136 | AM14: =G14+AI14-AK14 -> 1133178.4 | AN14: =H14+AJ14-AL14 -> 287 | AO14: =AM14-E14 -> -1237042.2 | AP14: SAYAP
B15: Y | C15: 6 | D15: =WEEKLY!B16 -> CHICKEN PATTY | E15: 134783.75 | F15: 49 | G15: 46761.708 | H15: 17 | AC15: ='TO-TI'!S19 -> 85485.875 | AD15: ='TO-TI'!Q21 -> 36 | AI15: =SUM(I15,K15,M15,O15,Q15,S15,U15,W15,Y15,AA15,AC15,AE15,AG15) -> 85485.875 | AJ15: =SUM(J15,L15,N15,P15,R15,T15,V15,X15,Z15,AB15,AD15,AF15,AH15) -> 36 | AK15: =WEEKLY!F16 -> 52241.368 | AL15: =WEEKLY!D16 -> 22 | AM15: =G15+AI15-AK15 -> 80006.214 | AN15: =H15+AJ15-AL15 -> 31 | AO15: =AM15-E15 -> -54777.531 | AP15: MARINADE
B16: A | C16: 7 | D16: =WEEKLY!B17 -> AYAM WHOLE | E16: 3327750 | F16: 135 | G16: 1084600 | H16: 44 | AG16: ='PEMBELIAN KREDIT'!H41 -> 1925600 | AH16: ='PEMBELIAN KREDIT'!I41 -> 80 | AI16: =SUM(I16,K16,M16,O16,Q16,S16,U16,W16,Y16,AA16,AC16,AE16,AG16) -> 1925600 | AJ16: =SUM(J16,L16,N16,P16,R16,T16,V16,X16,Z16,AB16,AD16,AF16,AH16) -> 80 | AK16: =WEEKLY!F17 -> 625820 | AL16: =WEEKLY!D17 -> 26 | AM16: =G16+AI16-AK16 -> 2384380 | AN16: =H16+AJ16-AL16 -> 98
B17: M | C17: 8 | D17: =WEEKLY!B18 -> SAYAP FULL | E17: 0 | F17: 0 | G17: 0 | H17: 0 | AI17: =SUM(I17,K17,M17,O17,Q17,S17,U17,W17,Y17,AA17,AC17,AE17,AG17) -> 0 | AJ17: =SUM(J17,L17,N17,P17,R17,T17,V17,X17,Z17,AB17,AD17,AF17,AH17) -> 0 | AK17: =WEEKLY!F18 -> 0 | AL17: =WEEKLY!D18 -> 0 | AM17: =G17+AI17-AK17 -> 0 | AN17: =H17+AJ17-AL17 -> 0
C18: 9 | D18: =WEEKLY!B19 -> KULIT | E18: 612675 | F18: 17.35 | G18: 351450 | H18: 9.9 | AG18: ='PEMBELIAN KREDIT'!H38 -> 369250 | AH18: ='PEMBELIAN KREDIT'!I38 -> 10.55 | AI18: =SUM(I18,K18,M18,O18,Q18,S18,U18,W18,Y18,AA18,AC18,AE18,AG18) -> 369250 | AJ18: =SUM(J18,L18,N18,P18,R18,T18,V18,X18,Z18,AB18,AD18,AF18,AH18) -> 10.55 | AK18: =WEEKLY!F19 -> 266250 | AL18: =WEEKLY!D19 -> 7.5 | AM18: =G18+AI18-AK18 -> 454450 | AN18: =H18+AJ18-AL18 -> 12.95
C19: 10 | D19: =WEEKLY!B20 -> PAHA BAWAH FULL | E19: 0 | F19: 0 | G19: 0 | H19: 0 | AI19: =SUM(I19,K19,M19,O19,Q19,S19,U19,W19,Y19,AA19,AC19,AE19,AG19) -> 0 | AJ19: =SUM(J19,L19,N19,P19,R19,T19,V19,X19,Z19,AB19,AD19,AF19,AH19) -> 0 | AK19: =WEEKLY!F20 -> 0 | AL19: =WEEKLY!D20 -> 0 | AM19: =G19+AI19-AK19 -> 0 | AN19: =H19+AJ19-AL19 -> 0
C20: 11 | D20: =WEEKLY!B21 -> CUT 10 | E20: 326780 | F20: 80 | G20: 1076920 | H20: 260 | AG20: ='PEMBELIAN KREDIT'!H40 -> 204375 | AH20: ='PEMBELIAN KREDIT'!I40 -> 50 | AI20: =SUM(I20,K20,M20,O20,Q20,S20,U20,W20,Y20,AA20,AC20,AE20,AG20) -> 204375 | AJ20: =SUM(J20,L20,N20,P20,R20,T20,V20,X20,Z20,AB20,AD20,AF20,AH20) -> 50 | AK20: =WEEKLY!F21 -> 994080 | AL20: =WEEKLY!D21 -> 240 | AM20: =G20+AI20-AK20 -> 287215 | AN20: =H20+AJ20-AL20 -> 70
C21: 12 | D21: =WEEKLY!B22 -> 0 | E21: 0 | F21: 0 | G21: 0 | H21: 0 | AI21: =SUM(I21,K21,M21,O21,Q21,S21,U21,W21,Y21,AA21,AC21,AE21,AG21) -> 0 | AJ21: =SUM(J21,L21,N21,P21,R21,T21,V21,X21,Z21,AB21,AD21,AF21,AH21) -> 0 | AK21: =WEEKLY!F22 -> 0 | AL21: =WEEKLY!D22 -> 0 | AM21: =G21+AI21-AK21 -> 0 | AN21: =H21+AJ21-AL21 -> 0
C22: 13 | D22: =WEEKLY!B23 -> 0 | E22: 0 | F22: 0 | G22: 0 | H22: 0 | AI22: =SUM(I22,K22,M22,O22,Q22,S22,U22,W22,Y22,AA22,AC22,AE22,AG22) -> 0 | AJ22: =SUM(J22,L22,N22,P22,R22,T22,V22,X22,Z22,AB22,AD22,AF22,AH22) -> 0 | AK22: =WEEKLY!F23 -> 0 | AL22: =WEEKLY!D23 -> 0 | AM22: =G22+AI22-AK22 -> 0 | AN22: =H22+AJ22-AL22 -> 0
C23: 14 | D23: =WEEKLY!B24 -> 0 | E23: 0 | F23: 0 | G23: 0 | H23: 0 | AI23: =SUM(I23,K23,M23,O23,Q23,S23,U23,W23,Y23,AA23,AC23,AE23,AG23) -> 0 | AJ23: =SUM(J23,L23,N23,P23,R23,T23,V23,X23,Z23,AB23,AD23,AF23,AH23) -> 0 | AK23: =WEEKLY!F24 -> 0 | AL23: =WEEKLY!D24 -> 0 | AM23: =G23+AI23-AK23 -> 0 | AN23: =H23+AJ23-AL23 -> 0 | AO23: AYAM | AP23: =SUM(AM10:AM23) -> 7760884.3
C24: 1 | D24: =WEEKLY!B27 -> VEGETABLE MIX | E24: 11200 | F24: 0.32 | G24: 35000 | H24: 1 | AI24: =SUM(I24,K24,M24,O24,Q24,S24,U24,W24,Y24,AA24,AC24,AE24,AG24) -> 0 | AJ24: =SUM(J24,L24,N24,P24,R24,T24,V24,X24,Z24,AB24,AD24,AF24,AH24) -> 0 | AK24: =WEEKLY!F27 -> 21000 | AL24: =WEEKLY!D27 -> 0.6 | AM24: =G24+AI24-AK24 -> 14000 | AN24: =H24+AJ24-AL24 -> 0.4 | AO24: =AM24-E24 -> 2800
B25: P | C25: 2 | D25: =WEEKLY!B28 -> BERAS | E25: 2197408.2 | F25: 137.53333 | G25: 2135000 | H25: 122 | AC25: =-('TO-TI'!N11+'TO-TI'!I11) -> -40166.99 | AD25: =-('TO-TI'!L11+'TO-TI'!G11)/15 -> -0.93333333 | AG25: ='PEMBELIAN KREDIT'!G13 -> 2905000 | AH25: 175 | AI25: =SUM(I25,K25,M25,O25,Q25,S25,U25,W25,Y25,AA25,AC25,AE25,AG25) -> 2864833 | AJ25: =SUM(J25,L25,N25,P25,R25,T25,V25,X25,Z25,AB25,AD25,AF25,AH25) -> 174.06667 | AK25: =WEEKLY!F28 -> 3885000 | AL25: =WEEKLY!D28 -> 222 | AM25: =G25+AI25-AK25 -> 1114833 | AN25: =H25+AJ25-AL25 -> 74.066667 | AO25: =AM25-E25 -> -1082575.2
B26: E | C26: 3 | D26: =WEEKLY!B29 -> FRENCH FRIES | E26: 105000 | F26: 2.3 | G26: 30000 | H26: 1 | I26: 84000 | J26: 2 | AI26: =SUM(I26,K26,M26,O26,Q26,S26,U26,W26,Y26,AA26,AC26,AE26,AG26) -> 84000 | AJ26: =SUM(J26,L26,N26,P26,R26,T26,V26,X26,Z26,AB26,AD26,AF26,AH26) -> 2 | AK26: =WEEKLY!F29 -> 12000 | AL26: =WEEKLY!D29 -> 0.4 | AM26: =G26+AI26-AK26 -> 102000 | AN26: =H26+AJ26-AL26 -> 2.6 | AO26: =AM26-E26 -> -3000
B27: L | C27: 4 | D27: =WEEKLY!B30 -> ROTI BURGER | E27: 141833 | F27: 49 | G27: 28330 | H27: 10 | K27: 34000 | L27: 12 | Q27: 36000 | R27: 12 | AI27: =SUM(I27,K27,M27,O27,Q27,S27,U27,W27,Y27,AA27,AC27,AE27,AG27) -> 70000 | AJ27: =SUM(J27,L27,N27,P27,R27,T27,V27,X27,Z27,AB27,AD27,AF27,AH27) -> 24 | AK27: =WEEKLY!F30 -> 8499 | AL27: =WEEKLY!D30 -> 3 | AM27: =G27+AI27-AK27 -> 89831 | AN27: =H27+AJ27-AL27 -> 31 | AO27: =AM27-E27 -> -52002
B28: E | C28: 5 | D28: =WEEKLY!B31 -> SOSIS | E28: 5200 | F28: 4 | G28: 18200 | H28: 14 | AI28: =SUM(I28,K28,M28,O28,Q28,S28,U28,W28,Y28,AA28,AC28,AE28,AG28) -> 0 | AJ28: =SUM(J28,L28,N28,P28,R28,T28,V28,X28,Z28,AB28,AD28,AF28,AH28) -> 0 | AK28: =WEEKLY!F31 -> 13000 | AL28: =WEEKLY!D31 -> 10 | AM28: =G28+AI28-AK28 -> 5200 | AN28: =H28+AJ28-AL28 -> 4 | AO28: =AM28-E28 -> 0
B29: N | C29: 6 | D29: =WEEKLY!B32 -> PERKEDEL | E29: 101905.72 | F29: 47 | G29: 84308.161 | H29: 34 | AC29: ='TO-TI'!D18 -> 139420.5 | AD29: ='TO-TI'!B20 -> 72 | AI29: =SUM(I29,K29,M29,O29,Q29,S29,U29,W29,Y29,AA29,AC29,AE29,AG29) -> 139420.5 | AJ29: =SUM(J29,L29,N29,P29,R29,T29,V29,X29,Z29,AB29,AD29,AF29,AH29) -> 72 | AK29: =WEEKLY!F32 -> 109104.68 | AL29: =WEEKLY!D32 -> 44 | AM29: =G29+AI29-AK29 -> 114623.98 | AN29: =H29+AJ29-AL29 -> 62 | AO29: =AM29-E29 -> 12718.259
B30: G | C30: 7 | D30: =WEEKLY!B33 -> SOSIS NASGOR | E30: -12650 | F30: -11 | G30: 12650 | H30: 11 | K30: 30000 | L30: 35 | AI30: =SUM(I30,K30,M30,O30,Q30,S30,U30,W30,Y30,AA30,AC30,AE30,AG30) -> 30000 | AJ30: =SUM(J30,L30,N30,P30,R30,T30,V30,X30,Z30,AB30,AD30,AF30,AH30) -> 35 | AK30: =WEEKLY!F33 -> 10350 | AL30: =WEEKLY!D33 -> 9 | AM30: =G30+AI30-AK30 -> 32300 | AN30: =H30+AJ30-AL30 -> 37 | AO30: =AM30-E30 -> 44950
B31: K | C31: 8 | D31: =WEEKLY!B34 -> NUGGET COIN | E31: 30400 | F31: 4 | G31: 28800 | H31: 48 | AI31: =SUM(I31,K31,M31,O31,Q31,S31,U31,W31,Y31,AA31,AC31,AE31,AG31) -> 0 | AJ31: =SUM(J31,L31,N31,P31,R31,T31,V31,X31,Z31,AB31,AD31,AF31,AH31) -> 0 | AK31: =WEEKLY!F34 -> 28800 | AL31: =WEEKLY!D34 -> 48 | AM31: =G31+AI31-AK31 -> 0 | AN31: =H31+AJ31-AL31 -> 0 | AO31: =AM31-E31 -> -30400
B32: A | C32: 9 | D32: =WEEKLY!B35 -> BAKSO | E32: 8320 | F32: 13 | G32: 2560 | H32: 4 | AI32: =SUM(I32,K32,M32,O32,Q32,S32,U32,W32,Y32,AA32,AC32,AE32,AG32) -> 0 | AJ32: =SUM(J32,L32,N32,P32,R32,T32,V32,X32,Z32,AB32,AD32,AF32,AH32) -> 0 | AK32: =WEEKLY!F35 -> 2560 | AL32: =WEEKLY!D35 -> 4 | AM32: =G32+AI32-AK32 -> 0 | AN32: =H32+AJ32-AL32 -> 0 | AO32: =AM32-E32 -> -8320
B33: P | C33: 10 | D33: =WEEKLY!B36 -> 0 | E33: 0 | F33: 0 | G33: 0 | H33: 0 | AI33: =SUM(I33,K33,M33,O33,Q33,S33,U33,W33,Y33,AA33,AC33,AE33,AG33) -> 0 | AJ33: =SUM(J33,L33,N33,P33,R33,T33,V33,X33,Z33,AB33,AD33,AF33,AH33) -> 0 | AK33: =WEEKLY!F36 -> 0 | AL33: =WEEKLY!D36 -> 0 | AM33: =G33+AI33-AK33 -> 0 | AN33: =H33+AJ33-AL33 -> 0 | AO33: =AM33-E33 -> 0
C34: 11 | D34: =WEEKLY!B37 -> 0 | E34: 0 | F34: 0 | G34: 0 | H34: 0 | AI34: =SUM(I34,K34,M34,O34,Q34,S34,U34,W34,Y34,AA34,AC34,AE34,AG34) -> 0 | AJ34: =SUM(J34,L34,N34,P34,R34,T34,V34,X34,Z34,AB34,AD34,AF34,AH34) -> 0 | AK34: =WEEKLY!F37 -> 0 | AL34: =WEEKLY!D37 -> 0 | AM34: =G34+AI34-AK34 -> 0 | AN34: =H34+AJ34-AL34 -> 0 | AO34: =AM34-E34 -> 0
C35: 12 | D35: =WEEKLY!B38 -> 0 | E35: 0 | F35: 0 | G35: 0 | H35: 0 | AI35: =SUM(I35,K35,M35,O35,Q35,S35,U35,W35,Y35,AA35,AC35,AE35,AG35) -> 0 | AJ35: =SUM(J35,L35,N35,P35,R35,T35,V35,X35,Z35,AB35,AD35,AF35,AH35) -> 0 | AK35: =WEEKLY!F38 -> 0 | AL35: =WEEKLY!D38 -> 0 | AM35: =G35+AI35-AK35 -> 0 | AN35: =H35+AJ35-AL35 -> 0 | AO35: =AM35-E35 -> 0
C36: 13 | D36: BAHAN ROTI | E36: 43182.933 | F36: 0 | G36: 109802.13 | I36: 23000 | K36: 35000 | M36: 15000 | U36: 26900 | AC36: =-('TO-TI'!S10+'TO-TI'!S11+'TO-TI'!S12+'TO-TI'!S14) -> -3950 | AI36: =SUM(I36,K36,M36,O36,Q36,S36,U36,W36,Y36,AA36,AC36,AE36,AG36) -> 95950 | AJ36: =SUM(J36,L36,N36,P36,R36,T36,V36,X36,Z36,AB36,AD36,AF36,AH36) -> 0 | AK36: =WEEKLY!I54 -> 70828.533 | AM36: =G36+AI36-AK36 -> 134923.6 | AN36: =H36+AJ36-AL36 -> 0 | AO36: =AM36-E36 -> 91740.667
C37: 14 | E37: 0 | F37: 0 | AI37: =SUM(I37,K37,M37,O37,Q37,S37,U37,W37,Y37,AA37,AC37,AE37,AG37) -> 0 | AJ37: =SUM(J37,L37,N37,P37,R37,T37,V37,X37,Z37,AB37,AD37,AF37,AH37) -> 0 | AM37: =G37+AI37-AK37 -> 0 | AN37: =H37+AJ37-AL37 -> 0 | AO37: PELENGKAP | AP37: =SUM(AM24:AM37) -> 1607711.6
B38: BA | C38: 1 | D38: =WEEKLY!B57 -> GULA PASIR | E38: 748000 | F38: 0 | G38: 0 | H38: 0 | I38: 100000 | K38: 100000 | O38: 350000 | U38: 262500 | AI38: =SUM(I38,K38,M38,O38,Q38,S38,U38,W38,Y38,AA38,AC38,AE38,AG38) -> 812500 | AJ38: =SUM(J38,L38,N38,P38,R38,T38,V38,X38,Z38,AB38,AD38,AF38,AH38) -> 0 | AK38: =WEEKLY!F57 -> 0 | AL38: =WEEKLY!D57 -> 0 | AM38: =G38+AI38-AK38 -> 812500 | AN38: =H38+AJ38-AL38 -> 0 | AO38: =AM38-E38 -> 64500
B39: HA | C39: 2 | D39: =WEEKLY!B58 -> 0 | E39: 0 | F39: 0 | G39: 0 | H39: 0 | AI39: =SUM(I39,K39,M39,O39,Q39,S39,U39,W39,Y39,AA39,AC39,AE39,AG39) -> 0 | AJ39: =SUM(J39,L39,N39,P39,R39,T39,V39,X39,Z39,AB39,AD39,AF39,AH39) -> 0 | AK39: =WEEKLY!F58 -> 0 | AL39: =WEEKLY!D58 -> 0 | AM39: =G39+AI39-AK39 -> 0 | AN39: =H39+AJ39-AL39 -> 0
B40: N | C40: 3 | D40: =WEEKLY!B59 -> ICE CREAM EMBER | E40: 0 | F40: 0 | G40: 0 | H40: 0 | AI40: =SUM(I40,K40,M40,O40,Q40,S40,U40,W40,Y40,AA40,AC40,AE40,AG40) -> 0 | AJ40: =SUM(J40,L40,N40,P40,R40,T40,V40,X40,Z40,AB40,AD40,AF40,AH40) -> 0 | AK40: =WEEKLY!F59 -> 13750 | AL40: =WEEKLY!D59 -> 0.5 | AM40: =G40+AI40-AK40 -> -13750 | AN40: =H40+AJ40-AL40 -> -0.5
B41: ES | C41: 4 | D41: BAHAN ES | E41: 568868.42 | F41: 0 | G41: 102631.58 | I41: 70000 | M41: 70000 | Q41: 70000 | S41: 45000 | U41: 24000 | AI41: =SUM(I41,K41,M41,O41,Q41,S41,U41,W41,Y41,AA41,AC41,AE41,AG41) -> 279000 | AJ41: =SUM(J41,L41,N41,P41,R41,T41,V41,X41,Z41,AB41,AD41,AF41,AH41) -> 0 | AK41: =WEEKLY!I69 -> 534133.33 | AM41: =G41+AI41-AK41 -> -152501.75 | AN41: =H41+AJ41-AL41 -> 0 | AO41: DESSERT | AP41: =SUM(AM38:AM41) -> 646248.25
C43: 1 | D43: =WEEKLY!B76 -> TEH BOTOL SOSRO (TBS) | E43: 75000 | F43: 30 | G43: 72500 | H43: 29 | AI43: =SUM(I43,K43,M43,O43,Q43,S43,U43,W43,Y43,AA43,AC43,AE43,AG43) -> 0 | AJ43: =SUM(J43,L43,N43,P43,R43,T43,V43,X43,Z43,AB43,AD43,AF43,AH43) -> 0 | AK43: =WEEKLY!F76 -> 37500 | AL43: =WEEKLY!D76 -> 15 | AM43: =G43+AI43-AK43 -> 35000 | AN43: =H43+AJ43-AL43 -> 14 | AO43: =AM43-E43 -> -40000
C44: 2 | D44: =WEEKLY!B77 -> TEH SOSRO POUCH (TBO) | E44: 32500 | F44: 13 | G44: 145000 | H44: 58 | AI44: =SUM(I44,K44,M44,O44,Q44,S44,U44,W44,Y44,AA44,AC44,AE44,AG44) -> 0 | AJ44: =SUM(J44,L44,N44,P44,R44,T44,V44,X44,Z44,AB44,AD44,AF44,AH44) -> 0 | AK44: =WEEKLY!F77 -> 137500 | AL44: =WEEKLY!D77 -> 55 | AM44: =G44+AI44-AK44 -> 7500 | AN44: =H44+AJ44-AL44 -> 3 | AO44: =AM44-E44 -> -25000
C45: 3 | D45: =WEEKLY!B78 -> 0 | E45: 0 | F45: 0 | G45: 0 | H45: 0 | AI45: =SUM(I45,K45,M45,O45,Q45,S45,U45,W45,Y45,AA45,AC45,AE45,AG45) -> 0 | AJ45: =SUM(J45,L45,N45,P45,R45,T45,V45,X45,Z45,AB45,AD45,AF45,AH45) -> 0 | AK45: =WEEKLY!F78 -> 0 | AL45: =WEEKLY!D78 -> 0 | AM45: =G45+AI45-AK45 -> 0 | AN45: =H45+AJ45-AL45 -> 0 | AO45: =AM45-E45 -> 0
C46: 4 | D46: =WEEKLY!B79 -> S-TEE | E46: 0 | F46: 0 | G46: 0 | H46: 0 | AI46: =SUM(I46,K46,M46,O46,Q46,S46,U46,W46,Y46,AA46,AC46,AE46,AG46) -> 0 | AJ46: =SUM(J46,L46,N46,P46,R46,T46,V46,X46,Z46,AB46,AD46,AF46,AH46) -> 0 | AK46: =WEEKLY!F79 -> 0 | AL46: =WEEKLY!D79 -> 0 | AM46: =G46+AI46-AK46 -> 0 | AN46: =H46+AJ46-AL46 -> 0 | AO46: =AM46-E46 -> 0
C47: 5 | D47: =WEEKLY!B80 -> 0 | E47: 0 | F47: 0 | G47: 0 | H47: 0 | AI47: =SUM(I47,K47,M47,O47,Q47,S47,U47,W47,Y47,AA47,AC47,AE47,AG47) -> 0 | AJ47: =SUM(J47,L47,N47,P47,R47,T47,V47,X47,Z47,AB47,AD47,AF47,AH47) -> 0 | AK47: =WEEKLY!F80 -> 0 | AL47: =WEEKLY!D80 -> 0 | AM47: =G47+AI47-AK47 -> 0 | AN47: =H47+AJ47-AL47 -> 0 | AO47: =AM47-E47 -> 0
C48: 6 | D48: =WEEKLY!B81 -> AIR MINERAL BOTOL (AMB) | E48: 21000 | F48: 12 | G48: 89250 | H48: 51 | AI48: =SUM(I48,K48,M48,O48,Q48,S48,U48,W48,Y48,AA48,AC48,AE48,AG48) -> 0 | AJ48: =SUM(J48,L48,N48,P48,R48,T48,V48,X48,Z48,AB48,AD48,AF48,AH48) -> 0 | AK48: =WEEKLY!F81 -> 50750 | AL48: =WEEKLY!D81 -> 29 | AM48: =G48+AI48-AK48 -> 38500 | AN48: =H48+AJ48-AL48 -> 22 | AO48: =AM48-E48 -> 17500
C49: 7 | D49: =WEEKLY!B82 -> AIR MINERAL CUP (AMC) | E49: 118800 | F49: 30 | G49: 0 | H49: 0 | AI49: =SUM(I49,K49,M49,O49,Q49,S49,U49,W49,Y49,AA49,AC49,AE49,AG49) -> 0 | AJ49: =SUM(J49,L49,N49,P49,R49,T49,V49,X49,Z49,AB49,AD49,AF49,AH49) -> 0 | AK49: =WEEKLY!F82 -> 0 | AL49: =WEEKLY!D82 -> 0 | AM49: =G49+AI49-AK49 -> 0 | AN49: =H49+AJ49-AL49 -> 0 | AO49: =AM49-E49 -> -118800
C50: 8 | D50: =WEEKLY!B83 -> MILO | E50: 137093 | F50: 1.03 | G50: 155727 | H50: 1.17 | AI50: =SUM(I50,K50,M50,O50,Q50,S50,U50,W50,Y50,AA50,AC50,AE50,AG50) -> 0 | AJ50: =SUM(J50,L50,N50,P50,R50,T50,V50,X50,Z50,AB50,AD50,AF50,AH50) -> 0 | AK50: =WEEKLY!F83 -> 57233 | AL50: =WEEKLY!D83 -> 0.43 | AM50: =G50+AI50-AK50 -> 98494 | AN50: =H50+AJ50-AL50 -> 0.74 | AO50: =AM50-E50 -> -38599
B51: M | C51: 9 | D51: =WEEKLY!B84 -> NESTEA | E51: 25121.25 | F51: 0.29 | G51: 0 | H51: 0 | M51: 178438 | N51: 2 | AI51: =SUM(I51,K51,M51,O51,Q51,S51,U51,W51,Y51,AA51,AC51,AE51,AG51) -> 178438 | AJ51: =SUM(J51,L51,N51,P51,R51,T51,V51,X51,Z51,AB51,AD51,AF51,AH51) -> 2 | AK51: =WEEKLY!F84 -> 142065 | AL51: =WEEKLY!D84 -> 1.64 | AM51: =G51+AI51-AK51 -> 36373 | AN51: =H51+AJ51-AL51 -> 0.36 | AO51: =AM51-E51 -> 11251.75
B52: I | C52: 10 | D52: =WEEKLY!B85 -> ORANGE | E52: 28889.5 | F52: 0.38 | G52: 101873.5 | H52: 1.34 | AI52: =SUM(I52,K52,M52,O52,Q52,S52,U52,W52,Y52,AA52,AC52,AE52,AG52) -> 0 | AJ52: =SUM(J52,L52,N52,P52,R52,T52,V52,X52,Z52,AB52,AD52,AF52,AH52) -> 0 | AK52: =WEEKLY!F85 -> 87428.75 | AL52: =WEEKLY!D85 -> 1.15 | AM52: =G52+AI52-AK52 -> 14444.75 | AN52: =H52+AJ52-AL52 -> 0.19 | AO52: =AM52-E52 -> -14444.75
B53: N | C53: 11 | D53: =WEEKLY!B86 -> TEH GOPEK | E53: 19800 | F53: 5 | G53: 146520 | H53: 37 | AE53: 396000 | AF53: 100 | AI53: =SUM(I53,K53,M53,O53,Q53,S53,U53,W53,Y53,AA53,AC53,AE53,AG53) -> 396000 | AJ53: =SUM(J53,L53,N53,P53,R53,T53,V53,X53,Z53,AB53,AD53,AF53,AH53) -> 100 | AK53: =WEEKLY!F86 -> 475200 | AL53: =WEEKLY!D86 -> 120 | AM53: =G53+AI53-AK53 -> 67320 | AN53: =H53+AJ53-AL53 -> 17 | AO53: =AM53-E53 -> 47520
B54: U | C54: 12 | D54: =WEEKLY!B87 -> 0 | E54: 0 | F54: 0 | G54: 0 | H54: 0 | AI54: =SUM(I54,K54,M54,O54,Q54,S54,U54,W54,Y54,AA54,AC54,AE54,AG54) -> 0 | AJ54: =SUM(J54,L54,N54,P54,R54,T54,V54,X54,Z54,AB54,AD54,AF54,AH54) -> 0 | AK54: =WEEKLY!F87 -> 0 | AL54: =WEEKLY!D87 -> 0 | AM54: =G54+AI54-AK54 -> 0 | AN54: =H54+AJ54-AL54 -> 0 | AO54: =AM54-E54 -> 0
B55: M | C55: 13 | D55: =WEEKLY!B88 -> AVOCADO | E55: -364000 | F55: 0 | G55: 440000 | H55: 10 | AI55: =SUM(I55,K55,M55,O55,Q55,S55,U55,W55,Y55,AA55,AC55,AE55,AG55) -> 0 | AJ55: =SUM(J55,L55,N55,P55,R55,T55,V55,X55,Z55,AB55,AD55,AF55,AH55) -> 0 | AK55: =WEEKLY!F88 -> 308000 | AL55: =WEEKLY!D88 -> 7 | AM55: =G55+AI55-AK55 -> 132000 | AN55: =H55+AJ55-AL55 -> 3 | AO55: =AM55-E55 -> 496000
B56: A | C56: 14 | D56: =WEEKLY!B89 -> MARJAN MOCCA | E56: 0 | F56: 0 | G56: 0 | H56: 0 | AI56: =SUM(I56,K56,M56,O56,Q56,S56,U56,W56,Y56,AA56,AC56,AE56,AG56) -> 0 | AJ56: =SUM(J56,L56,N56,P56,R56,T56,V56,X56,Z56,AB56,AD56,AF56,AH56) -> 0 | AK56: =WEEKLY!F89 -> 0 | AL56: =WEEKLY!D89 -> 0 | AM56: =G56+AI56-AK56 -> 0 | AN56: =H56+AJ56-AL56 -> 0 | AO56: =AM56-E56 -> 0
B57: N | C57: 15 | D57: =WEEKLY!B90 -> 0 | E57: 0 | F57: 0 | G57: 0 | H57: 0 | AI57: =SUM(I57,K57,M57,O57,Q57,S57,U57,W57,Y57,AA57,AC57,AE57,AG57) -> 0 | AJ57: =SUM(J57,L57,N57,P57,R57,T57,V57,X57,Z57,AB57,AD57,AF57,AH57) -> 0 | AK57: =WEEKLY!F90 -> 0 | AL57: =WEEKLY!D90 -> 0 | AM57: =G57+AI57-AK57 -> 0 | AN57: =H57+AJ57-AL57 -> 0 | AO57: =AM57-E57 -> 0
C58: 16 | D58: =WEEKLY!B91 -> 0 | E58: 0 | F58: 0 | G58: 0 | H58: 0 | AI58: =SUM(I58,K58,M58,O58,Q58,S58,U58,W58,Y58,AA58,AC58,AE58,AG58) -> 0 | AJ58: =SUM(J58,L58,N58,P58,R58,T58,V58,X58,Z58,AB58,AD58,AF58,AH58) -> 0 | AK58: =WEEKLY!F91 -> 0 | AL58: =WEEKLY!D91 -> 0 | AM58: =G58+AI58-AK58 -> 0 | AN58: =H58+AJ58-AL58 -> 0 | AO58: =AM58-E58 -> 0
C59: 17 | D59: =WEEKLY!B92 -> 0 | E59: 0 | F59: 0 | G59: 0 | H59: 0 | AI59: =SUM(I59,K59,M59,O59,Q59,S59,U59,W59,Y59,AA59,AC59,AE59,AG59) -> 0 | AJ59: =SUM(J59,L59,N59,P59,R59,T59,V59,X59,Z59,AB59,AD59,AF59,AH59) -> 0 | AK59: =WEEKLY!F92 -> 0 | AL59: =WEEKLY!D92 -> 0 | AM59: =G59+AI59-AK59 -> 0 | AN59: =H59+AJ59-AL59 -> 0 | AO59: =AM59-E59 -> 0
C60: 18 | D60: =WEEKLY!B93 -> 0 | E60: 0 | F60: 0 | G60: 0 | H60: 0 | AI60: =SUM(I60,K60,M60,O60,Q60,S60,U60,W60,Y60,AA60,AC60,AE60,AG60) -> 0 | AJ60: =SUM(J60,L60,N60,P60,R60,T60,V60,X60,Z60,AB60,AD60,AF60,AH60) -> 0 | AK60: =WEEKLY!F93 -> 0 | AL60: =WEEKLY!D93 -> 0 | AM60: =G60+AI60-AK60 -> 0 | AN60: =H60+AJ60-AL60 -> 0 | AO60: =AM60-E60 -> 0
C61: 19 | D61: =WEEKLY!B94 -> 0 | E61: 0 | F61: 0 | G61: 0 | H61: 0 | AI61: =SUM(I61,K61,M61,O61,Q61,S61,U61,W61,Y61,AA61,AC61,AE61,AG61) -> 0 | AJ61: =SUM(J61,L61,N61,P61,R61,T61,V61,X61,Z61,AB61,AD61,AF61,AH61) -> 0 | AK61: =WEEKLY!F94 -> 0 | AL61: =WEEKLY!D94 -> 0 | AM61: =G61+AI61-AK61 -> 0 | AN61: =H61+AJ61-AL61 -> 0 | AO61: =AM61-E61 -> 0
C62: 20 | D62: =WEEKLY!B95 -> 0 | E62: 0 | F62: 0 | G62: 0 | H62: 0 | AI62: =SUM(I62,K62,M62,O62,Q62,S62,U62,W62,Y62,AA62,AC62,AE62,AG62) -> 0 | AJ62: =SUM(J62,L62,N62,P62,R62,T62,V62,X62,Z62,AB62,AD62,AF62,AH62) -> 0 | AK62: =WEEKLY!F95 -> 0 | AL62: =WEEKLY!D95 -> 0 | AM62: =G62+AI62-AK62 -> 0 | AN62: =H62+AJ62-AL62 -> 0 | AO62: =AM62-E62 -> 0
C63: 21 | D63: =WEEKLY!B96 -> 0 | E63: 0 | F63: 0 | G63: 0 | H63: 0 | AI63: =SUM(I63,K63,M63,O63,Q63,S63,U63,W63,Y63,AA63,AC63,AE63,AG63) -> 0 | AJ63: =SUM(J63,L63,N63,P63,R63,T63,V63,X63,Z63,AB63,AD63,AF63,AH63) -> 0 | AK63: =WEEKLY!F96 -> 0 | AL63: =WEEKLY!D96 -> 0 | AM63: =G63+AI63-AK63 -> 0 | AN63: =H63+AJ63-AL63 -> 0 | AO63: =AM63-E63 -> 0
C64: 22 | D64: =WEEKLY!B97 -> 0 | E64: 0 | F64: 0 | G64: 0 | H64: 0 | AI64: =SUM(I64,K64,M64,O64,Q64,S64,U64,W64,Y64,AA64,AC64,AE64,AG64) -> 0 | AJ64: =SUM(J64,L64,N64,P64,R64,T64,V64,X64,Z64,AB64,AD64,AF64,AH64) -> 0 | AK64: =WEEKLY!F97 -> 0 | AL64: =WEEKLY!D97 -> 0 | AM64: =G64+AI64-AK64 -> 0 | AN64: =H64+AJ64-AL64 -> 0 | AO64: =AM64-E64 -> 0
C65: 23 | D65: =WEEKLY!B98 -> 0 | E65: 0 | F65: 0 | G65: 0 | H65: 0 | AI65: =SUM(I65,K65,M65,O65,Q65,S65,U65,W65,Y65,AA65,AC65,AE65,AG65) -> 0 | AJ65: =SUM(J65,L65,N65,P65,R65,T65,V65,X65,Z65,AB65,AD65,AF65,AH65) -> 0 | AK65: =WEEKLY!F98 -> 0 | AL65: =WEEKLY!D98 -> 0 | AM65: =G65+AI65-AK65 -> 0 | AN65: =H65+AJ65-AL65 -> 0
C66: 24 | D66: =WEEKLY!B99 -> 0 | E66: 0 | F66: 0 | G66: 0 | H66: 0 | AI66: =SUM(I66,K66,M66,O66,Q66,S66,U66,W66,Y66,AA66,AC66,AE66,AG66) -> 0 | AJ66: =SUM(J66,L66,N66,P66,R66,T66,V66,X66,Z66,AB66,AD66,AF66,AH66) -> 0 | AK66: =WEEKLY!F99 -> 0 | AL66: =WEEKLY!D99 -> 0 | AM66: =G66+AI66-AK66 -> 0 | AN66: =H66+AJ66-AL66 -> 0
C67: 25 | D67: =WEEKLY!B100 -> 0 | E67: 0 | F67: 0 | G67: 0 | H67: 0 | AI67: =SUM(I67,K67,M67,O67,Q67,S67,U67,W67,Y67,AA67,AC67,AE67,AG67) -> 0 | AJ67: =SUM(J67,L67,N67,P67,R67,T67,V67,X67,Z67,AB67,AD67,AF67,AH67) -> 0 | AK67: =WEEKLY!F100 -> 0 | AL67: =WEEKLY!D100 -> 0 | AM67: =G67+AI67-AK67 -> 0 | AN67: =H67+AJ67-AL67 -> 0
C68: 26 | D68: =WEEKLY!B101 -> 0 | E68: 0 | F68: 0 | G68: 0 | H68: 0 | AI68: =SUM(I68,K68,M68,O68,Q68,S68,U68,W68,Y68,AA68,AC68,AE68,AG68) -> 0 | AJ68: =SUM(J68,L68,N68,P68,R68,T68,V68,X68,Z68,AB68,AD68,AF68,AH68) -> 0 | AK68: =WEEKLY!F101 -> 0 | AL68: =WEEKLY!D101 -> 0 | AM68: =G68+AI68-AK68 -> 0 | AN68: =H68+AJ68-AL68 -> 0
C69: 27 | D69: =WEEKLY!B102 -> 0 | E69: 0 | F69: 0 | G69: 0 | H69: 0 | AI69: =SUM(I69,K69,M69,O69,Q69,S69,U69,W69,Y69,AA69,AC69,AE69,AG69) -> 0 | AJ69: =SUM(J69,L69,N69,P69,R69,T69,V69,X69,Z69,AB69,AD69,AF69,AH69) -> 0 | AK69: =WEEKLY!F102 -> 0 | AL69: =WEEKLY!D102 -> 0 | AM69: =G69+AI69-AK69 -> 0 | AN69: =H69+AJ69-AL69 -> 0
C70: 28 | D70: =WEEKLY!B103 -> 0 | E70: 0 | F70: 0 | G70: 0 | H70: 0 | AI70: =SUM(I70,K70,M70,O70,Q70,S70,U70,W70,Y70,AA70,AC70,AE70,AG70) -> 0 | AJ70: =SUM(J70,L70,N70,P70,R70,T70,V70,X70,Z70,AB70,AD70,AF70,AH70) -> 0 | AK70: =WEEKLY!F103 -> 0 | AL70: =WEEKLY!D103 -> 0 | AM70: =G70+AI70-AK70 -> 0 | AN70: =H70+AJ70-AL70 -> 0
C71: 29 | D71: =WEEKLY!B104 -> 0 | E71: 0 | F71: 0 | G71: 0 | H71: 0 | AI71: =SUM(I71,K71,M71,O71,Q71,S71,U71,W71,Y71,AA71,AC71,AE71,AG71) -> 0 | AJ71: =SUM(J71,L71,N71,P71,R71,T71,V71,X71,Z71,AB71,AD71,AF71,AH71) -> 0 | AK71: =WEEKLY!F104 -> 0 | AL71: =WEEKLY!D104 -> 0 | AM71: =G71+AI71-AK71 -> 0 | AN71: =H71+AJ71-AL71 -> 0
C72: 30 | D72: =WEEKLY!B105 -> 0 | E72: 0 | F72: 0 | G72: 0 | H72: 0 | AI72: =SUM(I72,K72,M72,O72,Q72,S72,U72,W72,Y72,AA72,AC72,AE72,AG72) -> 0 | AJ72: =SUM(J72,L72,N72,P72,R72,T72,V72,X72,Z72,AB72,AD72,AF72,AH72) -> 0 | AK72: =WEEKLY!F105 -> 0 | AL72: =WEEKLY!D105 -> 0 | AM72: =G72+AI72-AK72 -> 0 | AN72: =H72+AJ72-AL72 -> 0
C73: 31 | D73: =WEEKLY!B106 -> 0 | E73: 0 | F73: 0 | G73: 0 | H73: 0 | AI73: =SUM(I73,K73,M73,O73,Q73,S73,U73,W73,Y73,AA73,AC73,AE73,AG73) -> 0 | AJ73: =SUM(J73,L73,N73,P73,R73,T73,V73,X73,Z73,AB73,AD73,AF73,AH73) -> 0 | AK73: =WEEKLY!F106 -> 0 | AL73: =WEEKLY!D106 -> 0 | AM73: =G73+AI73-AK73 -> 0 | AN73: =H73+AJ73-AL73 -> 0 | AO73: MINUMAN | AP73: =SUM(AM43:AM73) -> 429631.75
D74: TOTAL LEMBAR 1 | E74: =SUM(E10:E73) -> 16877144 | G74: =SUM(G10:G73) -> 8489486.6 | I74: =SUM(I10:I73) -> 277000 | K74: =SUM(K10:K73) -> 199000 | M74: =SUM(M10:M73) -> 263438 | O74: =SUM(O10:O73) -> 350000 | Q74: =SUM(Q10:Q73) -> 106000 | S74: =SUM(S10:S73) -> 45000 | U74: =SUM(U10:U73) -> 313400 | W74: =SUM(W10:W73) -> 0 | Y74: =SUM(Y10:Y73) -> 0 | AA74: =SUM(AA10:AA73) -> 0 | AC74: =SUM(AC10:AC73) -> -18320.96 | AE74: =SUM(AE10:AE73) -> 396000 | AG74: =SUM(AG10:AG73) -> 10014010 | AI74: =SUM(I74,K74,M74,O74,Q74,S74,U74,W74,Y74,AA74,AC74,AE74,AG74) -> 11945527 | AK74: =SUM(AK10:AK73) -> 9990537.7 | AM74: =SUM(AM10:AM73) -> 10444476
B76: NB : PEMBELIAN AYAM CASH DIMASUKAN MANUAL DAN PEMBELIAN AYAM KREDIT WAJIB DIISI DI KOLOM PEMBELIAN KREDIT KHUSUS AYAM DAN MARINADE
B77: NB : KREDIT BARANG GUDANG DIMASUKAN MANUAL SENDIRI DAN PEMAKAIAN MINGGU LALU ATAU PERSEDIAAN AWAL DIISI MANUAL DAN TO/TI DIISI MANUAL JUGA .TO TANDA ( - )
B79: VENDOR REPORT
AI80: CABANG | AJ80: =AJ2 -> SC MARABAHAN
AI81: PERIODE | AJ81: =AJ3 -> 1-7 JULI 2026
B82: TGL FAKTUR | C82: NO | E82: PEMAKAIAN | G82: PERSEDIAAN | I82: =I5 -> 46204 | K82: =K5 -> 46205 | M82: =M5 -> 46206 | O82: =O5 -> 46207 | Q82: =Q5 -> 46208 | S82: =S5 -> 46209 | U82: =U5 -> 46210 | W82: =W5 -> 0 | Y82: =Y5 -> 0 | AA82: =AA5 -> 0 | AC82: KHUSUS TO/TI | AE82: KREDIT BARGUD | AG82: KREDIT BAHAN BAKU | AI82: TOTAL | AK82: PERSEDIAAN | AM82: PEMAKAIAN
D83: KETERANGAN BAHAN | E83: MINGGU LALU | G83: AWAL | AC83: C.PATTY/CATTERING STAFF | AI83: PEMBELIAN | AK83: AKHIR | AM83: MINGGU INI
B84: HARI | E84: DLM SATUAN | G84: DLM SATUAN | I84: =I7 -> RABU | K84: =K7 -> KAMIS | M84: =M7 -> JUM'AT | O84: =O7 -> SABTU | Q84: =Q7 -> MINGGU | S84: =S7 -> SENIN | U84: =U7 -> SELASA | W84: =W7 -> 0 | Y84: =Y7 -> 0 | AA84: =AA7 -> 0 | AC84: PERKEDEL/BARGUD | AG84: AYAM DLL | AI84: DLM SATUAN | AK84: DLM SATUAN | AM84: DLM SATUAN
E85: Rp | F85: Unit | G85: Rp | H85: Unit | J85: Unit | L85: Unit | N85: Unit | P85: Unit | R85: Unit | T85: Unit | V85: Unit | X85: Unit | Z85: Unit | AB85: Unit | AD85: Unit | AF85: Unit | AH85: Unit | AI85: Rp | AJ85: Unit | AK85: Rp | AL85: Unit | AM85: Rp | AN85: Unit
C86: 1 | D86: =WEEKLY!B109 -> PLASTIK JAGUNG | E86: -5000 | F86: -0.5 | G86: 5000 | H86: 0.5 | O86: 10000 | P86: 1 | S86: 10000 | T86: 1 | AI86: =SUM(I86,K86,M86,O86,Q86,S86,U86,W86,Y86,AA86,AC86,AE86,AG86) -> 20000 | AJ86: =SUM(J86,L86,N86,P86,R86,T86,V86,X86,Z86,AB86,AD86,AF86,AH86) -> 2 | AK86: =WEEKLY!F109 -> 15000 | AL86: =WEEKLY!D109 -> 1.5 | AM86: =G86+AI86-AK86 -> 10000 | AN86: =H86+AJ86-AL86 -> 1 | AO86: =AM86-E86 -> 15000
C87: 2 | D87: =WEEKLY!B110 -> PLASTIK SEDANG SC | E87: 136738.6 | F87: 376 | G87: 178527.6 | H87: 491 | AE87: 363650 | AF87: 1000 | AI87: =SUM(I87,K87,M87,O87,Q87,S87,U87,W87,Y87,AA87,AC87,AE87,AG87) -> 363650 | AJ87: =SUM(J87,L87,N87,P87,R87,T87,V87,X87,Z87,AB87,AD87,AF87,AH87) -> 1000 | AK87: =WEEKLY!F110 -> 428684.4 | AL87: =WEEKLY!D110 -> 1179 | AM87: =G87+AI87-AK87 -> 113493.2 | AN87: =H87+AJ87-AL87 -> 312 | AO87: =AM87-E87 -> -23245.4
C88: 3 | D88: =WEEKLY!B111 -> PLASTIK KECIL SC | E88: 84690 | F88: 353 | G88: 8400 | H88: 35 | AE88: 239850 | AF88: 1000 | AI88: =SUM(I88,K88,M88,O88,Q88,S88,U88,W88,Y88,AA88,AC88,AE88,AG88) -> 239850 | AJ88: =SUM(J88,L88,N88,P88,R88,T88,V88,X88,Z88,AB88,AD88,AF88,AH88) -> 1000 | AK88: =WEEKLY!F111 -> 185520 | AL88: =WEEKLY!D111 -> 773 | AM88: =G88+AI88-AK88 -> 62730 | AN88: =H88+AJ88-AL88 -> 262 | AO88: =AM88-E88 -> -21960
C89: 4 | D89: =WEEKLY!B112 -> PLASTIK BESAR SC | E89: 97021.5 | F89: 213 | G89: 76524 | H89: 168 | AE89: 136650 | AF89: 300 | AI89: =SUM(I89,K89,M89,O89,Q89,S89,U89,W89,Y89,AA89,AC89,AE89,AG89) -> 136650 | AJ89: =SUM(J89,L89,N89,P89,R89,T89,V89,X89,Z89,AB89,AD89,AF89,AH89) -> 300 | AK89: =WEEKLY!F112 -> 150315 | AL89: =WEEKLY!D112 -> 330 | AM89: =G89+AI89-AK89 -> 62859 | AN89: =H89+AJ89-AL89 -> 138 | AO89: =AM89-E89 -> -34162.5
C90: 5 | D90: =WEEKLY!B113 -> SEDOTAN PLASTIK | E90: 80670 | F90: 1431 | G90: 33950 | H90: 485 | M90: 30000 | N90: 500 | S90: 30000 | T90: 500 | AI90: =SUM(I90,K90,M90,O90,Q90,S90,U90,W90,Y90,AA90,AC90,AE90,AG90) -> 60000 | AJ90: =SUM(J90,L90,N90,P90,R90,T90,V90,X90,Z90,AB90,AD90,AF90,AH90) -> 1000 | AK90: =WEEKLY!F113 -> 22400 | AL90: =WEEKLY!D113 -> 320 | AM90: =G90+AI90-AK90 -> 71550 | AN90: =H90+AJ90-AL90 -> 1165 | AO90: =AM90-E90 -> -9120
C91: 6 | D91: =WEEKLY!B114 -> KERTAS MINYAK | E91: 10064 | F91: 68 | G91: 34336 | H91: 232 | S91: 37000 | T91: 250 | AI91: =SUM(I91,K91,M91,O91,Q91,S91,U91,W91,Y91,AA91,AC91,AE91,AG91) -> 37000 | AJ91: =SUM(J91,L91,N91,P91,R91,T91,V91,X91,Z91,AB91,AD91,AF91,AH91) -> 250 | AK91: =WEEKLY!F114 -> 51504 | AL91: =WEEKLY!D114 -> 348 | AM91: =G91+AI91-AK91 -> 19832 | AN91: =H91+AJ91-AL91 -> 134 | AO91: =AM91-E91 -> 9768
C92: 7 | D92: =WEEKLY!B115 -> BOX CATT KECIL | E92: 1649422 | F92: 1559 | G92: 1073870 | H92: 1015 | AE92: 3174000 | AF92: 3000 | AI92: =SUM(I92,K92,M92,O92,Q92,S92,U92,W92,Y92,AA92,AC92,AE92,AG92) -> 3174000 | AJ92: =SUM(J92,L92,N92,P92,R92,T92,V92,X92,Z92,AB92,AD92,AF92,AH92) -> 3000 | AK92: =WEEKLY!F115 -> 3187754 | AL92: =WEEKLY!D115 -> 3013 | AM92: =G92+AI92-AK92 -> 1060116 | AN92: =H92+AJ92-AL92 -> 1002 | AO92: =AM92-E92 -> -589306
C93: 8 | D93: =WEEKLY!B116 -> BOX AW (AYAM WHOLE) | E93: 365310 | F93: 123 | G93: 151470 | H93: 51 | AE93: 1090500 | AF93: 300 | AI93: =SUM(I93,K93,M93,O93,Q93,S93,U93,W93,Y93,AA93,AC93,AE93,AG93) -> 1090500 | AJ93: =SUM(J93,L93,N93,P93,R93,T93,V93,X93,Z93,AB93,AD93,AF93,AH93) -> 300 | AK93: =WEEKLY!F116 -> 795960 | AL93: =WEEKLY!D116 -> 268 | AM93: =G93+AI93-AK93 -> 446010 | AN93: =H93+AJ93-AL93 -> 83 | AO93: =AM93-E93 -> 80700
B94: P | C94: 9 | D94: =WEEKLY!B117 -> COVER NASI | E94: 189000 | F94: 1890 | G94: 6500 | H94: 65 | I94: 20000 | J94: 200 | M94: 50000 | N94: 500 | S94: 50000 | AI94: =SUM(I94,K94,M94,O94,Q94,S94,U94,W94,Y94,AA94,AC94,AE94,AG94) -> 120000 | AJ94: =SUM(J94,L94,N94,P94,R94,T94,V94,X94,Z94,AB94,AD94,AF94,AH94) -> 700 | AK94: =WEEKLY!F117 -> 48900 | AL94: =WEEKLY!D117 -> 489 | AM94: =G94+AI94-AK94 -> 77600 | AN94: =H94+AJ94-AL94 -> 276 | AO94: =AM94-E94 -> -111400
B95: E | C95: 10 | D95: =WEEKLY!B118 -> COVER BURGER | E95: 8085 | F95: 35 | G95: 9240 | H95: 40 | AE95: 23100 | AF95: 100 | AI95: =SUM(I95,K95,M95,O95,Q95,S95,U95,W95,Y95,AA95,AC95,AE95,AG95) -> 23100 | AJ95: =SUM(J95,L95,N95,P95,R95,T95,V95,X95,Z95,AB95,AD95,AF95,AH95) -> 100 | AK95: =WEEKLY!F118 -> 28875 | AL95: =WEEKLY!D118 -> 125 | AM95: =G95+AI95-AK95 -> 3465 | AN95: =H95+AJ95-AL95 -> 15 | AO95: =AM95-E95 -> -4620
B96: M | C96: 11 | D96: =WEEKLY!B119 -> 0 | E96: 0 | F96: 0 | G96: 0 | H96: 0 | AI96: =SUM(I96,K96,M96,O96,Q96,S96,U96,W96,Y96,AA96,AC96,AE96,AG96) -> 0 | AJ96: =SUM(J96,L96,N96,P96,R96,T96,V96,X96,Z96,AB96,AD96,AF96,AH96) -> 0 | AK96: =WEEKLY!F119 -> 0 | AL96: =WEEKLY!D119 -> 0 | AM96: =G96+AI96-AK96 -> 0 | AN96: =H96+AJ96-AL96 -> 0 | AO96: =AM96-E96 -> 0
B97: B | C97: 12 | D97: =WEEKLY!B120 -> CUP POLOS 22 OZ | E97: 55600 | F97: 130 | G97: 49920 | H97: 96 | S97: 44000 | T97: 100 | AI97: =SUM(I97,K97,M97,O97,Q97,S97,U97,W97,Y97,AA97,AC97,AE97,AG97) -> 44000 | AJ97: =SUM(J97,L97,N97,P97,R97,T97,V97,X97,Z97,AB97,AD97,AF97,AH97) -> 100 | AK97: =WEEKLY!F120 -> 46800 | AL97: =WEEKLY!D120 -> 90 | AM97: =G97+AI97-AK97 -> 47120 | AN97: =H97+AJ97-AL97 -> 106 | AO97: =AM97-E97 -> -8480
B98: U | C98: 13 | D98: =WEEKLY!B121 -> ROLL CUP SEALER | E98: 96000 | F98: 2.7 | G98: 65000 | H98: 1.3 | S98: 37000 | T98: 1 | AI98: =SUM(I98,K98,M98,O98,Q98,S98,U98,W98,Y98,AA98,AC98,AE98,AG98) -> 37000 | AJ98: =SUM(J98,L98,N98,P98,R98,T98,V98,X98,Z98,AB98,AD98,AF98,AH98) -> 1 | AK98: =WEEKLY!F121 -> 44400 | AL98: =WEEKLY!D121 -> 1.2 | AM98: =G98+AI98-AK98 -> 57600 | AN98: =H98+AJ98-AL98 -> 1.1 | AO98: =AM98-E98 -> -38400
B99: N | C99: 14 | D99: =WEEKLY!B122 -> CUP MINUM POLOS | E99: 248840 | F99: 822 | G99: 50160 | H99: 228 | AI99: =SUM(I99,K99,M99,O99,Q99,S99,U99,W99,Y99,AA99,AC99,AE99,AG99) -> 0 | AJ99: =SUM(J99,L99,N99,P99,R99,T99,V99,X99,Z99,AB99,AD99,AF99,AH99) -> 0 | AK99: =WEEKLY!F122 -> 0 | AL99: =WEEKLY!D122 -> 0 | AM99: =G99+AI99-AK99 -> 50160 | AN99: =H99+AJ99-AL99 -> 228 | AO99: =AM99-E99 -> -198680
B100: G | C100: 15 | D100: =WEEKLY!B123 -> TISSUE | E100: 52000 | F100: 6.5 | G100: 17500 | H100: 2.5 | M100: 19500 | N100: 3 | U100: 34400 | V100: 8 | AI100: =SUM(I100,K100,M100,O100,Q100,S100,U100,W100,Y100,AA100,AC100,AE100,AG100) -> 53900 | AJ100: =SUM(J100,L100,N100,P100,R100,T100,V100,X100,Z100,AB100,AD100,AF100,AH100) -> 11 | AK100: =WEEKLY!F123 -> 91000 | AL100: =WEEKLY!D123 -> 13 | AM100: =G100+AI100-AK100 -> -19600 | AN100: =H100+AJ100-AL100 -> 0.5 | AO100: =AM100-E100 -> -71600
B101: K | C101: 16 | D101: =WEEKLY!B124 -> KANTONG KERTAS | E101: 115544 | F101: 286 | G101: 237552 | H101: 588 | AE101: 323400 | AF101: 800 | AI101: =SUM(I101,K101,M101,O101,Q101,S101,U101,W101,Y101,AA101,AC101,AE101,AG101) -> 323400 | AJ101: =SUM(J101,L101,N101,P101,R101,T101,V101,X101,Z101,AB101,AD101,AF101,AH101) -> 800 | AK101: =WEEKLY!F124 -> 475912 | AL101: =WEEKLY!D124 -> 1178 | AM101: =G101+AI101-AK101 -> 85040 | AN101: =H101+AJ101-AL101 -> 210 | AO101: =AM101-E101 -> -30504
B102: U | C102: 17 | D102: =WEEKLY!B125 -> CUP MINUMAN | E102: 245700 | F102: 450 | G102: 191100 | H102: 350 | AE102: 1228500 | AF102: 2250 | AI102: =SUM(I102,K102,M102,O102,Q102,S102,U102,W102,Y102,AA102,AC102,AE102,AG102) -> 1228500 | AJ102: =SUM(J102,L102,N102,P102,R102,T102,V102,X102,Z102,AB102,AD102,AF102,AH102) -> 2250 | AK102: =WEEKLY!F125 -> 1230684 | AL102: =WEEKLY!D125 -> 2254 | AM102: =G102+AI102-AK102 -> 188916 | AN102: =H102+AJ102-AL102 -> 346 | AO102: =AM102-E102 -> -56784
B103: S | C103: 18 | D103: =WEEKLY!B126 -> PAPER FRENCH FRIES | E103: 328 | F103: 2 | G103: 1968 | H103: 12 | AI103: =SUM(I103,K103,M103,O103,Q103,S103,U103,W103,Y103,AA103,AC103,AE103,AG103) -> 0 | AJ103: =SUM(J103,L103,N103,P103,R103,T103,V103,X103,Z103,AB103,AD103,AF103,AH103) -> 0 | AK103: =WEEKLY!F126 -> 1148 | AL103: =WEEKLY!D126 -> 7 | AM103: =G103+AI103-AK103 -> 820 | AN103: =H103+AJ103-AL103 -> 5 | AO103: =AM103-E103 -> 492
C104: 19 | D104: =WEEKLY!B127 -> CUP PUDING 35 ML | E104: 53100 | F104: 177 | G104: 6900 | H104: 23 | K104: 30000 | L104: 100 | S104: 15000 | T104: 50 | AI104: =SUM(I104,K104,M104,O104,Q104,S104,U104,W104,Y104,AA104,AC104,AE104,AG104) -> 45000 | AJ104: =SUM(J104,L104,N104,P104,R104,T104,V104,X104,Z104,AB104,AD104,AF104,AH104) -> 150 | AK104: =WEEKLY!F127 -> 11400 | AL104: =WEEKLY!D127 -> 38 | AM104: =G104+AI104-AK104 -> 40500 | AN104: =H104+AJ104-AL104 -> 135 | AO104: =AM104-E104 -> -12600
C105: 20 | D105: =WEEKLY!B128 -> PLASTIK KLIP KECIL (TAKE AWAY) | E105: 6000 | F105: 1 | G105: 0 | H105: 0 | O105: 5000 | P105: 1 | AI105: =SUM(I105,K105,M105,O105,Q105,S105,U105,W105,Y105,AA105,AC105,AE105,AG105) -> 5000 | AJ105: =SUM(J105,L105,N105,P105,R105,T105,V105,X105,Z105,AB105,AD105,AF105,AH105) -> 1 | AK105: =WEEKLY!F128 -> 600 | AL105: =WEEKLY!D128 -> 0.1 | AM105: =G105+AI105-AK105 -> 4400 | AN105: =H105+AJ105-AL105 -> 0.9 | AO105: =AM105-E105 -> -1600
...

Sheet WEEKLY
A3: WEEKLY / MONTHLY INVENTORI
E5: Cabang : | F5: =LPKK!Q4 -> SC MARABAHAN
E6: Periode : | F6: =LPKK!Q5 -> 1-7 JULI 2026
A9: NO | B9: BAHAN | C9: UNIT | D9: QTY | E9: PRICE | F9: TOTAL (Rp)
A10: I | B10: BAHAN AYAM
A11: 1 | B11: DADA MENTOK | C11: Pcs | D11: 34 | E11: 5240.625 | F11: =D11*E11 -> 178181.25
A12: 2 | B12: DADA | C12: Pcs | D12: 51 | E12: 6248.4375 | F12: =D12*E12 -> 318670.31
A13: 3 | B13: PAHA ATAS | C13: Pcs | D13: 59 | E13: 6450 | F13: =D13*E13 -> 380550
A14: 4 | B14: PAHA BAWAH | C14: Pcs | D14: 128 | E14: 4635.9375 | F14: =D14*E14 -> 593400
A15: 5 | B15: SAYAP | C15: Pcs | D15: 136 | E15: 4240.0184 | F15: =D15*E15 -> 576642.5
A16: 6 | B16: CHICKEN PATTY | C16: Pcs | D16: 22 | E16: ='TO-TI'!S21 -> 2374.6076 | F16: =D16*E16 -> 52241.368
A17: 7 | B17: AYAM WHOLE | C17: Pcs | D17: 26 | E17: 24070 | F17: =D17*E17 -> 625820
A18: 8 | B18: SAYAP FULL | C18: Pcs | E18: 3172.75 | F18: =D18*E18 -> 0
A19: 9 | B19: KULIT | C19: Kg | D19: 7.5 | E19: 35500 | F19: =D19*E19 -> 266250
A20: 10 | B20: PAHA BAWAH FULL | C20: Pcs | E20: 4647.98 | F20: =D20*E20 -> 0
A21: 11 | B21: CUT 10 | C21: Pcs | D21: 240 | E21: 4142 | F21: =D21*E21 -> 994080
A22: 12 | F22: =D22*E22 -> 0
A23: 13 | F23: =D23*E23 -> 0
A24: 14 | F24: =D24*E24 -> 0
E25: JUMLAH | F25: =SUM(F11:F24) -> 3985835.4
A26: II | B26: BAHAN PELENGKAP
A27: 1 | B27: VEGETABLE MIX | C27: Kg | D27: 0.6 | E27: 35000 | F27: =D27*E27 -> 21000
A28: 2 | B28: BERAS | C28: Kg | D28: 222 | E28: 17500 | F28: =D28*E28 -> 3885000
A29: 3 | B29: FRENCH FRIES | C29: Kg | D29: 0.4 | E29: 30000 | F29: =D29*E29 -> 12000
A30: 4 | B30: ROTI BURGER | C30: Pcs | D30: 3 | E30: 2833 | F30: =D30*E30 -> 8499
A31: 5 | B31: SOSIS | C31: Pcs | D31: 10 | E31: 1300 | F31: =D31*E31 -> 13000
A32: 6 | B32: PERKEDEL | C32: pcs | D32: 44 | E32: 2479.6518 | F32: =D32*E32 -> 109104.68
A33: 7 | B33: SOSIS NASGOR | C33: Pcs | D33: 9 | E33: 1150 | F33: =D33*E33 -> 10350
A34: 8 | B34: NUGGET COIN | C34: Pcs | D34: 48 | E34: 600 | F34: =D34*E34 -> 28800
A35: 9 | B35: BAKSO | C35: Pcs | D35: 4 | E35: 640 | F35: =D35*E35 -> 2560
A36: 10 | F36: =D36*E36 -> 0
A37: 11 | F37: =D37*E37 -> 0
A38: 12 | F38: =D38*E38 -> 0
B39: BAHAN ROTI
A40: 13 | B40: SLICED CHEESE | C40: Pcs | D40: 17 | E40: 1166 | F40: =D40*E40 -> 19822
A41: 14 | B41: KEJU BATANG (170 GR ) | C41: Pack | D41: 1 | E41: 17000 | F41: =D41*E41 -> 17000
A42: 15 | B42: TEPUNG ROTI (PANIR) | C42: Kg | D42: 0.13 | E42: 31000 | F42: =D42*E42 -> 4030
A43: 16 | B43: CUKA DIXI 150 ML | C43: Botol | D43: 1 | E43: 5000 | F43: =D43*E43 -> 5000
A44: 17 | B44: BAWANG BOMBAY | C44: Kg | D44: 0.1 | E44: 40000 | F44: =D44*E44 -> 4000
A45: 18 | B45: DRESSING BURGER | C45: Resep | D45: 0.2 | E45: 37882.667 | F45: =D45*E45 -> 7576.5333
A46: 19 | B46: MARGARINE( 200 GR ) | C46: Pack | D46: 1 | E46: 7000 | F46: =D46*E46 -> 7000
A47: 20 | B47: TOMAT | C47: Kg | D47: 0.1 | E47: 20000 | F47: =D47*E47 -> 2000
A48: 21 | B48: ROTI TAWAR | C48: Pcs | D48: 3 | E48: 900 | F48: =D48*E48 -> 2700
A49: 22 | B49: SELADA | C49: Kg | D49: 0.17 | E49: 10000 | F49: =D49*E49 -> 1700
A50: 23 | B50: GULA HALUS 250 GR | C50: Pack | E50: 17000 | F50: =D50*E50 -> 0
A51: 24 | B51: SUSU ULTRA( 250 ML ) | C51: Pack | E51: 6000 | F51: =D51*E51 -> 0
A52: 25 | F52: =D52*E52 -> 0
A53: 26 | F53: =D53*E53 -> 0
E54: JUMLAH | F54: =SUM(F27:F53) -> 4161142.2 | G54: TOTAL BAHAN ROTI | I54: =SUM(F40:F53) -> 70828.533
A55: III | B55: BAHAN ES
A57: 1 | B57: GULA PASIR | C57: kg | E57: 17500 | F57: =D57*E57 -> 0
A58: 2 | F58: =D58*E58 -> 0
A59: 3 | B59: ICE CREAM EMBER | C59: kg | D59: 0.5 | E59: 27500 | F59: =D59*E59 -> 13750
A60: 4 | B60: SUSU PUTIH | C60: kg | D60: 0.48 | E60: 15000 | F60: =D60*E60 -> 7200
A61: 5 | B61: AIR GALON | C61: Gln | D61: 4 | E61: 6000 | F61: =D61*E61 -> 24000
A62: 6 | B62: ES BATU | C62: pack | D62: 1 | E62: 14000 | F62: =D62*E62 -> 14000
A63: 8 | B63: SIMPLE SYRUP | C63: Liter | D63: 36.1 | E63: 13543.86 | F63: =D63*E63 -> 488933.33
A64: 9 | B64: ES BALOK | E64: 1000 | F64: =D64*E64 -> 0
A65: 10 | F65: =D65*E65 -> 0
A66: 11 | F66: =D66*E66 -> 0
A67: 12 | F67: =D67*E67 -> 0
A68: 13 | F68: =D68*E68 -> 0
E69: JUMLAH | F69: =SUM(F56:F68) -> 547883.33 | G69: TOTAL BAHAN ES | I69: =SUM(F60:F68) -> 534133.33
E70: TOTAL LEMBAR 1 | F70: =F25+F54+F69 -> 8694861
A74: NO | B74: BAHAN | C74: UNIT | D74: QTY | E74: PRICE | F74: TOTAL (Rp)
A75: IV | B75: BAHAN MINUMAN
A76: 1 | B76: TEH BOTOL SOSRO (TBS) | C76: Pcs | D76: 15 | E76: 2500 | F76: =D76*E76 -> 37500
A77: 2 | B77: TEH SOSRO POUCH (TBO) | C77: Pcs | D77: 55 | E77: 2500 | F77: =D77*E77 -> 137500
A78: 3 | F78: =D78*E78 -> 0
A79: 4 | B79: S-TEE | C79: Pcs | F79: =D79*E79 -> 0
A80: 5 | F80: =D80*E80 -> 0
A81: 6 | B81: AIR MINERAL BOTOL (AMB) | C81: Pcs | D81: 29 | E81: 1750 | F81: =D81*E81 -> 50750
A82: 7 | B82: AIR MINERAL CUP (AMC) | C82: Pcs | F82: =D82*E82 -> 0
A83: 8 | B83: MILO | C83: Pack | D83: 0.43 | E83: 133100 | F83: =D83*E83 -> 57233
A84: 9 | B84: NESTEA | C84: Pack | D84: 1.64 | E84: 86625 | F84: =D84*E84 -> 142065
A85: 10 | B85: ORANGE | C85: Pack | D85: 1.15 | E85: 76025 | F85: =D85*E85 -> 87428.75
A86: 11 | B86: TEH GOPEK | C86: Pcs | D86: 120 | E86: 3960 | F86: =D86*E86 -> 475200
A87: 12 | F87: =D87*E87 -> 0
A88: 13 | B88: AVOCADO | C88: Kg | D88: 7 | E88: 44000 | F88: =D88*E88 -> 308000
A89: 14 | B89: MARJAN MOCCA | C89: Pcs | F89: =D89*E89 -> 0
A90: 15 | F90: =D90*E90 -> 0
A91: 16 | F91: =D91*E91 -> 0
A92: 17 | F92: =D92*E92 -> 0
A93: 18 | F93: =D93*E93 -> 0
A94: 19 | F94: =D94*E94 -> 0
A95: 20 | F95: =D95*E95 -> 0
A96: 21 | F96: =D96*E96 -> 0
A97: 22 | F97: =D97*E97 -> 0
A98: 23 | F98: =D98*E98 -> 0
A99: 24 | F99: =D99*E99 -> 0
A100: 25 | F100: =D100*E100 -> 0
A101: 26 | F101: =D101*E101 -> 0
... A106: 31 | F106: =D106*E106 -> 0
E107: JUMLAH | F107: =SUM(F76:F106) -> 1295676.8
A108: V | B108: BAHAN PEMBUNGKUS
A109: 1 | B109: PLASTIK JAGUNG | C109: Pcs | D109: 1.5 | E109: 10000 | F109: =D109*E109 -> 15000
A110: 2 | B110: PLASTIK SEDANG SC | C110: Pcs | D110: 1179 | E110: 363.6 | F110: =D110*E110 -> 428684.4
A111: 3 | B111: PLASTIK KECIL SC | C111: Pcs | D111: 773 | E111: 240 | F111: =D111*E111 -> 185520
A112: 4 | B112: PLASTIK BESAR SC | C112: Pcs | D112: 330 | E112: 455.5 | F112: =D112*E112 -> 150315
A113: 5 | B113: SEDOTAN PLASTIK | C113: Pcs | D113: 320 | E113: 70 | F113: =D113*E113 -> 22400
...

Sheet LAP. CF
A4: LAPORAN CASH FLOW
H6: Periode : | I6: =LPKK!Q5 -> 1-7 JULI 2026
H7: CABANG : | I7: =LPKK!Q4 -> SC MARABAHAN
A8: SALDO AWAL PER ………………………..
A10: Penerimaan : | J10: Rp. | K10: 1589512
B11: Sales tanggal, | D11: ='LAPORAN KAS PERIODE'!$D$6 -> 1-Juli-2026 | G11: Rp. | H11: ='LAPORAN KAS PERIODE'!$D$15 -> 4454000
B12: Sales tanggal, | D12: ='LAPORAN KAS PERIODE'!$E$6 -> 2-Juli-2026 | G12: Rp. | H12: ='LAPORAN KAS PERIODE'!$E$15 -> 3639000
B13: Sales tanggal, | D13: ='LAPORAN KAS PERIODE'!$F$6 -> 3-Juli-2026 | G13: Rp. | H13: ='LAPORAN KAS PERIODE'!$F$15 -> 3173500
B14: Sales tanggal, | D14: ='LAPORAN KAS PERIODE'!$G$6 -> 4-Juli-2026 | G14: Rp. | H14: ='LAPORAN KAS PERIODE'!$G$15 -> 3484000
B15: Sales tanggal, | D15: ='LAPORAN KAS PERIODE'!$H$6 -> 5-Juli-2026 | G15: Rp. | H15: ='LAPORAN KAS PERIODE'!$H$15 -> 4920500
B16: Sales tanggal, | D16: ='LAPORAN KAS PERIODE'!$I$6 -> 6-Juli-2026 | G16: Rp. | H16: ='LAPORAN KAS PERIODE'!$I$15 -> 4009000
B17: Sales tanggal, | D17: ='LAPORAN KAS PERIODE'!$J$6 -> 7-Juli-2026 | G17: Rp. | H17: ='LAPORAN KAS PERIODE'!$J$15 -> 3711500
B18: Sales tanggal, | D18: ='LAPORAN KAS PERIODE'!$K$6 -> 0 | G18: Rp. | H18: ='LAPORAN KAS PERIODE'!$K$15 -> 0
B19: Sales tanggal, | D19: ='LAPORAN KAS PERIODE'!$L$6 -> 0 | G19: Rp. | H19: ='LAPORAN KAS PERIODE'!$L$15 -> 0
B20: Sales tanggal, | D20: ='LAPORAN KAS PERIODE'!$M$6 -> 0 | G20: Rp. | H20: ='LAPORAN KAS PERIODE'!$M$15 -> 0
D23: Total Penerimaan Sales | H23: ….................................. | J23: Rp. | K23: =SUM(H11:I20) -> 27391500
A25: Penerimaan Lain - lain :
B26: MIKAS OWNER | G26: Rp | H26: 663000
G27: Rp
G28: Rp
G29: Rp
G30: Rp
H32: ….................................... | J32: Rp. | K32: =SUM(H26:I30) -> 663000
D34: Total Uang Yang Ada | H34: …................................... | J34: Rp. | K34: =K10+K23+K32 -> 29644012
A35: Pengeluaran :
B37: Belanja Tgl | D37: =D11 -> 1-Juli-2026 | G37: Rp. | H37: =VENDOR!I216 -> 1994000
B38: Belanja Tgl | D38: =D12 -> 2-Juli-2026 | G38: Rp. | H38: =VENDOR!K216 -> 1985500
B39: Belanja Tgl | D39: =D13 -> 3-Juli-2026 | G39: Rp. | H39: =VENDOR!M216 -> 4009438
B40: Belanja Tgl | D40: =D14 -> 4-Juli-2026 | G40: Rp. | H40: =VENDOR!O216 -> 2489000
B41: Belanja Tgl | D41: =D15 -> 5-Juli-2026 | G41: Rp. | H41: =VENDOR!Q216 -> 6584925
B42: Belanja Tgl | D42: =D16 -> 6-Juli-2026 | G42: Rp. | H42: =VENDOR!S216 -> 3270500
B43: Belanja Tgl | D43: =D17 -> 7-Juli-2026 | G43: Rp. | H43: =VENDOR!U216 -> 3709202
B44: Belanja Tgl | D44: =D18 -> 0 | G44: Rp. | H44: =VENDOR!W216 -> 0
B45: Belanja Tgl | D45: =D19 -> 0 | G45: Rp. | H45: =VENDOR!Y216 -> 0
B46: Belanja Tgl | D46: =D20 -> 0 | G46: Rp. | H46: =VENDOR!AA216 -> 0
D50: Total Pengeluaran | H50: …................................... | J50: Rp. | K50: =SUM(H37:I47) -> 24042565
A52: SALDO AKHIR PER ………………….. | H52: …................................... | J52: Rp. | K52: =K34-K50 -> 5601447
B55: Paraf Supervisor

Sheet IKHTISAR FOOD COST
A2: LAPORAN IKHTISAR FOOD COST
C5: CABANG : | D5: =LPKK!Q4 -> SC MARABAHAN
C6: PERIODE: | D6: =LPKK!Q5 -> 1-7 JULI 2026
B8: FOOD & BEVERAGE | D8: PAPER
A10: PERSEDIAAN AWAL | B10: 12327192 | D10: 2273313.6
A12: TRANSFER IN (+) =
A13: C. PATTY | B13: ='TO-TI'!S19 -> 85485.875
A14: PERKEDEL | B14: ='TO-TI'!D18 -> 139420.5
A16: TOTAL TRANSFER IN | B16: =SUM(B12:B14) -> 224906.38 | D16: =SUM(D12:D14) -> 0
A18: PEMBELIAN
A19: PEMBELIAN KREDIT | B19: =VENDOR!AI153 -> 12120878 | D19: =VENDOR!AI154 -> 6579650
A20: PEMBELIAN KONTAN | B20: =VENDOR!AI155 -> 2809438 | D20: =VENDOR!AI156 -> 421900
A21: TOTAL PEMBELIAN | B21: =B19+B20 -> 14930316 | D21: =D19+D20 -> 7001550
A23: JUMLAH YANG TERSEDIA | B23: =B10+B16+B21 -> 27482414 | D23: =D10+D16+D21 -> 9274863.6
A25: TRANSFER OUT (-) =
A26: TO CATERING STAFF / FREE | B26: ='TO-TI'!I20+'TO-TI'!N21 -> 160667.96
A27: C. PATTY | B27: ='TO-TI'!S19 -> 85485.875
A28: PERKEDEL | B28: ='TO-TI'!D18 -> 139420.5
A31: TOTAL TRANSFER OUT | B31: =SUM(B26:B29) -> 385574.33 | D31: =SUM(D26:D29) -> 0
A33: PERSEDIAAN AKHIR | B33: =WEEKLY!F333 -> 14070978 | D33: =WEEKLY!F334 -> 6867740.4
A35: JUMLAH YANG DIPAKAI | B35: =B23-B31-B33 -> 13025862 | D35: =D23-D31-D33 -> 2407123.2
A36: (%) | B36: =(B35/B44) -> 0.47554394 | D36: =D35/B44 -> 0.087878473
A39: PENJUALAN KOTOR | B39: ='LAPORAN KAS PERIODE'!N8 -> 27391500
A40: KOREKSI (-) | B40: ='LAPORAN KAS PERIODE'!N12 -> 0
A41: DISCOUNT (-) | B41: ='LAPORAN KAS PERIODE'!N13 -> 0
A42: KOMISI PENJUALAN ONLINE (-) | B42: =SUM('LAPORAN KAS PERIODE'!N9:N11) -> 0
A43: TAX ( - )
A44: PENJUALAN BERSIH | B44: =B39-B40-B41-B42-B43 -> 27391500
A47: JUMLAH BAHAN YANG DIPAKAI | B47: =B35+D35 -> 15432985 | D47: =B47/B48 -> 0.56342241
A48: JUMLAH PENJUALAN BERSIH | B48: =B44 -> 27391500

Sheet LAPORAN KAS PERIODE
B2: LAPORAN KAS & PENJUALAN PER PERIODE
L3: CABANG : | M3: =LPKK!Q4 -> SC MARABAHAN
L4: PERIODE : | M4: =LPKK!Q5 -> 1-7 JULI 2026
B6: TANGGAL | D6: 1-Juli-2026 | E6: 2-Juli-2026 | F6: 3-Juli-2026 | G6: 4-Juli-2026 | H6: 5-Juli-2026 | I6: 6-Juli-2026 | J6: 7-Juli-2026 | N6: TOTAL
B7: HARI | D7: Rabu | E7: Kamis | F7: Jum`at | G7: Sabtu | H7: Minggu | I7: Senin | J7: Selasa
B8: Penjualan Kotor | D8: =SUM('LAP. PENJUALAN REGULER'!D112,'LAP. PENJUALAN GOFOOD'!D112,'LAP. PENJUALAN GRABFOOD'!D112,'LAP. PENJUALAN SHOPEFOOD'!D112) -> 4454000 | E8: =SUM('LAP. PENJUALAN REGULER'!E112,'LAP. PENJUALAN GOFOOD'!E112,'LAP. PENJUALAN GRABFOOD'!E112,'LAP. PENJUALAN SHOPEFOOD'!E112) -> 3639000 | F8: =SUM('LAP. PENJUALAN REGULER'!F112,'LAP. PENJUALAN GOFOOD'!F112,'LAP. PENJUALAN GRABFOOD'!F112,'LAP. PENJUALAN SHOPEFOOD'!F112) -> 3173500 | G8: =SUM('LAP. PENJUALAN REGULER'!G112,'LAP. PENJUALAN GOFOOD'!G112,'LAP. PENJUALAN GRABFOOD'!G112,'LAP. PENJUALAN SHOPEFOOD'!G112) -> 3484000 | H8: =SUM('LAP. PENJUALAN REGULER'!H112,'LAP. PENJUALAN GOFOOD'!H112,'LAP. PENJUALAN GRABFOOD'!H112,'LAP. PENJUALAN SHOPEFOOD'!H112) -> 4920500 | I8: =SUM('LAP. PENJUALAN REGULER'!I112,'LAP. PENJUALAN GOFOOD'!I112,'LAP. PENJUALAN GRABFOOD'!I112,'LAP. PENJUALAN SHOPEFOOD'!I112) -> 4009000 | J8: =SUM('LAP. PENJUALAN REGULER'!J112,'LAP. PENJUALAN GOFOOD'!J112,'LAP. PENJUALAN GRABFOOD'!J112,'LAP. PENJUALAN SHOPEFOOD'!J112) -> 3711500 | K8: =SUM('LAP. PENJUALAN REGULER'!K112,'LAP. PENJUALAN GOFOOD'!K112,'LAP. PENJUALAN GRABFOOD'!K112,'LAP. PENJUALAN SHOPEFOOD'!K112) -> 0 | ... M8: =SUM('LAP. PENJUALAN REGULER'!M112,'LAP. PENJUALAN GOFOOD'!M112,'LAP. PENJUALAN GRABFOOD'!M112,'LAP. PENJUALAN SHOPEFOOD'!M112) -> 0 | N8: =SUM(D8:M8) -> 27391500
B9: Komisi grab food | N9: =SUM(D9:M9) -> 0
B10: Komisi gofood | N10: =SUM(D10:M10) -> 0
B11: Komisi shopee food | N11: =SUM(D11:M11) -> 0
B12: Koreksi | N12: =SUM(D12:M12) -> 0
B13: Discount | N13: =SUM(D13:M13) -> 0
B14: Tax/ pajak ( FULL PPN) | N14: =SUM(D14:M14) -> 0
B15: Penjualan Bersih | D15: =D8-D9-D10-D11-D12-D13-D14 -> 4454000 | E15: =E8-E9-E10-E11-E12-E13-E14 -> 3639000 | F15: =F8-F9-F10-F11-F12-F13-F14 -> 3173500 | G15: =G8-G9-G10-G11-G12-G13-G14 -> 3484000 | H15: =H8-H9-H10-H11-H12-H13-H14 -> 4920500 | I15: =I8-I9-I10-I11-I12-I13-I14 -> 4009000 | J15: =J8-J9-J10-J11-J12-J13-J14 -> 3711500 | K15: =K8-K9-K10-K11-K12-K13-K14 -> 0 | ... M15: =M8-M9-M10-M11-M12-M13-M14 -> 0 | N15: =SUM(D15:M15) -> 27391500
B16: Transferan grab food | N16: =SUM(D16:M16) -> 0
B17: Transferan gofood | N17: =SUM(D17:M17) -> 0
B18: Transferan shopee food | N18: =SUM(D18:M18) -> 0
B19: Q-Ris Gopay | N19: =SUM(D19:M19) -> 0
B20: Q-Ris Bank BSI | D20: 830500 | E20: 1042500 | F20: 787000 | G20: 607000 | H20: 1541500 | I20: 626500 | J20: 436000 | N20: =SUM(D20:M20) -> 5871000
B21: Q-Ris Ovo | N21: =SUM(D21:M21) -> 0
B22: Tax/Pajak ( SEBAGIAN PPN) | N22: =SUM(D22:M22) -> 0
B23: Selisih Kas | N23: =SUM(D23:M23) -> 0
N24: =SUM(D24:M24) -> 0
B25: Kas yang harus disetor | D25: =D15-D17-D18-D19-D20-D21-D22-D23-D16 -> 3623500 | E25: =E15-E17-E18-E19-E20-E21-E22-E23-E16 -> 2596500 | F25: =F15-F17-F18-F19-F20-F21-F22-F23-F16 -> 2386500 | G25: =G15-G17-G18-G19-G20-G21-G22-G23-G16 -> 2877000 | H25: =H15-H17-H18-H19-H20-H21-H22-H23-H16 -> 3379000 | I25: =I15-I17-I18-I19-I20-I21-I22-I23-I16 -> 3382500 | J25: =J15-J17-J18-J19-J20-J21-J22-J23-J16 -> 3275500 | K25: =K15-K17-K18-K19-K20-K21-K22-K23-K16 -> 0 | ... M25: =M15-M17-M18-M19-M20-M21-M22-M23-M16 -> 0 | N25: =SUM(D25:M25) -> 21520500
B26: No.Rizet PLU / TTL | N26: =SUM(D26:M26) -> 0
B27: Penjualan Mikas | N27: =SUM(D27:M27) -> 0
B28: Penjualan Lain - lain | N28: =SUM(D28:M28) -> 0
B29: Setor Bank | N29: =SUM(D29:M29) -> 0
B30: Setor Pihak Gedung | N30: =SUM(D30:M30) -> 0
B31: Jumlah Pembeli | D31: ='LAP. PENJUALAN REGULER'!D113 -> 81 | E31: ='LAP. PENJUALAN REGULER'!E113 -> 90 | F31: ='LAP. PENJUALAN REGULER'!F113 -> 87 | G31: ='LAP. PENJUALAN REGULER'!G113 -> 85 | H31: ='LAP. PENJUALAN REGULER'!H113 -> 96 | I31: ='LAP. PENJUALAN REGULER'!I113 -> 111 | J31: ='LAP. PENJUALAN REGULER'!J113 -> 96 | K31: ='LAP. PENJUALAN REGULER'!K113 -> 0 | ... M31: ='LAP. PENJUALAN REGULER'!M113 -> 0 | N31: =SUM(D31:M31) -> 646
M33: PARAF

Sheet LAP. PENJUALAN REGULER
A2: LAPORAN PENJUALAN REGULER
M3: Cabang : | O3: =LPKK!Q4 -> SC MARABAHAN
M4: Periode : | O4: =LPKK!Q5 -> 1-7 JULI 2026
A6: NO | B6: PRODUCT | C6: =B6 -> PRODUCT | D6: 1 | E6: 2 | F6: 3 | G6: 4 | H6: 5 | I6: 6 | J6: 7 | N6: TOTAL | P6: % | Q6: FC ITEM | R6: CON FC | S6: Harga
D7: Rabu | E7: Kamis | F7: Jum`at | G7: Sabtu | H7: Minggu | I7: Senin | J7: Sabtu | N7: UNIT | O7: ( Rp ) | S7: ( Unit )
A8: 1 | B8: Dada | C8: =B8 -> Dada | D8: 17 | E8: 13 | F8: 14 | G8: 13 | H8: 17 | I8: 23 | J8: 19 | N8: =SUM(D8:M8) -> 116 | O8: =N8*S8 -> 1740000 | P8: =(O8/O112)*100 -> 6.3523356 | Q8: ='FOOD COST PRODUCT'!G7 -> 0.54255249 | R8: =P8*Q8 -> 3.4464755 | S8: 15000 | U8: =D8*S8 -> 255000 | V8: =E8*S8 -> 195000 | W8: =F8*S8 -> 210000 | X8: =G8*S8 -> 195000 | Y8: =H8*S8 -> 255000 | Z8: =I8*S8 -> 345000 | AA8: =J8*S8 -> 285000 | AB8: =K8*S8 -> 0 | AC8: =L8*S8 -> 0 | AD8: =M8*S8 -> 0
A9: 2 | B9: Paha Atas | C9: =B9 -> Paha Atas | D9: 17 | E9: 12 | F9: 18 | G9: 10 | H9: 21 | I9: 8 | J9: 9 | N9: =SUM(D9:M9) -> 95 | O9: =N9*S9 -> 1425000 | P9: =(O9/O112)*100 -> 5.2023438 | Q9: ='FOOD COST PRODUCT'!G8 -> 0.55598999 | R9: =P9*Q9 -> 2.8924511 | S9: 15000 | U9: =D9*S9 -> 255000 | V9: =E9*S9 -> 180000 | W9: =F9*S9 -> 270000 | X9: =G9*S9 -> 150000 | Y9: =H9*S9 -> 315000 | Z9: =I9*S9 -> 120000 | AA9: =J9*S9 -> 135000 | AB9: =K9*S9 -> 0 | AC9: =L9*S9 -> 0 | AD9: =M9*S9 -> 0
A10: 3 | B10: Paha Bawah | C10: =B10 -> Paha Bawah | D10: 5 | E10: 4 | F10: 2 | H10: 2 | I10: 10 | J10: 5 | N10: =SUM(D10:M10) -> 28 | O10: =N10*S10 -> 378000 | P10: =(O10/O112)*100 -> 1.3799901 | Q10: ='FOOD COST PRODUCT'!G9 -> 0.48339166 | R10: =P10*Q10 -> 0.66707572 | S10: 13500 | U10: =D10*S10 -> 67500 | V10: =E10*S10 -> 54000 | W10: =F10*S10 -> 27000 | X10: =G10*S10 -> 0 | Y10: =H10*S10 -> 27000 | Z10: =I10*S10 -> 135000 | AA10: =J10*S10 -> 67500 | AB10: =K10*S10 -> 0 | AC10: =L10*S10 -> 0 | AD10: =M10*S10 -> 0
A11: 4 | B11: Sayap | C11: =B11 -> Sayap | D11: 11 | E11: 2 | F11: 5 | G11: 4 | H11: 3 | I11: 2 | N11: =SUM(D11:M11) -> 27 | O11: =N11*S11 -> 337500 | P11: =(O11/O112)*100 -> 1.2321341 | Q11: ='FOOD COST PRODUCT'!G10 -> 0.49038946 | R11: =P11*Q11 -> 0.60422555 | S11: 12500 | U11: =D11*S11 -> 137500 | V11: =E11*S11 -> 25000 | W11: =F11*S11 -> 62500 | X11: =G11*S11 -> 50000 | Y11: =H11*S11 -> 37500 | Z11: =I11*S11 -> 25000 | AA11: =J11*S11 -> 0 | AB11: =K11*S11 -> 0 | AC11: =L11*S11 -> 0 | AD11: =M11*S11 -> 0
A12: 5 | B12: Chicken Strips | C12: =B12 -> Chicken Strips | D12: 3 | E12: 6 | F12: 6 | G12: 7 | H12: 3 | I12: 1 | J12: 3 | N12: =SUM(D12:M12) -> 29 | O12: =N12*S12 -> 377000 | P12: =(O12/O112)*100 -> 1.3763394 | Q12: ='FOOD COST PRODUCT'!G11 -> 0.4245776 | R12: =P12*Q12 -> 0.58436287 | S12: 13000 | U12: =D12*S12 -> 39000 | V12: =E12*S12 -> 78000 | W12: =F12*S12 -> 78000 | X12: =G12*S12 -> 91000 | Y12: =H12*S12 -> 39000 | Z12: =I12*S12 -> 13000 | AA12: =J12*S12 -> 39000 | AB12: =K12*S12 -> 0 | AC12: =L12*S12 -> 0 | AD12: =M12*S12 -> 0
A13: 6 | B13: Chicken Steak | C13: =B13 -> Chicken Steak | D13: 1 | E13: 1 | H13: 3 | J13: 2 | N13: =SUM(D13:M13) -> 7 | O13: =N13*S13 -> 98000 | P13: =(O13/O112)*100 -> 0.35777522 | Q13: ='FOOD COST PRODUCT'!G12 -> 2.2252445 | R13: =P13*Q13 -> 0.79613733 | S13: 14000 | U13: =D13*S13 -> 14000 | V13: =E13*S13 -> 14000 | W13: =F13*S13 -> 0 | X13: =G13*S13 -> 0 | Y13: =H13*S13 -> 42000 | Z13: =I13*S13 -> 0 | AA13: =J13*S13 -> 28000 | AB13: =K13*S13 -> 0 | AC13: =L13*S13 -> 0 | AD13: =M13*S13 -> 0
A14: 7 | C14: Dada Lembut | N14: =SUM(D14:M14) -> 0 | O14: =N14*S14 -> 0 | P14: =(O14/O112)*100 -> 0 | Q14: ='FOOD COST PRODUCT'!G13 -> 0.54255249 | R14: =P14*Q14 -> 0 | S14: 15000 | U14: =D14*S14 -> 0 | V14: =E14*S14 -> 0 | W14: =F14*S14 -> 0 | X14: =G14*S14 -> 0 | Y14: =H14*S14 -> 0 | Z14: =I14*S14 -> 0 | AA14: =J14*S14 -> 0 | AB14: =K14*S14 -> 0 | AC14: =L14*S14 -> 0 | AD14: =M14*S14 -> 0
A15: 8 | B15: French Fries | C15: =B15 -> French Fries | D15: 8 | E15: 3 | G15: 1 | H15: 4 | I15: 2 | N15: =SUM(D15:M15) -> 18 | O15: =N15*S15 -> 216000 | P15: =(O15/O112)*100 -> 0.7885658 | Q15: ='FOOD COST PRODUCT'!G14 -> 0.36748104 | R15: =P15*Q15 -> 0.28978298 | S15: 12000 | U15: =D15*S15 -> 96000 | V15: =E15*S15 -> 36000 | W15: =F15*S15 -> 0 | X15: =G15*S15 -> 12000 | Y15: =H15*S15 -> 48000 | Z15: =I15*S15 -> 24000 | AA15: =J15*S15 -> 0 | AB15: =K15*S15 -> 0 | AC15: =L15*S15 -> 0 | AD15: =M15*S15 -> 0
A16: 9 | B16: Nasi | C16: =B16 -> Nasi | D16: 24 | E16: 26 | F16: 15 | G16: 13 | H16: 34 | I16: 22 | J16: 15 | N16: =SUM(D16:M16) -> 149 | O16: =N16*S16 -> 745000 | P16: =(O16/O112)*100 -> 2.7198218 | Q16: ='FOOD COST PRODUCT'!G15 -> 0.29554656 | R16: =P16*Q16 -> 0.80383399 | S16: 5000 | U16: =D16*S16 -> 120000 | V16: =E16*S16 -> 130000 | W16: =F16*S16 -> 75000 | X16: =G16*S16 -> 65000 | Y16: =H16*S16 -> 170000 | Z16: =I16*S16 -> 110000 | AA16: =J16*S16 -> 75000 | AB16: =K16*S16 -> 0 | AC16: =L16*S16 -> 0 | AD16: =M16*S16 -> 0
A17: 10 | B17: Perkedel | C17: =B17 -> Perkedel | D17: 14 | E17: 8 | F17: 9 | G17: 7 | H17: 5 | I17: 9 | J17: 6 | N17: =SUM(D17:M17) -> 58 | O17: =N17*S17 -> 348000 | P17: =(O17/O112)*100 -> 1.2704671 | Q17: ='FOOD COST PRODUCT'!G16 -> 0.75133429 | R17: =P17*Q17 -> 0.95454551 | S17: 6000 | U17: =D17*S17 -> 84000 | V17: =E17*S17 -> 48000 | W17: =F17*S17 -> 54000 | X17: =G17*S17 -> 42000 | Y17: =H17*S17 -> 30000 | Z17: =I17*S17 -> 54000 | AA17: =J17*S17 -> 36000 | AB17: =K17*S17 -> 0 | AC17: =L17*S17 -> 0 | AD17: =M17*S17 -> 0
A18: 11 | B18: Chicken Burger | C18: =B18 -> Chicken Burger | D18: 3 | E18: 2 | F18: 1 | G18: 1 | H18: 1 | I18: 1 | J18: 2 | N18: =SUM(D18:M18) -> 11 | O18: =N18*S18 -> 176000 | P18: =(O18/O112)*100 -> 0.64253509 | Q18: ='FOOD COST PRODUCT'!G17 -> 0.43699995 | R18: =P18*Q18 -> 0.2807878 | S18: 16000 | U18: =D18*S18 -> 48000 | V18: =E18*S18 -> 32000 | W18: =F18*S18 -> 16000 | X18: =G18*S18 -> 16000 | Y18: =H18*S18 -> 16000 | Z18: =I18*S18 -> 16000 | AA18: =J18*S18 -> 32000 | AB18: =K18*S18 -> 0 | AC18: =L18*S18 -> 0 | AD18: =M18*S18 -> 0
A19: 12 | B19: Cheese Burger | C19: =B19 -> Cheese Burger | D19: 4 | E19: 2 | F19: 1 | G19: 2 | H19: 3 | J19: 1 | N19: =SUM(D19:M19) -> 13 | O19: =N19*S19 -> 234000 | P19: =(O19/O112)*100 -> 0.85427961 | Q19: ='FOOD COST PRODUCT'!G18 -> 0.45322218 | R19: =P19*Q19 -> 0.38717847 | S19: 18000 | U19: =D19*S19 -> 72000 | V19: =E19*S19 -> 36000 | W19: =F19*S19 -> 18000 | X19: =G19*S19 -> 36000 | Y19: =H19*S19 -> 54000 | Z19: =I19*S19 -> 0 | AA19: =J19*S19 -> 18000 | AB19: =K19*S19 -> 0 | AC19: =L19*S19 -> 0 | AD19: =M19*S19 -> 0
A20: 13 | B20: Nasi Goreng | C20: =B20 -> Nasi Goreng | D20: 1 | F20: 3 | G20: 3 | N20: =SUM(D20:M20) -> 7 | O20: =N20*S20 -> 119000 | P20: =(O20/O112)*100 -> 0.43444134 | Q20: ='FOOD COST PRODUCT'!G19 -> 0.58392147 | R20: =P20*Q20 -> 0.25367963 | S20: 17000 | U20: =D20*S20 -> 17000 | V20: =E20*S20 -> 0 | W20: =F20*S20 -> 51000 | X20: =G20*S20 -> 51000 | Y20: =H20*S20 -> 0 | Z20: =I20*S20 -> 0 | AA20: =J20*S20 -> 0 | AB20: =K20*S20 -> 0 | AC20: =L20*S20 -> 0 | AD20: =M20*S20 -> 0
A21: 14 | B21: Telor Ceplok | C21: Nasi Goreng Spesial | E21: 1 | F21: 1 | G21: 4 | H21: 2 | J21: 1 | N21: =SUM(D21:M21) -> 9 | O21: =N21*S21 -> 180000 | P21: =(O21/O112)*100 -> 0.65713816 | Q21: ='FOOD COST PRODUCT'!G20 -> 0.5153519 | R21: =P21*Q21 -> 0.3386574 | S21: 20000 | U21: =D21*S21 -> 0 | V21: =E21*S21 -> 20000 | W21: =F21*S21 -> 20000 | X21: =G21*S21 -> 80000 | Y21: =H21*S21 -> 40000 | Z21: =I21*S21 -> 0 | AA21: =J21*S21 -> 20000 | AB21: =K21*S21 -> 0 | AC21: =L21*S21 -> 0 | AD21: =M21*S21 -> 0
A22: 15 | B22: Nasi Goreng Telor Ceplok | C22: Mie Goreng | D22: 1 | H22: 1 | N22: =SUM(D22:M22) -> 2 | O22: =N22*S22 -> 34000 | P22: =(O22/O112)*100 -> 0.1241261 | Q22: ='FOOD COST PRODUCT'!G21 -> 0.55171679 | R22: =P22*Q22 -> 0.068482452 | S22: 17000 | U22: =D22*S22 -> 17000 | V22: =E22*S22 -> 0 | W22: =F22*S22 -> 0 | X22: =G22*S22 -> 0 | Y22: =H22*S22 -> 17000 | Z22: =I22*S22 -> 0 | AA22: =J22*S22 -> 0 | AB22: =K22*S22 -> 0 | AC22: =L22*S22 -> 0 | AD22: =M22*S22 -> 0
A23: 16 | C23: Chicken 2 Pcs | D23: 1 | I23: 1 | N23: =SUM(D23:M23) -> 2 | O23: =N23*S23 -> 52000 | P23: =(O23/O112)*100 -> 0.18983991 | Q23: ='FOOD COST PRODUCT'!G22 -> 0.56400287 | R23: =P23*Q23 -> 0.10707026 | S23: 26000 | U23: =D23*S23 -> 26000 | V23: =E23*S23 -> 0 | W23: =F23*S23 -> 0 | X23: =G23*S23 -> 0 | Y23: =H23*S23 -> 0 | Z23: =I23*S23 -> 26000 | AA23: =J23*S23 -> 0 | AB23: =K23*S23 -> 0 | AC23: =L23*S23 -> 0 | AD23: =M23*S23 -> 0
A24: 17 | C24: Steak Blackpaper | H24: 1 | J24: 1 | N24: =SUM(D24:M24) -> 2 | O24: =N24*S24 -> 30000 | P24: =(O24/O112)*100 -> 0.10952303 | Q24: ='FOOD COST PRODUCT'!G23 -> 0 | R24: =P24*Q24 -> 0 | S24: 15000 | U24: =D24*S24 -> 0 | V24: =E24*S24 -> 0 | W24: =F24*S24 -> 0 | X24: =G24*S24 -> 0 | Y24: =H24*S24 -> 15000 | Z24: =I24*S24 -> 0 | AA24: =J24*S24 -> 15000 | AB24: =K24*S24 -> 0 | AC24: =L24*S24 -> 0 | AD24: =M24*S24 -> 0
A25: 18 | N25: =SUM(D25:M25) -> 0 | O25: =N25*S25 -> 0 | P25: =(O25/O112)*100 -> 0 | R25: =P25*Q25 -> 0 | U25: =D25*S25 -> 0 | V25: =E25*S25 -> 0 | W25: =F25*S25 -> 0 | X25: =G25*S25 -> 0 | Y25: =H25*S25 -> 0 | Z25: =I25*S25 -> 0 | AA25: =J25*S25 -> 0 | AB25: =K25*S25 -> 0 | AC25: =L25*S25 -> 0 | AD25: =M25*S25 -> 0
A26: 19 | B26: Paket Rocket 1 | C26: Paket Sonic 1 | D26: 40 | E26: 30 | F26: 25 | G26: 31 | H26: 45 | I26: 49 | J26: 28 | N26: =SUM(D26:M26) -> 248 | O26: =N26*S26 -> 3224000 | P26: =(O26/O112)*100 -> 11.770075 | Q26: ='FOOD COST PRODUCT'!G25 -> 0.84390064 | R26: =P26*Q26 -> 9.9327736 | S26: 13000 | U26: =D26*S26 -> 520000 | V26: =E26*S26 -> 390000 | W26: =F26*S26 -> 325000 | X26: =G26*S26 -> 403000 | Y26: =H26*S26 -> 585000 | Z26: =I26*S26 -> 637000 | AA26: =J26*S26 -> 364000 | AB26: =K26*S26 -> 0 | AC26: =L26*S26 -> 0 | AD26: =M26*S26 -> 0
A27: 20 | B27: Paket Rocket 2 | C27: Paket Sonic 2 | D27: 45 | E27: 24 | F27: 9 | G27: 23 | H27: 15 | I27: 41 | J27: 21 | N27: =SUM(D27:M27) -> 178 | O27: =N27*S27 -> 2670000 | P27: =(O27/O112)*100 -> 9.7475494 | Q27: ='FOOD COST PRODUCT'!G26 -> 2.3996175 | R27: =P27*Q27 -> 23.39039 | S27: 15000 | U27: =D27*S27 -> 675000 | V27: =E27*S27 -> 360000 | W27: =F27*S27 -> 135000 | X27: =G27*S27 -> 345000 | Y27: =H27*S27 -> 225000 | Z27: =I27*S27 -> 615000 | AA27: =J27*S27 -> 315000 | AB27: =K27*S27 -> 0 | AC27: =L27*S27 -> 0 | AD27: =M27*S27 -> 0
A28: 21 | B28: Paket Rocket 3 | C28: Paket Sonic 3 | D28: 4 | E28: 2 | F28: 6 | G28: 4 | H28: 3 | I28: 3 | J28: 2 | N28: =SUM(D28:M28) -> 24 | O28: =N28*S28 -> 624000 | P28: =(O28/O112)*100 -> 2.278079 | Q28: ='FOOD COST PRODUCT'!G27 -> 0.49919721 | R28: =P28*Q28 -> 1.1372107 | S28: 26000 | U28: =D28*S28 -> 104000 | V28: =E28*S28 -> 52000 | W28: =F28*S28 -> 156000 | X28: =G28*S28 -> 104000 | Y28: =H28*S28 -> 78000 | Z28: =I28*S28 -> 78000 | AA28: =J28*S28 -> 52000 | AB28: =K28*S28 -> 0 | AC28: =L28*S28 -> 0 | AD28: =M28*S28 -> 0
A29: 22 | B29: Paket Rocket 4 | C29: Paket Sonic 4 | D29: 5 | E29: 4 | F29: 5 | G29: 5 | H29: 1 | I29: 4 | J29: 6 | N29: =SUM(D29:M29) -> 30 | O29: =N29*S29 -> 780000 | P29: =(O29/O112)*100 -> 2.8475987 | Q29: ='FOOD COST PRODUCT'!G28 -> 0.50694961 | R29: =P29*Q29 -> 1.4435891 | S29: 26000 | U29: =D29*S29 -> 130000 | V29: =E29*S29 -> 104000 | W29: =F29*S29 -> 130000 | X29: =G29*S29 -> 130000 | Y29: =H29*S29 -> 26000 | Z29: =I29*S29 -> 104000 | AA29: =J29*S29 -> 156000 | AB29: =K29*S29 -> 0 | AC29: =L29*S29 -> 0 | AD29: =M29*S29 -> 0
A30: 23 | B30: Paket Rocket 5 | C30: Paket Sonic 5 | F30: 1 | N30: =SUM(D30:M30) -> 1 | O30: =N30*S30 -> 25000 | P30: =(O30/O112)*100 -> 0.091269189 | Q30: ='FOOD COST PRODUCT'!G29 -> 0.45015268 | R30: =P30*Q30 -> 0.04108507 | S30: 25000 | U30: =D30*S30 -> 0 | V30: =E30*S30 -> 0 | W30: =F30*S30 -> 25000 | X30: =G30*S30 -> 0 | Y30: =H30*S30 -> 0 | Z30: =I30*S30 -> 0 | AA30: =J30*S30 -> 0 | AB30: =K30*S30 -> 0 | AC30: =L30*S30 -> 0 | AD30: =M30*S30 -> 0
A31: 24 | B31: Paket Rocket 6 | C31: Paket Sonic 6 | D31: 2 | F31: 1 | G31: 2 | J31: 2 | N31: =SUM(D31:M31) -> 7 | O31: =N31*S31 -> 210000 | P31: =(O31/O112)*100 -> 0.76666119 | Q31: ='FOOD COST PRODUCT'!G30 -> 0.50788185 | R31: =P31*Q31 -> 0.3893733 | S31: 30000 | U31: =D31*S31 -> 60000 | V31: =E31*S31 -> 0 | W31: =F31*S31 -> 30000 | X31: =G31*S31 -> 60000 | Y31: =H31*S31 -> 0 | Z31: =I31*S31 -> 0 | AA31: =J31*S31 -> 60000 | AB31: =K31*S31 -> 0 | AC31: =L31*S31 -> 0 | AD31: =M31*S31 -> 0
A32: 25 | B32: Paket Rocket 7 | C32: Paket Sonic 7 | D32: 1 | F32: 2 | H32: 1 | I32: 1 | J32: 1 | N32: =SUM(D32:M32) -> 6 | O32: =N32*S32 -> 126000 | P32: =(O32/O112)*100 -> 0.45999671 | Q32: ='FOOD COST PRODUCT'!G31 -> 0.6753924 | R32: =P32*Q32 -> 0.31067829 | S32: 21000 | U32: =D32*S32 -> 21000 | V32: =E32*S32 -> 0 | W32: =F32*S32 -> 42000 | X32: =G32*S32 -> 0 | Y32: =H32*S32 -> 21000 | Z32: =I32*S32 -> 21000 | AA32: =J32*S32 -> 21000 | AB32: =K32*S32 -> 0 | AC32: =L32*S32 -> 0 | AD32: =M32*S32 -> 0
A33: 26 | C33: Paket Sonic 8 | G33: 1 | H33: 4 | I33: 1 | N33: =SUM(D33:M33) -> 6 | O33: =N33*S33 -> 150000 | P33: =(O33/O112)*100 -> 0.54761514 | Q33: ='FOOD COST PRODUCT'!G32 -> 1.4755092 | R33: =P33*Q33 -> 0.80801119 | S33: 25000 | U33: =D33*S33 -> 0 | V33: =E33*S33 -> 0 | W33: =F33*S33 -> 0 | X33: =G33*S33 -> 25000 | Y33: =H33*S33 -> 100000 | Z33: =I33*S33 -> 25000 | AA33: =J33*S33 -> 0 | AB33: =K33*S33 -> 0 | AC33: =L33*S33 -> 0 | AD33: =M33*S33 -> 0
A34: 27 | B34: Paket Rocket 8 | C34: Paket Sonic 9 | N34: =SUM(D34:M34) -> 0 | O34: =N34*S34 -> 0 | P34: =(O34/O112)*100 -> 0 | Q34: ='FOOD COST PRODUCT'!G33 -> 0.63065712 | R34: =P34*Q34 -> 0 | U34: =D34*S34 -> 0 | V34: =E34*S34 -> 0 | W34: =F34*S34 -> 0 | X34: =G34*S34 -> 0 | Y34: =H34*S34 -> 0 | Z34: =I34*S34 -> 0 | AA34: =J34*S34 -> 0 | AB34: =K34*S34 -> 0 | AC34: =L34*S34 -> 0 | AD34: =M34*S34 -> 0
A35: 28 | O35: =N35*S35 -> 0 | P35: =(O35/O112)*100 -> 0 | R35: =P35*Q35 -> 0 | U35: =D35*S35 -> 0 | V35: =E35*S35 -> 0 | W35: =F35*S35 -> 0 | X35: =G35*S35 -> 0 | Y35: =H35*S35 -> 0 | Z35: =I35*S35 -> 0 | AA35: =J35*S35 -> 0 | AB35: =K35*S35 -> 0 | AC35: =L35*S35 -> 0 | AD35: =M35*S35 -> 0
A36: 29 | B36: Paket Rocket 9 | C36: Paket Gepso 1 | D36: 4 | F36: 1 | G36: 1 | H36: 2 | J36: 1 | N36: =SUM(D36:M36) -> 9 | O36: =N36*S36 -> 216000 | P36: =(O36/O112)*100 -> 0.7885658 | Q36: ='FOOD COST PRODUCT'!G35 -> 0.75815065 | R36: =P36*Q36 -> 0.59785167 | S36: 24000 | U36: =D36*S36 -> 96000 | V36: =E36*S36 -> 0 | W36: =F36*S36 -> 24000 | X36: =G36*S36 -> 24000 | Y36: =H36*S36 -> 48000 | Z36: =I36*S36 -> 0 | AA36: =J36*S36 -> 24000 | AB36: =K36*S36 -> 0 | AC36: =L36*S36 -> 0 | AD36: =M36*S36 -> 0
A37: 30 | B37: Paket Rocket 10 | C37: Paket Gepso 2 | D37: 2 | G37: 1 | H37: 2 | I37: 1 | N37: =SUM(D37:M37) -> 6 | O37: =N37*S37 -> 150000 | P37: =(O37/O112)*100 -> 0.54761514 | Q37: ='FOOD COST PRODUCT'!G36 -> 0.74366139 | R37: =P37*Q37 -> 0.40724023 | S37: 25000 | U37: =D37*S37 -> 50000 | V37: =E37*S37 -> 0 | W37: =F37*S37 -> 0 | X37: =G37*S37 -> 25000 | Y37: =H37*S37 -> 50000 | Z37: =I37*S37 -> 25000 | AA37: =J37*S37 -> 0 | AB37: =K37*S37 -> 0 | AC37: =L37*S37 -> 0 | AD37: =M37*S37 -> 0
A38: 31 | C38: Paket Gepso 3 | D38: 1 | E38: 2 | F38: 1 | G38: 3 | H38: 7 | I38: 1 | J38: 5 | N38: =SUM(D38:M38) -> 20 | O38: =N38*S38 -> 540000 | P38: =(O38/O112)*100 -> 1.9714145 | Q38: ='FOOD COST PRODUCT'!G37 -> 0.74829758 | R38: =P38*Q38 -> 1.4752047 | S38: 27000 | U38: =D38*S38 -> 27000 | V38: =E38*S38 -> 54000 | W38: =F38*S38 -> 27000 | X38: =G38*S38 -> 81000 | Y38: =H38*S38 -> 189000 | Z38: =I38*S38 -> 27000 | AA38: =J38*S38 -> 135000 | AB38: =K38*S38 -> 0 | AC38: =L38*S38 -> 0 | AD38: =M38*S38 -> 0
A39: 32 | C39: Paket Gepso 4 | F39: 1 | G39: 2 | H39: 2 | I39: 2 | J39: 1 | N39: =SUM(D39:M39) -> 8 | O39: =N39*S39 -> 216000 | P39: =(O39/O112)*100 -> 0.7885658 | Q39: ='FOOD COST PRODUCT'!G38 -> 0.75576286 | R39: =P39*Q39 -> 0.59596874 | S39: 27000 | U39: =D39*S39 -> 0 | V39: =E39*S39 -> 0 | W39: =F39*S39 -> 27000 | X39: =G39*S39 -> 54000 | Y39: =H39*S39 -> 54000 | Z39: =I39*S39 -> 54000 | AA39: =J39*S39 -> 27000 | AB39: =K39*S39 -> 0 | AC39: =L39*S39 -> 0 | AD39: =M39*S39 -> 0
A40: 33 | B40: Paket Roma 1 | O40: =N40*S40 -> 0 | P40: =(O40/O112)*100 -> 0 | R40: =P40*Q40 -> 0 | U40: =D40*S40 -> 0 | V40: =E40*S40 -> 0 | W40: =F40*S40 -> 0 | X40: =G40*S40 -> 0 | Y40: =H40*S40 -> 0 | Z40: =I40*S40 -> 0 | AA40: =J40*S40 -> 0 | AB40: =K40*S40 -> 0 | AC40: =L40*S40 -> 0 | AD40: =M40*S40 -> 0
A41: 34 | B41: Paket Roma 2 | C41: Paket Prenic 1 | E41: 1 | F41: 4 | H41: 2 | N41: =SUM(D41:M41) -> 7 | O41: =N41*S41 -> 175000 | P41: =(O41/O112)*100 -> 0.63888433 | Q41: ='FOOD COST PRODUCT'!G40 -> 0.51554206 | R41: =P41*Q41 -> 0.32937174 | S41: 25000 | U41: =D41*S41 -> 0 | V41: =E41*S41 -> 25000 | W41: =F41*S41 -> 100000 | X41: =G41*S41 -> 0 | Y41: =H41*S41 -> 50000 | Z41: =I41*S41 -> 0 | AA41: =J41*S41 -> 0 | AB41: =K41*S41 -> 0 | AC41: =L41*S41 -> 0 | AD41: =M41*S41 -> 0
A42: 35 | B42: Paket Roma 3 | C42: Paket Prenic 2 | H42: 1 | N42: =SUM(D42:M42) -> 1 | O42: =N42*S42 -> 26000 | P42: =(O42/O112)*100 -> 0.094919957 | Q42: ='FOOD COST PRODUCT'!G41 -> 0.47793573 | R42: =P42*Q42 -> 0.045365639 | S42: 26000 | U42: =D42*S42 -> 0 | V42: =E42*S42 -> 0 | W42: =F42*S42 -> 0 | X42: =G42*S42 -> 0 | Y42: =H42*S42 -> 26000 | Z42: =I42*S42 -> 0 | AA42: =J42*S42 -> 0 | AB42: =K42*S42 -> 0 | AC42: =L42*S42 -> 0 | AD42: =M42*S42 -> 0
A43: 36 | B43: Paket Roma 4 | C43: Paket Prenic 3 | N43: =SUM(D43:M43) -> 0 | O43: =N43*S43 -> 0 | P43: =(O43/O112)*100 -> 0 | Q43: ='FOOD COST PRODUCT'!G42 -> 0.60394133 | R43: =P43*Q43 -> 0 | S43: 25000 | U43: =D43*S43 -> 0 | V43: =E43*S43 -> 0 | W43: =F43*S43 -> 0 | X43: =G43*S43 -> 0 | Y43: =H43*S43 -> 0 | Z43: =I43*S43 -> 0 | AA43: =J43*S43 -> 0 | AB43: =K43*S43 -> 0 | AC43: =L43*S43 -> 0 | AD43: =M43*S43 -> 0
A44: 37 | B44: Paket Roma 5 | C44: Paket Prenic 4 | N44: =SUM(D44:M44) -> 0 | O44: =N44*S44 -> 0 | P44: =(O44/O112)*100 -> 0 | Q44: ='FOOD COST PRODUCT'!G43 -> 0.42504714 | R44: =P44*Q44 -> 0 | S44: 23000 | U44: =D44*S44 -> 0 | V44: =E44*S44 -> 0 | W44: =F44*S44 -> 0 | X44: =G44*S44 -> 0 | Y44: =H44*S44 -> 0 | Z44: =I44*S44 -> 0 | AA44: =J44*S44 -> 0 | AB44: =K44*S44 -> 0 | AC44: =L44*S44 -> 0 | AD44: =M44*S44 -> 0
A45: 38 | O45: =N45*S45 -> 0 | P45: =(O45/O112)*100 -> 0 | R45: =P45*Q45 -> 0 | U45: =D45*S45 -> 0 | V45: =E45*S45 -> 0 | W45: =F45*S45 -> 0 | X45: =G45*S45 -> 0 | Y45: =H45*S45 -> 0 | Z45: =I45*S45 -> 0 | AA45: =J45*S45 -> 0 | AB45: =K45*S45 -> 0 | AC45: =L45*S45 -> 0 | AD45: =M45*S45 -> 0
A46: 39 | B46: Paket Geprek 1 | C46: Geprek Sayap | H46: 1 | I46: 1 | N46: =SUM(D46:M46) -> 2 | O46: =N46*S46 -> 30000 | P46: =(O46/O112)*100 -> 0.10952303 | Q46: ='FOOD COST PRODUCT'!G45 -> 0.83075383 | R46: =P46*Q46 -> 0.090986674 | S46: 15000 | U46: =D46*S46 -> 0 | V46: =E46*S46 -> 0 | W46: =F46*S46 -> 0 | X46: =G46*S46 -> 0 | Y46: =H46*S46 -> 15000 | Z46: =I46*S46 -> 15000 | AA46: =J46*S46 -> 0 | AB46: =K46*S46 -> 0 | AC46: =L46*S46 -> 0 | AD46: =M46*S46 -> 0
A47: 40 | B47: Paket Geprek 2 | C47: Geprek Paha Bawah | E47: 1 | J47: 1 | N47: =SUM(D47:M47) -> 2 | O47: =N47*S47 -> 32000 | P47: =(O47/O112)*100 -> 0.11682456 | Q47: ='FOOD COST PRODUCT'!G46 -> 0.80357666 | R47: =P47*Q47 -> 0.093877491 | S47: 16000 | U47: =D47*S47 -> 0 | V47: =E47*S47 -> 16000 | W47: =F47*S47 -> 0 | X47: =G47*S47 -> 0 | Y47: =H47*S47 -> 0 | Z47: =I47*S47 -> 0 | AA47: =J47*S47 -> 16000 | AB47: =K47*S47 -> 0 | AC47: =L47*S47 -> 0 | AD47: =M47*S47 -> 0
A48: 41 | B48: Paket Geprek 3 | C48: Geprek Dada/Paha Atas | D48: 5 | E48: 8 | F48: 5 | G48: 4 | H48: 11 | I48: 2 | J48: 3 | N48: =SUM(D48:M48) -> 38 | O48: =N48*S48 -> 684000 | P48: =(O48/O112)*100 -> 2.497125 | Q48: ='FOOD COST PRODUCT'!G47 -> 0.81507161 | R48: =P48*Q48 -> 2.0353357 | S48: 18000 | U48: =D48*S48 -> 90000 | V48: =E48*S48 -> 144000 | W48: =F48*S48 -> 90000 | X48: =G48*S48 -> 72000 | Y48: =H48*S48 -> 198000 | Z48: =I48*S48 -> 36000 | AA48: =J48*S48 -> 54000 | AB48: =K48*S48 -> 0 | AC48: =L48*S48 -> 0 | AD48: =M48*S48 -> 0
A49: 42 | B49: Geprek Sayap | C49: Sambel Geprek | D49: 1 | E49: 2 | G49: 3 | H49: 4 | I49: 3 | J49: 2 | N49: =SUM(D49:M49) -> 15 | O49: =N49*S49 -> 75000 | P49: =(O49/O112)*100 -> 0.27380757 | Q49: ='FOOD COST PRODUCT'!G48 -> 0.9770345 | R49: =P49*Q49 -> 0.26751944 | S49: 5000 | U49: =D49*S49 -> 5000 | V49: =E49*S49 -> 10000 | W49: =F49*S49 -> 0 | X49: =G49*S49 -> 15000 | Y49: =H49*S49 -> 20000 | Z49: =I49*S49 -> 15000 | AA49: =J49*S49 -> 10000 | AB49: =K49*S49 -> 0 | AC49: =L49*S49 -> 0 | AD49: =M49*S49 -> 0
A50: 43 | O50: =N50*S50 -> 0 | P50: =(O50/O112)*100 -> 0 | R50: =P50*Q50 -> 0 | U50: =D50*S50 -> 0 | V50: =E50*S50 -> 0 | W50: =F50*S50 -> 0 | X50: =G50*S50 -> 0 | Y50: =H50*S50 -> 0 | Z50: =I50*S50 -> 0 | AA50: =J50*S50 -> 0 | AB50: =K50*S50 -> 0 | AC50: =L50*S50 -> 0 | AD50: =M50*S50 -> 0
A51: 44 | B51: Geprek Paha Bawah | C51: Paket Panic 1 | N51: =SUM(D51:M51) -> 0 | O51: =N51*S51 -> 0 | P51: =(O51/O112)*100 -> 0 | Q51: ='FOOD COST PRODUCT'!G50 -> 1.5240593 | R51: =P51*Q51 -> 0 | S51: 24000 | U51: =D51*S51 -> 0 | V51: =E51*S51 -> 0 | W51: =F51*S51 -> 0 | X51: =G51*S51 -> 0 | Y51: =H51*S51 -> 0 | Z51: =I51*S51 -> 0 | AA51: =J51*S51 -> 0 | AB51: =K51*S51 -> 0 | AC51: =L51*S51 -> 0 | AD51: =M51*S51 -> 0
A52: 45 | B52: Geprek Paha Atas / Dada | C52: Paket Panic 2 | D52: 1 | H52: 2 | I52: 1 | N52: =SUM(D52:M52) -> 4 | O52: =N52*S52 -> 100000 | P52: =(O52/O112)*100 -> 0.36507676 | Q52: ='FOOD COST PRODUCT'!G51 -> 1.7886284 | R52: =P52*Q52 -> 0.65298665 | S52: 25000 | U52: =D52*S52 -> 25000 | V52: =E52*S52 -> 0 | W52: =F52*S52 -> 0 | X52: =G52*S52 -> 0 | Y52: =H52*S52 -> 50000 | Z52: =I52*S52 -> 25000 | AA52: =J52*S52 -> 0 | AB52: =K52*S52 -> 0 | AC52: =L52*S52 -> 0 | AD52: =M52*S52 -> 0
A53: 46 | B53: Sambal Geprek | C53: Paket Panic 3 | J53: 3 | N53: =SUM(D53:M53) -> 3 | O53: =N53*S53 -> 57000 | P53: =(O53/O112)*100 -> 0.20809375 | Q53: ='FOOD COST PRODUCT'!G52 -> 0.52080965 | R53: =P53*Q53 -> 0.10837723 | S53: 19000 | U53: =D53*S53 -> 0 | V53: =E53*S53 -> 0 | W53: =F53*S53 -> 0 | X53: =G53*S53 -> 0 | Y53: =H53*S53 -> 0 | Z53: =I53*S53 -> 0 | AA53: =J53*S53 -> 57000 | AB53: =K53*S53 -> 0 | AC53: =L53*S53 -> 0 | AD53: =M53*S53 -> 0
A54: 47 | C54: Paket Panic 4 | G54: 1 | H54: 1 | I54: 1 | N54: =SUM(D54:M54) -> 3 | O54: =N54*S54 -> 75000 | P54: =(O54/O112)*100 -> 0.27380757 | Q54: ='FOOD COST PRODUCT'!G53 -> 0.32937233 | R54: =P54*Q54 -> 0.090184636 | S54: 25000 | U54: =D54*S54 -> 0 | V54: =E54*S54 -> 0 | W54: =F54*S54 -> 0 | X54: =G54*S54 -> 25000 | Y54: =H54*S54 -> 25000 | Z54: =I54*S54 -> 25000 | AA54: =J54*S54 -> 0 | AB54: =K54*S54 -> 0 | AC54: =L54*S54 -> 0 | AD54: =M54*S54 -> 0
A55: 48 | B55: Paket Geprek Matah 1 | O55: =N55*S55 -> 0 | P55: =(O55/O112)*100 -> 0 | R55: =P55*Q55 -> 0 | U55: =D55*S55 -> 0 | V55: =E55*S55 -> 0 | W55: =F55*S55 -> 0 | X55: =G55*S55 -> 0 | Y55: =H55*S55 -> 0 | Z55: =I55*S55 -> 0 | AA55: =J55*S55 -> 0 | AB55: =K55*S55 -> 0 | AC55: =L55*S55 -> 0 | AD55: =M55*S55 -> 0
A56: 49 | B56: Paket Geprek Matah 2 | C56: Cattring 1 | N56: =SUM(D56:M56) -> 0 | O56: =N56*S56 -> 0 | P56: =(O56/O112)*100 -> 0 | Q56: ='FOOD COST PRODUCT'!G55 -> 0.69645136 | R56: =P56*Q56 -> 0 | S56: 13000 | U56: =D56*S56 -> 0 | V56: =E56*S56 -> 0 | W56: =F56*S56 -> 0 | X56: =G56*S56 -> 0 | Y56: =H56*S56 -> 0 | Z56: =I56*S56 -> 0 | AA56: =J56*S56 -> 0 | AB56: =K56*S56 -> 0 | AC56: =L56*S56 -> 0 | AD56: =M56*S56 -> 0
A57: 50 | B57: Paket Geprek Matah 3 | C57: Cattring 2 | N57: =SUM(D57:M57) -> 0 | O57: =N57*S57 -> 0 | P57: =(O57/O112)*100 -> 0 | Q57: ='FOOD COST PRODUCT'!G56 -> 2.2718281 | R57: =P57*Q57 -> 0 | S57: 15000 | U57: =D57*S57 -> 0 | V57: =E57*S57 -> 0 | W57: =F57*S57 -> 0 | X57: =G57*S57 -> 0 | Y57: =H57*S57 -> 0 | Z57: =I57*S57 -> 0 | AA57: =J57*S57 -> 0 | AB57: =K57*S57 -> 0 | AC57: =L57*S57 -> 0 | AD57: =M57*S57 -> 0
A58: 51 | B58: Geprek Matah Sayap | C58: Cattring 3 | N58: =SUM(D58:M58) -> 0 | O58: =N58*S58 -> 0 | P58: =(O58/O112)*100 -> 0 | Q58: ='FOOD COST PRODUCT'!G57 -> 0.65072275 | R58: =P58*Q58 -> 0 | S58: 17000 | U58: =D58*S58 -> 0 | V58: =E58*S58 -> 0 | W58: =F58*S58 -> 0 | X58: =G58*S58 -> 0 | Y58: =H58*S58 -> 0 | Z58: =I58*S58 -> 0 | AA58: =J58*S58 -> 0 | AB58: =K58*S58 -> 0 | AC58: =L58*S58 -> 0 | AD58: =M58*S58 -> 0
A59: 52 | B59: Geprek Matah Paha Bawah | C59: Cuan 3 | D59: 1 | E59: 1 | I59: 2 | N59: =SUM(D59:L59) -> 4 | O59: =N59*S59 -> 60000 | P59: =(O59/O112)*100 -> 0.21904605 | R59: =P59*Q59 -> 0 | S59: 15000 | U59: =D59*S59 -> 15000 | V59: =E59*S59 -> 15000 | W59: =F59*S59 -> 0 | X59: =G59*S59 -> 0 | Y59: =H59*S59 -> 0 | Z59: =I59*S59 -> 30000 | AA59: =J59*S59 -> 0 | AB59: =K59*S59 -> 0 | AC59: =L59*S59 -> 0 | AD59: =M59*S59 -> 0
A60: 53 | B60: Geprek Matah Paha Atas / Dada | C60: Super Sonic 1 | E60: 1 | H60: 1 | N60: =SUM(D60:M60) -> 2 | O60: =N60*S60 -> 150000 | P60: =(O60/O112)*100 -> 0.54761514 | Q60: ='FOOD COST PRODUCT'!G59 -> 0.49456999 | R60: =P60*Q60 -> 0.27083401 | S60: 75000 | U60: =D60*S60 -> 0 | V60: =E60*S60 -> 75000 | W60: =F60*S60 -> 0 | X60: =G60*S60 -> 0 | Y60: =H60*S60 -> 75000 | Z60: =I60*S60 -> 0 | AA60: =J60*S60 -> 0 | AB60: =K60*S60 -> 0 | AC60: =L60*S60 -> 0 | AD60: =M60*S60 -> 0
A61: 54 | B61: Sambal Geprek Matah | C61: Super Sonic 2 | N61: =SUM(D61:M61) -> 0 | O61: =N61*S61 -> 0 | P61: =(O61/O112)*100 -> 0 | Q61: ='FOOD COST PRODUCT'!G60 -> 0.72374837 | R61: =P61*Q61 -> 0 | S61: 85000 | U61: =D61*S61 -> 0 | V61: =E61*S61 -> 0 | W61: =F61*S61 -> 0 | X61: =G61*S61 -> 0 | Y61: =H61*S61 -> 0 | Z61: =I61*S61 -> 0 | AA61: =J61*S61 -> 0 | AB61: =K61*S61 -> 0 | AC61: =L61*S61 -> 0 | AD61: =M61*S61 -> 0
A62: 55 | C62: Super Sonic 3 | E62: 2 | F62: 1 | H62: 1 | I62: 1 | N62: =SUM(D62:M62) -> 5 | O62: =N62*S62 -> 450000 | P62: =(O62/O112)*100 -> 1.6428454 | Q62: ='FOOD COST PRODUCT'!G61 -> 0.60072907 | R62: =P62*Q62 -> 0.986905 | S62: 90000 | U62: =D62*S62 -> 0 | V62: =E62*S62 -> 180000 | W62: =F62*S62 -> 90000 | X62: =G62*S62 -> 0 | Y62: =H62*S62 -> 90000 | Z62: =I62*S62 -> 90000 | AA62: =J62*S62 -> 0 | AB62: =K62*S62 -> 0 | AC62: =L62*S62 -> 0 | AD62: =M62*S62 -> 0
A63: 56 | B63: Paket Geprek Terasi 1 | C63: Super Sonic 4 | D63: 2 | N63: =SUM(D63:M63) -> 2 | O63: =N63*S63 -> 200000 | P63: =(O63/O112)*100 -> 0.73015351 | Q63: ='FOOD COST PRODUCT'!G62 -> 0.78491479 | R63: =P63*Q63 -> 0.57310829 | S63: 100000 | U63: =D63*S63 -> 200000 | V63: =E63*S63 -> 0 | W63: =F63*S63 -> 0 | X63: =G63*S63 -> 0 | Y63: =H63*S63 -> 0 | Z63: =I63*S63 -> 0 | AA63: =J63*S63 -> 0 | AB63: =K63*S63 -> 0 | AC63: =L63*S63 -> 0 | AD63: =M63*S63 -> 0
A64: 57 | B64: Paket Geprek Terasi 2 | C64: SP Blackpaper 3 | D64: 1 | N64: =D64 -> 1 | O64: =N64*S64 -> 21000 | P64: =(O64/O112)*100 -> 0.076666119 | R64: =P64*Q64 -> 0 | S64: 21000 | U64: =D64*S64 -> 21000 | V64: =E64*S64 -> 0 | W64: =F64*S64 -> 0 | X64: =G64*S64 -> 0 | Y64: =H64*S64 -> 0 | Z64: =I64*S64 -> 0 | AA64: =J64*S64 -> 0 | AB64: =K64*S64 -> 0 | AC64: =L64*S64 -> 0 | AD64: =M64*S64 -> 0
A65: 58 | B65: Paket Geprek Terasi 3 | C65: Paket Ceria 1 | N65: =SUM(D65:M65) -> 0 | O65: =N65*S65 -> 0 | P65: =(O65/O112)*100 -> 0 | Q65: ='FOOD COST PRODUCT'!G64 -> 0.69922389 | R65: =P65*Q65 -> 0 | S65: 11000 | U65: =D65*S65 -> 0 | V65: =E65*S65 -> 0 | W65: =F65*S65 -> 0 | X65: =G65*S65 -> 0 | Y65: =H65*S65 -> 0 | Z65: =I65*S65 -> 0 | AA65: =J65*S65 -> 0 | AB65: =K65*S65 -> 0 | AC65: =L65*S65 -> 0 | AD65: =M65*S65 -> 0
A66: 59 | C66: Paket Ceria 2 | D66: 2 | N66: =SUM(D66:M66) -> 2 | O66: =N66*S66 -> 24000 | P66: =(O66/O112)*100 -> 0.087618422 | Q66: ='FOOD COST PRODUCT'!G65 -> 0.7076219 | R66: =P66*Q66 -> 0.062000714 | S66: 12000 | U66: =D66*S66 -> 24000 | V66: =E66*S66 -> 0 | W66: =F66*S66 -> 0 | X66: =G66*S66 -> 0 | Y66: =H66*S66 -> 0 | Z66: =I66*S66 -> 0 | AA66: =J66*S66 -> 0 | AB66: =K66*S66 -> 0 | AC66: =L66*S66 -> 0 | AD66: =M66*S66 -> 0
A67: 60 | C67: Paket Ceria 3 | N67: =SUM(D67:M67) -> 0 | O67: =N67*S67 -> 0 | P67: =(O67/O112)*100 -> 0 | Q67: ='FOOD COST PRODUCT'!G66 -> 0.74857406 | R67: =P67*Q67 -> 0 | S67: 13000 | U67: =D67*S67 -> 0 | V67: =E67*S67 -> 0 | W67: =F67*S67 -> 0 | X67: =G67*S67 -> 0 | Y67: =H67*S67 -> 0 | Z67: =I67*S67 -> 0 | AA67: =J67*S67 -> 0 | AB67: =K67*S67 -> 0 | AC67: =L67*S67 -> 0 | AD67: =M67*S67 -> 0
A68: 61 | C68: Paket Ceria 4 | N68: =SUM(D68:M68) -> 0 | O68: =N68*S68 -> 0 | P68: =(O68/O112)*100 -> 0 | Q68: ='FOOD COST PRODUCT'!G67 -> 0.64743085 | R68: =P68*Q68 -> 0 | S68: 15000 | U68: =D68*S68 -> 0 | V68: =E68*S68 -> 0 | W68: =F68*S68 -> 0 | X68: =G68*S68 -> 0 | Y68: =H68*S68 -> 0 | Z68: =I68*S68 -> 0 | AA68: =J68*S68 -> 0 | AB68: =K68*S68 -> 0 | AC68: =L68*S68 -> 0 | AD68: =M68*S68 -> 0
A69: 62 | C69: cuan4 | E69: 1 | F69: 2 | I69: 1 | N69: =SUM(D69:M69) -> 4 | O69: =N69*S69 -> 88000 | P69: =(O69/O112)*100 -> 0.32126755 | R69: =P69*Q69 -> 0 | S69: 22000 | U69: =D69*S69 -> 0 | V69: =E69*S69 -> 22000 | W69: =F69*S69 -> 44000 | X69: =G69*S69 -> 0 | Y69: =H69*S69 -> 0 | Z69: =I69*S69 -> 22000 | AA69: =J69*S69 -> 0 | AB69: =K69*S69 -> 0 | AC69: =L69*S69 -> 0 | AD69: =M69*S69 -> 0
A70: 63 | C70: hemat supersonic 1 | D70: 1 | E70: 3 | F70: 2 | G70: 3 | H70: 12 | I70: 7 | J70: 4 | N70: =SUM(D70:M70) -> 32 | O70: =N70*S70 -> 1760000 | P70: =(O70/O112)*100 -> 6.4253509 | R70: =P70*Q70 -> 0 | S70: 55000 | U70: =D70*S70 -> 55000 | V70: =E70*S70 -> 165000 | W70: =F70*S70 -> 110000 | X70: =G70*S70 -> 165000 | Y70: =H70*S70 -> 660000 | Z70: =I70*S70 -> 385000 | AA70: =J70*S70 -> 220000 | AB70: =K70*S70 -> 0 | AC70: =L70*S70 -> 0 | AD70: =M70*S70 -> 0
A71: 64 | C71: hemat supersonic 2 | D71: 2 | E71: 1 | F71: 4 | G71: 4 | H71: 3 | I71: 2 | J71: 5 | N71: =SUM(D71:M71) -> 21 | O71: =N71*S71 -> 1260000 | P71: =(O71/O112)*100 -> 4.5999671 | R71: =P71*Q71 -> 0 | S71: 60000 | U71: =D71*S71 -> 120000 | V71: =E71*S71 -> 60000 | W71: =F71*S71 -> 240000 | X71: =G71*S71 -> 240000 | Y71: =H71*S71 -> 180000 | Z71: =I71*S71 -> 120000 | AA71: =J71*S71 -> 300000 | AB71: =K71*S71 -> 0 | AC71: =L71*S71 -> 0 | AD71: =M71*S71 -> 0
A72: 65 | C72: hemat supersonic 3 | D72: 3 | E72: 6 | F72: 1 | H72: 2 | I72: 1 | J72: 3 | N72: =SUM(D72:M72) -> 16 | O72: =N72*S72 -> 1040000 | P72: =(O72/O112)*100 -> 3.7967983 | R72: =P72*Q72 -> 0 | S72: 65000 | U72: =D72*S72 -> 195000 | V72: =E72*S72 -> 390000 | W72: =F72*S72 -> 65000 | X72: =G72*S72 -> 0 | Y72: =H72*S72 -> 130000 | Z72: =I72*S72 -> 65000 | AA72: =J72*S72 -> 195000 | AB72: =K72*S72 -> 0 | AC72: =L72*S72 -> 0 | AD72: =M72*S72 -> 0 | AE72: =N72*2 -> 32
A73: 66 | C73: hemat supersonic 4 | E73: 2 | F73: 1 | G73: 3 | I73: 2 | N73: =SUM(D73:M73) -> 8 | O73: =N73*S73 -> 560000 | P73: =(O73/O112)*100 -> 2.0444298 | R73: =P73*Q73 -> 0 | S73: 70000 | U73: =D73*S73 -> 0 | V73: =E73*S73 -> 140000 | W73: =F73*S73 -> 70000 | X73: =G73*S73 -> 210000 | Y73: =H73*S73 -> 0 | Z73: =I73*S73 -> 140000 | AA73: =J73*S73 -> 0 | AB73: =K73*S73 -> 0 | AC73: =L73*S73 -> 0 | AD73: =M73*S73 -> 0 | AE73: =N73*2 -> 16
A74: 67 | C74: hemat supersonic 5 | H74: 1 | J74: 3 | N74: =SUM(D74:M74)*2 -> 8 | O74: =N74*S74 -> 960000 | P74: =(O74/O112)*100 -> 3.5047369 | R74: =P74*Q74 -> 0 | S74: 120000 | U74: =D74*S74 -> 0 | V74: =E74*S74 -> 0 | W74: =F74*S74 -> 0 | X74: =G74*S74 -> 0 | Y74: =H74*S74 -> 120000 | Z74: =I74*S74 -> 0 | AA74: =J74*S74 -> 360000 | AB74: =K74*S74 -> 0 | AC74: =L74*S74 -> 0 | AD74: =M74*S74 -> 0 | AE74: =N74*2 -> 16
A75: 68 | C75: hemat supersonic 6 | F75: 1 | G75: 1 | N75: =SUM(D75:M75)*2 -> 4 | O75: =N75*S75 -> 520000 | P75: =(O75/O112)*100 -> 1.8983991 | R75: =P75*Q75 -> 0 | S75: 130000 | U75: =D75*S75 -> 0 | V75: =E75*S75 -> 0 | W75: =F75*S75 -> 130000 | X75: =G75*S75 -> 130000 | Y75: =H75*S75 -> 0 | Z75: =I75*S75 -> 0 | AA75: =J75*S75 -> 0 | AB75: =K75*S75 -> 0 | AC75: =L75*S75 -> 0 | AD75: =M75*S75 -> 0 | AE75: =N75*2 -> 8
A76: 69 | C76: Paket C.Steak Blackpepper | D76: 6 | F76: 3 | I76: 2 | N76: =SUM(D76:M76) -> 11 | O76: =N76*S76 -> 253000 | P76: =(O76/O112)*100 -> 0.9236442 | R76: =P76*Q76 -> 0 | S76: 23000 | U76: =D76*S76 -> 138000 | V76: =E76*S76 -> 0 | W76: =F76*S76 -> 69000 | X76: =G76*S76 -> 0 | Y76: =H76*S76 -> 0 | Z76: =I76*S76 -> 46000 | AA76: =J76*S76 -> 0 | AB76: =K76*S76 -> 0 | AC76: =L76*S76 -> 0 | AD76: =M76*S76 -> 0
A77: 70 | C77: Paket C.Steak Es Teh | D77: 2 | N77: =SUM(D77:M77) -> 2 | O77: =N77*S77 -> 42000 | P77: =(O77/O112)*100 -> 0.15333224 | R77: =P77*Q77 -> 0 | S77: 21000 | U77: =D77*S77 -> 42000 | V77: =E77*S77 -> 0 | W77: =F77*S77 -> 0 | X77: =G77*S77 -> 0 | Y77: =H77*S77 -> 0 | Z77: =I77*S77 -> 0 | AA77: =J77*S77 -> 0 | AB77: =K77*S77 -> 0 | AC77: =L77*S77 -> 0 | AD77: =M77*S77 -> 0
A78: 71 | C78: Cuan 1 | D78: 3 | E78: 4 | F78: 4 | G78: 4 | H78: 4 | I78: 1 | J78: 3 | N78: =SUM(D78:M78) -> 23 | O78: =N78*S78 -> 345000 | P78: =(O78/O112)*100 -> 1.2595148 | R78: =P78*Q78 -> 0 | S78: 15000 | U78: =D78*S78 -> 45000 | V78: =E78*S78 -> 60000 | W78: =F78*S78 -> 60000 | X78: =G78*S78 -> 60000 | Y78: =H78*S78 -> 60000 | Z78: =I78*S78 -> 15000 | AA78: =J78*S78 -> 45000 | AB78: =K78*S78 -> 0 | AC78: =L78*S78 -> 0 | AD78: =M78*S78 -> 0
A79: 72 | C79: Paket Skin TN | D79: 13 | E79: 8 | F79: 8 | G79: 12 | H79: 7 | I79: 17 | J79: 8 | N79: =SUM(D79:M79) -> 73 | O79: =N79*S79 -> 876000 | P79: =(O79/O112)*100 -> 3.1980724 | R79: =P79*Q79 -> 0 | S79: 12000 | U79: =D79*S79 -> 156000 | V79: =E79*S79 -> 96000 | W79: =F79*S79 -> 96000 | X79: =G79*S79 -> 144000 | Y79: =H79*S79 -> 84000 | Z79: =I79*S79 -> 204000 | AA79: =J79*S79 -> 96000 | AB79: =K79*S79 -> 0 | AC79: =L79*S79 -> 0 | AD79: =M79*S79 -> 0
A80: 73 | C80: Paket Skin PN | D80: 9 | E80: 11 | F80: 9 | G80: 12 | H80: 19 | I80: 8 | J80: 14 | N80: =SUM(D80:M80) -> 82 | O80: =N80*S80 -> 1230000 | P80: =(O80/O112)*100 -> 4.4904441 | R80: =P80*Q80 -> 0 | S80: 15000 | U80: =D80*S80 -> 135000 | V80: =E80*S80 -> 165000 | W80: =F80*S80 -> 135000 | X80: =G80*S80 -> 180000 | Y80: =H80*S80 -> 285000 | Z80: =I80*S80 -> 120000 | AA80: =J80*S80 -> 210000 | AB80: =K80*S80 -> 0 | AC80: =L80*S80 -> 0 | AD80: =M80*S80 -> 0
A81: 74 | C81: Mie goreng FS | D81: 1 | G81: 1 | H81: 3 | I81: 1 | J81: 4 | N81: =SUM(D81:M81) -> 10 | O81: =N81*S81 -> 110000 | P81: =(O81/O112)*100 -> 0.40158443 | R81: =P81*Q81 -> 0 | S81: 11000 | U81: =D81*S81 -> 11000 | V81: =E81*S81 -> 0 | W81: =F81*S81 -> 0 | X81: =G81*S81 -> 11000 | Y81: =H81*S81 -> 33000 | Z81: =I81*S81 -> 11000 | AA81: =J81*S81 -> 44000 | AB81: =K81*S81 -> 0 | AC81: =L81*S81 -> 0 | AD81: =M81*S81 -> 0
A82: 75 | C82: Cuan 2 | D82: 5 | E82: 5 | F82: 2 | G82: 4 | H82: 12 | I82: 5 | J82: 4 | N82: =SUM(D82:M82) -> 37 | O82: =N82*S82 -> 740000 | P82: =(O82/O112)*100 -> 2.701568 | R82: =P82*Q82 -> 0 | S82: 20000 | U82: =D82*S82 -> 100000 | V82: =E82*S82 -> 100000 | W82: =F82*S82 -> 40000 | X82: =G82*S82 -> 80000 | Y82: =H82*S82 -> 240000 | Z82: =I82*S82 -> 100000 | AA82: =J82*S82 -> 80000 | AB82: =K82*S82 -> 0 | AC82: =L82*S82 -> 0 | AD82: =M82*S82 -> 0
B83: TOTAL FOOD | C83: =B83 -> TOTAL FOOD | D83: =U83 -> 4308000 | E83: =V83 -> 3471000 | F83: =W83 -> 3141500 | G83: =X83 -> 3371000 | H83: =Y83 -> 4822500 | I83: =Z83 -> 3918000 | J83: =AA83 -> 3591500 | K83: =AB83 -> 0 | ... M83: =AD83 -> 0 | O83: =SUM(D83:M83) -> 26623500 | P83: =SUM(P8:P82)/100 -> 0.99897779 | R83: =SUM(R8:R82)/100 -> 0.58610977 | U83: =SUM(U8:U82) -> 4308000 | V83: =SUM(V8:V82) -> 3471000 | W83: =SUM(W8:W82) -> 3141500 | X83: =SUM(X8:X82) -> 3371000 | Y83: =SUM(Y8:Y82) -> 4822500 | Z83: =SUM(Z8:Z82) -> 3918000 | AA83: =SUM(AA8:AA82) -> 3591500 | AB83: =SUM(AB8:AB82) -> 0 | ... AD83: =SUM(AD8:AD82) -> 0
A85: NO | B85: BEVERAGES | C85: =B85 -> BEVERAGES | D85: 1 | E85: 2 | F85: 3 | G85: 4 | H85: 5 | I85: 6 | J85: 7
A86: 1 | B86: Air Mineral Botol | C86: =B86 -> Air Mineral Botol | D86: 5 | E86: 1 | F86: 3 | G86: 2 | H86: 2 | I86: 5 | J86: 4 | N86: =SUM(D86:M86) -> 22 | O86: =N86*S86 -> 88000 | P86: =(O86/O112)*100 -> 0.32126755 | Q86: ='FOOD COST PRODUCT'!G76 -> 0.4375 | R86: =P86*Q86 -> 0.14055455 | S86: 4000 | U86: =D86*S86 -> 20000 | V86: =E86*S86 -> 4000 | W86: =F86*S86 -> 12000 | X86: =G86*S86 -> 8000 | Y86: =H86*S86 -> 8000 | Z86: =I86*S86 -> 20000 | AA86: =J86*S86 -> 16000 | AB86: =K86*S86 -> 0 | AC86: =L86*S86 -> 0 | AD86: =M86*S86 -> 0
A87: 2 | B87: Air Mineral Cup | C87: =B87 -> Air Mineral Cup | N87: =SUM(D87:M87) -> 0 | O87: =N87*S87 -> 0 | P87: =(O87/O112)*100 -> 0 | Q87: ='FOOD COST PRODUCT'!G77 -> 0 | R87: =P87*Q87 -> 0 | S87: 2000 | U87: =D87*S87 -> 0 | V87: =E87*S87 -> 0 | W87: =F87*S87 -> 0 | X87: =G87*S87 -> 0 | Y87: =H87*S87 -> 0 | Z87: =I87*S87 -> 0 | AA87: =J87*S87 -> 0 | AB87: =K87*S87 -> 0 | AC87: =L87*S87 -> 0 | AD87: =M87*S87 -> 0
A88: 3 | B88: Teh Botol | C88: =B88 -> Teh Botol | D88: 2 | G88: 1 | J88: 4 | N88: =SUM(D88:M88) -> 7 | O88: =N88*S88 -> 49000 | P88: =(O88/O112)*100 -> 0.17888761 | Q88: ='FOOD COST PRODUCT'!G78 -> 0.35714286 | R88: =P88*Q88 -> 0.063888433 | S88: 7000 | U88: =D88*S88 -> 14000 | V88: =E88*S88 -> 0 | W88: =F88*S88 -> 0 | X88: =G88*S88 -> 7000 | Y88: =H88*S88 -> 0 | Z88: =I88*S88 -> 0 | AA88: =J88*S88 -> 28000 | AB88: =K88*S88 -> 0 | AC88: =L88*S88 -> 0 | AD88: =M88*S88 -> 0
A89: 4 | B89: Teh Sosro Genggam | C89: =B89 -> Teh Sosro Genggam | N89: =SUM(D89:M89) -> 0 | O89: =N89*S89 -> 0 | P89: =(O89/O112)*100 -> 0 | Q89: ='FOOD COST PRODUCT'!G79 -> 0.35714286 | R89: =P89*Q89 -> 0 | S89: 7000 | U89: =D89*S89 -> 0 | V89: =E89*S89 -> 0 | W89: =F89*S89 -> 0 | X89: =G89*S89 -> 0 | Y89: =H89*S89 -> 0 | Z89: =I89*S89 -> 0 | AA89: =J89*S89 -> 0 | AB89: =K89*S89 -> 0 | AC89: =L89*S89 -> 0 | AD89: =M89*S89 -> 0
A90: 5 | B90: Fruit Tea Botol | N90: =SUM(D90:M90) -> 0 | O90: =N90*S90 -> 0 | P90: =(O90/O112)*100 -> 0 | Q90: ='FOOD COST PRODUCT'!G80 -> 0 | R90: =P90*Q90 -> 0 | U90: =D90*S90 -> 0 | V90: =E90*S90 -> 0 | W90: =F90*S90 -> 0 | X90: =G90*S90 -> 0 | Y90: =H90*S90 -> 0 | Z90: =I90*S90 -> 0 | AA90: =J90*S90 -> 0 | AB90: =K90*S90 -> 0 | AC90: =L90*S90 -> 0 | AD90: =M90*S90 -> 0
A91: 6 | B91: Fuit Tea Genggam | C91: S-tee | N91: =SUM(D91:M91) -> 0 | O91: =N91*S91 -> 0 | P91: =(O91/O112)*100 -> 0 | Q91: ='FOOD COST PRODUCT'!G81 -> 0 | R91: =P91*Q91 -> 0 | S91: 6000 | U91: =D91*S91 -> 0 | V91: =E91*S91 -> 0 | W91: =F91*S91 -> 0 | X91: =G91*S91 -> 0 | Y91: =H91*S91 -> 0 | Z91: =I91*S91 -> 0 | AA91: =J91*S91 -> 0 | AB91: =K91*S91 -> 0 | AC91: =L91*S91 -> 0 | AD91: =M91*S91 -> 0
B92: Tebs | O92: =N92*S92 -> 0 | P92: =(O92/O112)*100 -> 0 | R92: =P92*Q92 -> 0 | U92: =D92*S92 -> 0 | V92: =E92*S92 -> 0 | W92: =F92*S92 -> 0 | X92: =G92*S92 -> 0 | Y92: =H92*S92 -> 0 | Z92: =I92*S92 -> 0 | AA92: =J92*S92 -> 0 | AB92: =K92*S92 -> 0 | AC92: =L92*S92 -> 0 | AD92: =M92*S92 -> 0
A93: 7 | B93: STEE | C93: Millo | D93: 3 | E93: 6 | G93: 6 | H93: 4 | I93: 1 | J93: 2 | N93: =SUM(D93:M93) -> 22 | O93: =N93*S93 -> 220000 | P93: =(O93/O112)*100 -> 0.80316887 | Q93: ='FOOD COST PRODUCT'!G83 -> 0.38346839 | R93: =P93*Q93 -> 0.30798987 | S93: 10000 | U93: =D93*S93 -> 30000 | V93: =E93*S93 -> 60000 | W93: =F93*S93 -> 0 | X93: =G93*S93 -> 60000 | Y93: =H93*S93 -> 40000 | Z93: =I93*S93 -> 10000 | AA93: =J93*S93 -> 20000 | AB93: =K93*S93 -> 0 | AC93: =L93*S93 -> 0 | AD93: =M93*S93 -> 0
A94: 8 | C94: Nestea | J94: 1 | N94: =SUM(D94:M94) -> 1 | O94: =N94*S94 -> 8000 | P94: =(O94/O112)*100 -> 0.029206141 | Q94: ='FOOD COST PRODUCT'!G84 -> 0.35128859 | R94: =P94*Q94 -> 0.010259784 | S94: 8000 | U94: =D94*S94 -> 0 | V94: =E94*S94 -> 0 | W94: =F94*S94 -> 0 | X94: =G94*S94 -> 0 | Y94: =H94*S94 -> 0 | Z94: =I94*S94 -> 0 | AA94: =J94*S94 -> 8000 | AB94: =K94*S94 -> 0 | AC94: =L94*S94 -> 0 | AD94: =M94*S94 -> 0
A95: 9 | B95: Juice Durian Float | C95: Orange Juice | G95: 1 | J95: 1 | N95: =SUM(D95:M95) -> 2 | O95: =N95*S95 -> 16000 | P95: =(O95/O112)*100 -> 0.058412281 | Q95: ='FOOD COST PRODUCT'!G85 -> 0.37093291 | R95: =P95*Q95 -> 0.021667038 | S95: 8000 | U95: =D95*S95 -> 0 | V95: =E95*S95 -> 0 | W95: =F95*S95 -> 0 | X95: =G95*S95 -> 8000 | Y95: =H95*S95 -> 0 | Z95: =I95*S95 -> 0 | AA95: =J95*S95 -> 8000 | AB95: =K95*S95 -> 0 | AC95: =L95*S95 -> 0 | AD95: =M95*S95 -> 0
A96: 10 | B96: Juice Durian | C96: Orange Float | N96: =SUM(D96:M96) -> 0 | O96: =N96*S96 -> 0 | P96: =(O96/O112)*100 -> 0 | Q96: ='FOOD COST PRODUCT'!G86 -> 0 | R96: =P96*Q96 -> 0 | S96: 9000 | U96: =D96*S96 -> 0 | V96: =E96*S96 -> 0 | W96: =F96*S96 -> 0 | X96: =G96*S96 -> 0 | Y96: =H96*S96 -> 0 | Z96: =I96*S96 -> 0 | AA96: =J96*S96 -> 0 | AB96: =K96*S96 -> 0 | AC96: =L96*S96 -> 0 | AD96: =M96*S96 -> 0
A97: 11 | B97: Juice Melon Float | C97: Avocado Float | D97: 2 | J97: 1 | N97: =SUM(D97:M97) -> 3 | O97: =N97*S97 -> 45000 | P97: =(O97/O112)*100 -> 0.16428454 | Q97: ='FOOD COST PRODUCT'!G87 -> 0 | R97: =P97*Q97 -> 0 | S97: 15000 | U97: =D97*S97 -> 30000 | V97: =E97*S97 -> 0 | W97: =F97*S97 -> 0 | X97: =G97*S97 -> 0 | Y97: =H97*S97 -> 0 | Z97: =I97*S97 -> 0 | AA97: =J97*S97 -> 15000 | AB97: =K97*S97 -> 0 | AC97: =L97*S97 -> 0 | AD97: =M97*S97 -> 0
A98: 12 | B98: Juice Melon | N98: =SUM(D98:M98) -> 0 | O98: =N98*S98 -> 0 | P98: =(O98/O112)*100 -> 0 | Q98: ='FOOD COST PRODUCT'!G88 -> 0 | R98: =P98*Q98 -> 0 | U98: =D98*S98 -> 0 | V98: =E98*S98 -> 0 | W98: =F98*S98 -> 0 | X98: =G98*S98 -> 0 | Y98: =H98*S98 -> 0 | Z98: =I98*S98 -> 0 | AA98: =J98*S98 -> 0 | AB98: =K98*S98 -> 0 | AC98: =L98*S98 -> 0 | AD98: =M98*S98 -> 0
A99: 13 | B99: Juice Strawberry Float | C99: Es Teh | D99: 7 | E99: 4 | G99: 3 | H99: 5 | I99: 2 | J99: 3 | N99: =SUM(D99:M99) -> 24 | O99: =N99*S99 -> 120000 | P99: =(O99/O112)*100 -> 0.43809211 | Q99: ='FOOD COST PRODUCT'!G89 -> 0.38336813 | R99: =P99*Q99 -> 0.16795055 | S99: 5000 | U99: =D99*S99 -> 35000 | V99: =E99*S99 -> 20000 | W99: =F99*S99 -> 0 | X99: =G99*S99 -> 15000 | Y99: =H99*S99 -> 25000 | Z99: =I99*S99 -> 10000 | AA99: =J99*S99 -> 15000 | AB99: =K99*S99 -> 0 | AC99: =L99*S99 -> 0 | AD99: =M99*S99 -> 0
A100: 14 | B100: Juice Stawbery | C100: Air Mineral Botol 600ml | N100: =SUM(D100:M100) -> 0 | O100: =N100*S100 -> 0 | P100: =(O100/O112)*100 -> 0 | Q100: ='FOOD COST PRODUCT'!G90 -> 0 | R100: =P100*Q100 -> 0 | S100: 6500 | U100: =D100*S100 -> 0 | V100: =E100*S100 -> 0 | W100: =F100*S100 -> 0 | X100: =G100*S100 -> 0 | Y100: =H100*S100 -> 0 | Z100: =I100*S100 -> 0 | AA100: =J100*S100 -> 0 | AB100: =K100*S100 -> 0 | AC100: =L100*S100 -> 0 | AD100: =M100*S100 -> 0
A101: 15 | B101: Juice Mangga Float | N101: =SUM(D101:M101) -> 0 | O101: =N101*S101 -> 0 | P101: =(O101/O112)*100 -> 0 | R101: =P101*Q101 -> 0 | U101: =D101*S101 -> 0 | V101: =E101*S101 -> 0 | W101: =F101*S101 -> 0 | X101: =G101*S101 -> 0 | Y101: =H101*S101 -> 0 | Z101: =I101*S101 -> 0 | AA101: =J101*S101 -> 0 | AB101: =K101*S101 -> 0 | AC101: =L101*S101 -> 0 | AD101: =M101*S101 -> 0
A102: 16 | B102: Juice Mangga | C102: es the jumbo | D102: 1 | F102: 4 | G102: 3 | H102: 5 | I102: 7 | J102: 2 | N102: =SUM(D102:M102) -> 22 | O102: =N102*S102 -> 110000 | P102: =(O102/O112)*100 -> 0.40158443 | R102: =P102*Q102 -> 0 | S102: 5000 | U102: =D102*S102 -> 5000 | V102: =E102*S102 -> 0 | W102: =F102*S102 -> 20000 | X102: =G102*S102 -> 15000 | Y102: =H102*S102 -> 25000 | Z102: =I102*S102 -> 35000 | AA102: =J102*S102 -> 10000 | AB102: =K102*S102 -> 0 | AC102: =L102*S102 -> 0 | AD102: =M102*S102 -> 0
A103: 17 | B103: Juice Jambu Float | C103: milo jumbo | D103: 1 | E103: 7 | N103: =SUM(D103:M103) -> 8 | O103: =N103*S103 -> 96000 | P103: =(O103/O112)*100 -> 0.35047369 | R103: =P103*Q103 -> 0 | S103: 12000 | U103: =D103*S103 -> 12000 | V103: =E103*S103 -> 84000 | W103: =F103*S103 -> 0 | X103: =G103*S103 -> 0 | Y103: =H103*S103 -> 0 | Z103: =I103*S103 -> 0 | AA103: =J103*S103 -> 0 | AB103: =K103*S103 -> 0 | AC103: =L103*S103 -> 0 | AD103: =M103*S103 -> 0
...

Sheet LAP. PENJUALAN GRABFOOD
A2: LAPORAN PENJUALAN GRABFOOD
M3: Cabang : | O3: =LPKK!Q4 -> SC MARABAHAN
M4: Periode : | O4: =LPKK!Q5 -> 1-7 JULI 2026
A6: NO | B6: PRODUCT | C6: =B6 -> PRODUCT | D6: ='LAP. PENJUALAN REGULER'!D6 -> 1 | E6: ='LAP. PENJUALAN REGULER'!E6 -> 2 | F6: ='LAP. PENJUALAN REGULER'!F6 -> 3 | G6: ='LAP. PENJUALAN REGULER'!G6 -> 4 | H6: ='LAP. PENJUALAN REGULER'!H6 -> 5 | I6: ='LAP. PENJUALAN REGULER'!I6 -> 6 | J6: ='LAP. PENJUALAN REGULER'!J6 -> 7 | K6: ='LAP. PENJUALAN REGULER'!K6 -> 0 | ... M6: ='LAP. PENJUALAN REGULER'!M6 -> 0 | N6: TOTAL | P6: % | Q6: FC ITEM | R6: CON FC | S6: Harga
D7: ='LAP. PENJUALAN REGULER'!D7 -> Rabu | E7: ='LAP. PENJUALAN REGULER'!E7 -> Kamis | F7: ='LAP. PENJUALAN REGULER'!F7 -> Jum`at | G7: ='LAP. PENJUALAN REGULER'!G7 -> Sabtu | H7: ='LAP. PENJUALAN REGULER'!H7 -> Minggu | I7: ='LAP. PENJUALAN REGULER'!I7 -> Senin | J7: ='LAP. PENJUALAN REGULER'!J7 -> Sabtu | K7: ='LAP. PENJUALAN REGULER'!K7 -> 0 | ... M7: ='LAP. PENJUALAN REGULER'!M7 -> 0 | N7: UNIT | O7: ( Rp ) | S7: ( Unit )
A8: 1 | B8: Dada | C8: =B8 -> Dada | N8: =SUM(D8:M8) -> 0 | O8: =N8*S8 -> 0 | P8: =(O8/O112)*100 -> #DIV/0! | R8: =P8*Q8 -> #DIV/0! | S8: 19575 | U8: =D8*S8 -> 0 | V8: =E8*S8 -> 0 | W8: =F8*S8 -> 0 | X8: =G8*S8 -> 0 | Y8: =H8*S8 -> 0 | Z8: =I8*S8 -> 0 | AA8: =J8*S8 -> 0 | AB8: =K8*S8 -> 0 | AC8: =L8*S8 -> 0 | AD8: =M8*S8 -> 0
A9: 2 | B9: Paha Atas | C9: =B9 -> Paha Atas | N9: =SUM(D9:M9) -> 0 | O9: =N9*S9 -> 0 | P9: =(O9/O112)*100 -> #DIV/0! | R9: =P9*Q9 -> #DIV/0! | S9: 19575 | U9: =D9*S9 -> 0 | V9: =E9*S9 -> 0 | W9: =F9*S9 -> 0 | X9: =G9*S9 -> 0 | Y9: =H9*S9 -> 0 | Z9: =I9*S9 -> 0 | AA9: =J9*S9 -> 0 | AB9: =K9*S9 -> 0 | AC9: =L9*S9 -> 0 | AD9: =M9*S9 -> 0
A10: 3 | B10: Paha Bawah | C10: =B10 -> Paha Bawah | N10: =SUM(D10:M10) -> 0 | O10: =N10*S10 -> 0 | P10: =(O10/O112)*100 -> #DIV/0! | R10: =P10*Q10 -> #DIV/0! | S10: 17550 | U10: =D10*S10 -> 0 | V10: =E10*S10 -> 0 | W10: =F10*S10 -> 0 | X10: =G10*S10 -> 0 | Y10: =H10*S10 -> 0 | Z10: =I10*S10 -> 0 | AA10: =J10*S10 -> 0 | AB10: =K10*S10 -> 0 | AC10: =L10*S10 -> 0 | AD10: =M10*S10 -> 0
A11: 4 | B11: Sayap | C11: =B11 -> Sayap | N11: =SUM(D11:M11) -> 0 | O11: =N11*S11 -> 0 | P11: =(O11/O112)*100 -> #DIV/0! | R11: =P11*Q11 -> #DIV/0! | S11: 16200 | U11: =D11*S11 -> 0 | V11: =E11*S11 -> 0 | W11: =F11*S11 -> 0 | X11: =G11*S11 -> 0 | Y11: =H11*S11 -> 0 | Z11: =I11*S11 -> 0 | AA11: =J11*S11 -> 0 | AB11: =K11*S11 -> 0 | AC11: =L11*S11 -> 0 | AD11: =M11*S11 -> 0
A12: 5 | B12: Chicken Strips | C12: =B12 -> Chicken Strips | N12: =SUM(D12:M12) -> 0 | O12: =N12*S12 -> 0 | P12: =(O12/O112)*100 -> #DIV/0! | R12: =P12*Q12 -> #DIV/0! | S12: 16200 | U12: =D12*S12 -> 0 | V12: =E12*S12 -> 0 | W12: =F12*S12 -> 0 | X12: =G12*S12 -> 0 | Y12: =H12*S12 -> 0 | Z12: =I12*S12 -> 0 | AA12: =J12*S12 -> 0 | AB12: =K12*S12 -> 0 | AC12: =L12*S12 -> 0 | AD12: =M12*S12 -> 0
A13: 6 | B13: Chicken Steak | C13: =B13 -> Chicken Steak | N13: =SUM(D13:M13) -> 0 | O13: =N13*S13 -> 0 | P13: =(O13/O112)*100 -> #DIV/0! | R13: =P13*Q13 -> #DIV/0! | S13: 17550 | U13: =D13*S13 -> 0 | V13: =E13*S13 -> 0 | W13: =F13*S13 -> 0 | X13: =G13*S13 -> 0 | Y13: =H13*S13 -> 0 | Z13: =I13*S13 -> 0 | AA13: =J13*S13 -> 0 | AB13: =K13*S13 -> 0 | AC13: =L13*S13 -> 0 | AD13: =M13*S13 -> 0
A14: 7 | C14: Dada Lembut | N14: =SUM(D14:M14) -> 0 | O14: =N14*S14 -> 0 | P14: =(O14/O112)*100 -> #DIV/0! | R14: =P14*Q14 -> #DIV/0! | S14: 19575 | U14: =D14*S14 -> 0 | V14: =E14*S14 -> 0 | W14: =F14*S14 -> 0 | X14: =G14*S14 -> 0 | Y14: =H14*S14 -> 0 | Z14: =I14*S14 -> 0 | AA14: =J14*S14 -> 0 | AB14: =K14*S14 -> 0 | AC14: =L14*S14 -> 0 | AD14: =M14*S14 -> 0
A15: 8 | B15: French Fries | C15: =B15 -> French Fries | N15: =SUM(D15:M15) -> 0 | O15: =N15*S15 -> 0 | P15: =(O15/O112)*100 -> #DIV/0! | R15: =P15*Q15 -> #DIV/0! | S15: 14850 | U15: =D15*S15 -> 0 | V15: =E15*S15 -> 0 | W15: =F15*S15 -> 0 | X15: =G15*S15 -> 0 | Y15: =H15*S15 -> 0 | Z15: =I15*S15 -> 0 | AA15: =J15*S15 -> 0 | AB15: =K15*S15 -> 0 | AC15: =L15*S15 -> 0 | AD15: =M15*S15 -> 0
A16: 9 | B16: Nasi | C16: =B16 -> Nasi | N16: =SUM(D16:M16) -> 0 | O16: =N16*S16 -> 0 | P16: =(O16/O112)*100 -> #DIV/0! | R16: =P16*Q16 -> #DIV/0! | S16: 6750 | U16: =D16*S16 -> 0 | V16: =E16*S16 -> 0 | W16: =F16*S16 -> 0 | X16: =G16*S16 -> 0 | Y16: =H16*S16 -> 0 | Z16: =I16*S16 -> 0 | AA16: =J16*S16 -> 0 | AB16: =K16*S16 -> 0 | AC16: =L16*S16 -> 0 | AD16: =M16*S16 -> 0
A17: 10 | B17: Perkedel | C17: =B17 -> Perkedel | N17: =SUM(D17:M17) -> 0 | O17: =N17*S17 -> 0 | P17: =(O17/O112)*100 -> #DIV/0! | R17: =P17*Q17 -> #DIV/0! | S17: 6750 | U17: =D17*S17 -> 0 | V17: =E17*S17 -> 0 | W17: =F17*S17 -> 0 | X17: =G17*S17 -> 0 | Y17: =H17*S17 -> 0 | Z17: =I17*S17 -> 0 | AA17: =J17*S17 -> 0 | AB17: =K17*S17 -> 0 | AC17: =L17*S17 -> 0 | AD17: =M17*S17 -> 0
A18: 11 | B18: Chicken Burger | C18: =B18 -> Chicken Burger | N18: =SUM(D18:M18) -> 0 | O18: =N18*S18 -> 0 | P18: =(O18/O112)*100 -> #DIV/0! | R18: =P18*Q18 -> #DIV/0! | S18: 20250 | U18: =D18*S18 -> 0 | V18: =E18*S18 -> 0 | W18: =F18*S18 -> 0 | X18: =G18*S18 -> 0 | Y18: =H18*S18 -> 0 | Z18: =I18*S18 -> 0 | AA18: =J18*S18 -> 0 | AB18: =K18*S18 -> 0 | AC18: =L18*S18 -> 0 | AD18: =M18*S18 -> 0
A19: 12 | B19: Cheese Burger | C19: =B19 -> Cheese Burger | N19: =SUM(D19:M19) -> 0 | O19: =N19*S19 -> 0 | P19: =(O19/O112)*100 -> #DIV/0! | R19: =P19*Q19 -> #DIV/0! | S19: 22950 | U19: =D19*S19 -> 0 | V19: =E19*S19 -> 0 | W19: =F19*S19 -> 0 | X19: =G19*S19 -> 0 | Y19: =H19*S19 -> 0 | Z19: =I19*S19 -> 0 | AA19: =J19*S19 -> 0 | AB19: =K19*S19 -> 0 | AC19: =L19*S19 -> 0 | AD19: =M19*S19 -> 0
A20: 13 | B20: Nasi Goreng | C20: =B20 -> Nasi Goreng | N20: =SUM(D20:M20) -> 0 | O20: =N20*S20 -> 0 | P20: =(O20/O112)*100 -> #DIV/0! | R20: =P20*Q20 -> #DIV/0! | S20: 21600 | U20: =D20*S20 -> 0 | V20: =E20*S20 -> 0 | W20: =F20*S20 -> 0 | X20: =G20*S20 -> 0 | Y20: =H20*S20 -> 0 | Z20: =I20*S20 -> 0 | AA20: =J20*S20 -> 0 | AB20: =K20*S20 -> 0 | AC20: =L20*S20 -> 0 | AD20: =M20*S20 -> 0
A21: 14 | B21: Telor Ceplok | C21: Nasi Goreng Spesial | N21: =SUM(D21:M21) -> 0 | O21: =N21*S21 -> 0 | P21: =(O21/O112)*100 -> #DIV/0! | R21: =P21*Q21 -> #DIV/0! | S21: 25650 | U21: =D21*S21 -> 0 | V21: =E21*S21 -> 0 | W21: =F21*S21 -> 0 | X21: =G21*S21 -> 0 | Y21: =H21*S21 -> 0 | Z21: =I21*S21 -> 0 | AA21: =J21*S21 -> 0 | AB21: =K21*S21 -> 0 | AC21: =L21*S21 -> 0 | AD21: =M21*S21 -> 0
A22: 15 | B22: Nasi Goreng Telor Ceplok | C22: Mie Goreng | N22: =SUM(D22:M22) -> 0 | O22: =N22*S22 -> 0 | P22: =(O22/O112)*100 -> #DIV/0! | R22: =P22*Q22 -> #DIV/0! | S22: 21600 | U22: =D22*S22 -> 0 | V22: =E22*S22 -> 0 | W22: =F22*S22 -> 0 | X22: =G22*S22 -> 0 | Y22: =H22*S22 -> 0 | Z22: =I22*S22 -> 0 | AA22: =J22*S22 -> 0 | AB22: =K22*S22 -> 0 | AC22: =L22*S22 -> 0 | AD22: =M22*S22 -> 0
A23: 16 | C23: Chicken 2 Pcs | N23: =SUM(D23:M23) -> 0 | O23: =N23*S23 -> 0 | P23: =(O23/O112)*100 -> #DIV/0! | R23: =P23*Q23 -> #DIV/0! | S23: 33750 | U23: =D23*S23 -> 0 | V23: =E23*S23 -> 0 | W23: =F23*S23 -> 0 | X23: =G23*S23 -> 0 | Y23: =H23*S23 -> 0 | Z23: =I23*S23 -> 0 | AA23: =J23*S23 -> 0 | AB23: =K23*S23 -> 0 | AC23: =L23*S23 -> 0 | AD23: =M23*S23 -> 0
A24: 17 | C24: Steak Blackpaper | N24: =SUM(D24:M24) -> 0 | O24: =N24*S24 -> 0 | P24: =(O24/O112)*100 -> #DIV/0! | R24: =P24*Q24 -> #DIV/0! | S24: 20250 | U24: =D24*S24 -> 0 | V24: =E24*S24 -> 0 | W24: =F24*S24 -> 0 | X24: =G24*S24 -> 0 | Y24: =H24*S24 -> 0 | Z24: =I24*S24 -> 0 | AA24: =J24*S24 -> 0 | AB24: =K24*S24 -> 0 | AC24: =L24*S24 -> 0 | AD24: =M24*S24 -> 0
A25: 18 | N25: =SUM(D25:M25) -> 0 | O25: =N25*S25 -> 0 | P25: =(O25/O112)*100 -> #DIV/0! | R25: =P25*Q25 -> #DIV/0! | U25: =D25*S25 -> 0 | V25: =E25*S25 -> 0 | W25: =F25*S25 -> 0 | X25: =G25*S25 -> 0 | Y25: =H25*S25 -> 0 | Z25: =I25*S25 -> 0 | AA25: =J25*S25 -> 0 | AB25: =K25*S25 -> 0 | AC25: =L25*S25 -> 0 | AD25: =M25*S25 -> 0
A26: 19 | B26: Paket Rocket 1 | C26: Paket Sonic 1 | N26: =SUM(D26:M26) -> 0 | O26: =N26*S26 -> 0 | P26: =(O26/O112)*100 -> #DIV/0! | R26: =P26*Q26 -> #DIV/0! | S26: 17550 | U26: =D26*S26 -> 0 | V26: =E26*S26 -> 0 | W26: =F26*S26 -> 0 | X26: =G26*S26 -> 0 | Y26: =H26*S26 -> 0 | Z26: =I26*S26 -> 0 | AA26: =J26*S26 -> 0 | AB26: =K26*S26 -> 0 | AC26: =L26*S26 -> 0 | AD26: =M26*S26 -> 0
A27: 20 | B27: Paket Rocket 2 | C27: Paket Sonic 2 | N27: =SUM(D27:M27) -> 0 | O27: =N27*S27 -> 0 | P27: =(O27/O112)*100 -> #DIV/0! | R27: =P27*Q27 -> #DIV/0! | S27: 20250 | U27: =D27*S27 -> 0 | V27: =E27*S27 -> 0 | W27: =F27*S27 -> 0 | X27: =G27*S27 -> 0 | Y27: =H27*S27 -> 0 | Z27: =I27*S27 -> 0 | AA27: =J27*S27 -> 0 | AB27: =K27*S27 -> 0 | AC27: =L27*S27 -> 0 | AD27: =M27*S27 -> 0
A28: 21 | B28: Paket Rocket 3 | C28: Paket Sonic 3 | N28: =SUM(D28:M28) -> 0 | O28: =N28*S28 -> 0 | P28: =(O28/O112)*100 -> #DIV/0! | R28: =P28*Q28 -> #DIV/0! | S28: 32400 | U28: =D28*S28 -> 0 | V28: =E28*S28 -> 0 | W28: =F28*S28 -> 0 | X28: =G28*S28 -> 0 | Y28: =H28*S28 -> 0 | Z28: =I28*S28 -> 0 | AA28: =J28*S28 -> 0 | AB28: =K28*S28 -> 0 | AC28: =L28*S28 -> 0 | AD28: =M28*S28 -> 0
A29: 22 | B29: Paket Rocket 4 | C29: Paket Sonic 4 | N29: =SUM(D29:M29) -> 0 | O29: =N29*S29 -> 0 | P29: =(O29/O112)*100 -> #DIV/0! | R29: =P29*Q29 -> #DIV/0! | S29: 32400 | U29: =D29*S29 -> 0 | V29: =E29*S29 -> 0 | W29: =F29*S29 -> 0 | X29: =G29*S29 -> 0 | Y29: =H29*S29 -> 0 | Z29: =I29*S29 -> 0 | AA29: =J29*S29 -> 0 | AB29: =K29*S29 -> 0 | AC29: =L29*S29 -> 0 | AD29: =M29*S29 -> 0
A30: 23 | B30: Paket Rocket 5 | C30: Paket Sonic 5 | N30: =SUM(D30:M30) -> 0 | O30: =N30*S30 -> 0 | P30: =(O30/O112)*100 -> #DIV/0! | R30: =P30*Q30 -> #DIV/0! | S30: 32400 | U30: =D30*S30 -> 0 | V30: =E30*S30 -> 0 | W30: =F30*S30 -> 0 | X30: =G30*S30 -> 0 | Y30: =H30*S30 -> 0 | Z30: =I30*S30 -> 0 | AA30: =J30*S30 -> 0 | AB30: =K30*S30 -> 0 | AC30: =L30*S30 -> 0 | AD30: =M30*S30 -> 0
A31: 24 | B31: Paket Rocket 6 | C31: Paket Sonic 6 | N31: =SUM(D31:M31) -> 0 | O31: =N31*S31 -> 0 | P31: =(O31/O112)*100 -> #DIV/0! | R31: =P31*Q31 -> #DIV/0! | S31: 37800 | U31: =D31*S31 -> 0 | V31: =E31*S31 -> 0 | W31: =F31*S31 -> 0 | X31: =G31*S31 -> 0 | Y31: =H31*S31 -> 0 | Z31: =I31*S31 -> 0 | AA31: =J31*S31 -> 0 | AB31: =K31*S31 -> 0 | AC31: =L31*S31 -> 0 | AD31: =M31*S31 -> 0
A32: 25 | B32: Paket Rocket 7 | C32: Paket Sonic 7 | N32: =SUM(D32:M32) -> 0 | O32: =N32*S32 -> 0 | P32: =(O32/O112)*100 -> #DIV/0! | R32: =P32*Q32 -> #DIV/0! | S32: 27000 | U32: =D32*S32 -> 0 | V32: =E32*S32 -> 0 | W32: =F32*S32 -> 0 | X32: =G32*S32 -> 0 | Y32: =H32*S32 -> 0 | Z32: =I32*S32 -> 0 | AA32: =J32*S32 -> 0 | AB32: =K32*S32 -> 0 | AC32: =L32*S32 -> 0 | AD32: =M32*S32 -> 0
A33: 26 | C33: Paket Sonic 8 | N33: =SUM(D33:M33) -> 0 | O33: =N33*S33 -> 0 | P33: =(O33/O112)*100 -> #DIV/0! | R33: =P33*Q33 -> #DIV/0! | S33: 32400 | U33: =D33*S33 -> 0 | V33: =E33*S33 -> 0 | W33: =F33*S33 -> 0 | X33: =G33*S33 -> 0 | Y33: =H33*S33 -> 0 | Z33: =I33*S33 -> 0 | AA33: =J33*S33 -> 0 | AB33: =K33*S33 -> 0 | AC33: =L33*S33 -> 0 | AD33: =M33*S33 -> 0
A34: 27 | B34: Paket Rocket 8 | C34: Paket Sonic 9 | N34: =SUM(D34:M34) -> 0 | O34: =N34*S34 -> 0 | P34: =(O34/O112)*100 -> #DIV/0! | R34: =P34*Q34 -> #DIV/0! | U34: =D34*S34 -> 0 | V34: =E34*S34 -> 0 | W34: =F34*S34 -> 0 | X34: =G34*S34 -> 0 | Y34: =H34*S34 -> 0 | Z34: =I34*S34 -> 0 | AA34: =J34*S34 -> 0 | AB34: =K34*S34 -> 0 | AC34: =L34*S34 -> 0 | AD34: =M34*S34 -> 0
A35: 28 | O35: =N35*S35 -> 0 | P35: =(O35/O112)*100 -> #DIV/0! | R35: =P35*Q35 -> #DIV/0! | U35: =D35*S35 -> 0 | V35: =E35*S35 -> 0 | W35: =F35*S35 -> 0 | X35: =G35*S35 -> 0 | Y35: =H35*S35 -> 0 | Z35: =I35*S35 -> 0 | AA35: =J35*S35 -> 0 | AB35: =K35*S35 -> 0 | AC35: =L35*S35 -> 0 | AD35: =M35*S35 -> 0
A36: 29 | B36: Paket Rocket 9 | C36: Paket Gepso 1 | N36: =SUM(D36:M36) -> 0 | O36: =N36*S36 -> 0 | P36: =(O36/O112)*100 -> #DIV/0! | R36: =P36*Q36 -> #DIV/0! | S36: 28350 | U36: =D36*S36 -> 0 | V36: =E36*S36 -> 0 | W36: =F36*S36 -> 0 | X36: =G36*S36 -> 0 | Y36: =H36*S36 -> 0 | Z36: =I36*S36 -> 0 | AA36: =J36*S36 -> 0 | AB36: =K36*S36 -> 0 | AC36: =L36*S36 -> 0 | AD36: =M36*S36 -> 0
A37: 30 | B37: Paket Rocket 10 | C37: Paket Gepso 2 | N37: =SUM(D37:M37) -> 0 | O37: =N37*S37 -> 0 | P37: =(O37/O112)*100 -> #DIV/0! | R37: =P37*Q37 -> #DIV/0! | S37: 31050 | U37: =D37*S37 -> 0 | V37: =E37*S37 -> 0 | W37: =F37*S37 -> 0 | X37: =G37*S37 -> 0 | Y37: =H37*S37 -> 0 | Z37: =I37*S37 -> 0 | AA37: =J37*S37 -> 0 | AB37: =K37*S37 -> 0 | AC37: =L37*S37 -> 0 | AD37: =M37*S37 -> 0
A38: 31 | C38: Paket Gepso 3 | N38: =SUM(D38:M38) -> 0 | O38: =N38*S38 -> 0 | P38: =(O38/O112)*100 -> #DIV/0! | R38: =P38*Q38 -> #DIV/0! | S38: 33750 | U38: =D38*S38 -> 0 | V38: =E38*S38 -> 0 | W38: =F38*S38 -> 0 | X38: =G38*S38 -> 0 | Y38: =H38*S38 -> 0 | Z38: =I38*S38 -> 0 | AA38: =J38*S38 -> 0 | AB38: =K38*S38 -> 0 | AC38: =L38*S38 -> 0 | AD38: =M38*S38 -> 0
A39: 32 | C39: Paket Gepso 4 | N39: =SUM(D39:M39) -> 0 | O39: =N39*S39 -> 0 | P39: =(O39/O112)*100 -> #DIV/0! | R39: =P39*Q39 -> #DIV/0! | S39: 33750 | U39: =D39*S39 -> 0 | V39: =E39*S39 -> 0 | W39: =F39*S39 -> 0 | X39: =G39*S39 -> 0 | Y39: =H39*S39 -> 0 | Z39: =I39*S39 -> 0 | AA39: =J39*S39 -> 0 | AB39: =K39*S39 -> 0 | AC39: =L39*S39 -> 0 | AD39: =M39*S39 -> 0
A40: 33 | B40: Paket Roma 1 | O40: =N40*S40 -> 0 | P40: =(O40/O112)*100 -> #DIV/0! | R40: =P40*Q40 -> #DIV/0! | U40: =D40*S40 -> 0 | V40: =E40*S40 -> 0 | W40: =F40*S40 -> 0 | X40: =G40*S40 -> 0 | Y40: =H40*S40 -> 0 | Z40: =I40*S40 -> 0 | AA40: =J40*S40 -> 0 | AB40: =K40*S40 -> 0 | AC40: =L40*S40 -> 0 | AD40: =M40*S40 -> 0
A41: 34 | B41: Paket Roma 2 | C41: Paket Prenic 1 | N41: =SUM(D41:M41) -> 0 | O41: =N41*S41 -> 0 | P41: =(O41/O112)*100 -> #DIV/0! | R41: =P41*Q41 -> #DIV/0! | S41: 32400 | U41: =D41*S41 -> 0 | V41: =E41*S41 -> 0 | W41: =F41*S41 -> 0 | X41: =G41*S41 -> 0 | Y41: =H41*S41 -> 0 | Z41: =I41*S41 -> 0 | AA41: =J41*S41 -> 0 | AB41: =K41*S41 -> 0 | AC41: =L41*S41 -> 0 | AD41: =M41*S41 -> 0
A42: 35 | B42: Paket Roma 3 | C42: Paket Prenic 2 | N42: =SUM(D42:M42) -> 0 | O42: =N42*S42 -> 0 | P42: =(O42/O112)*100 -> #DIV/0! | R42: =P42*Q42 -> #DIV/0! | S42: 33750 | U42: =D42*S42 -> 0 | V42: =E42*S42 -> 0 | W42: =F42*S42 -> 0 | X42: =G42*S42 -> 0 | Y42: =H42*S42 -> 0 | Z42: =I42*S42 -> 0 | AA42: =J42*S42 -> 0 | AB42: =K42*S42 -> 0 | AC42: =L42*S42 -> 0 | AD42: =M42*S42 -> 0
A43: 36 | B43: Paket Roma 4 | C43: Paket Prenic 3 | N43: =SUM(D43:M43) -> 0 | O43: =N43*S43 -> 0 | P43: =(O43/O112)*100 -> #DIV/0! | R43: =P43*Q43 -> #DIV/0! | S43: 32400 | U43: =D43*S43 -> 0 | V43: =E43*S43 -> 0 | W43: =F43*S43 -> 0 | X43: =G43*S43 -> 0 | Y43: =H43*S43 -> 0 | Z43: =I43*S43 -> 0 | AA43: =J43*S43 -> 0 | AB43: =K43*S43 -> 0 | AC43: =L43*S43 -> 0 | AD43: =M43*S43 -> 0
A44: 37 | B44: Paket Roma 5 | C44: Paket Prenic 4 | N44: =SUM(D44:M44) -> 0 | O44: =N44*S44 -> 0 | P44: =(O44/O112)*100 -> #DIV/0! | R44: =P44*Q44 -> #DIV/0! | S44: 29700 | U44: =D44*S44 -> 0 | V44: =E44*S44 -> 0 | W44: =F44*S44 -> 0 | X44: =G44*S44 -> 0 | Y44: =H44*S44 -> 0 | Z44: =I44*S44 -> 0 | AA44: =J44*S44 -> 0 | AB44: =K44*S44 -> 0 | AC44: =L44*S44 -> 0 | AD44: =M44*S44 -> 0
A45: 38 | O45: =N45*S45 -> 0 | P45: =(O45/O112)*100 -> #DIV/0! | R45: =P45*Q45 -> #DIV/0! | U45: =D45*S45 -> 0 | V45: =E45*S45 -> 0 | W45: =F45*S45 -> 0 | X45: =G45*S45 -> 0 | Y45: =H45*S45 -> 0 | Z45: =I45*S45 -> 0 | AA45: =J45*S45 -> 0 | AB45: =K45*S45 -> 0 | AC45: =L45*S45 -> 0 | AD45: =M45*S45 -> 0
A46: 39 | B46: Paket Geprek 1 | C46: Geprek Sayap | N46: =SUM(D46:M46) -> 0 | O46: =N46*S46 -> 0 | P46: =(O46/O112)*100 -> #DIV/0! | R46: =P46*Q46 -> #DIV/0! | S46: 18900 | U46: =D46*S46 -> 0 | V46: =E46*S46 -> 0 | W46: =F46*S46 -> 0 | X46: =G46*S46 -> 0 | Y46: =H46*S46 -> 0 | Z46: =I46*S46 -> 0 | AA46: =J46*S46 -> 0 | AB46: =K46*S46 -> 0 | AC46: =L46*S46 -> 0 | AD46: =M46*S46 -> 0
A47: 40 | B47: Paket Geprek 2 | C47: Geprek Paha Bawah | N47: =SUM(D47:M47) -> 0 | O47: =N47*S47 -> 0 | P47: =(O47/O112)*100 -> #DIV/0! | R47: =P47*Q47 -> #DIV/0! | S47: 20250 | U47: =D47*S47 -> 0 | V47: =E47*S47 -> 0 | W47: =F47*S47 -> 0 | X47: =G47*S47 -> 0 | Y47: =H47*S47 -> 0 | Z47: =I47*S47 -> 0 | AA47: =J47*S47 -> 0 | AB47: =K47*S47 -> 0 | AC47: =L47*S47 -> 0 | AD47: =M47*S47 -> 0
A48: 41 | B48: Paket Geprek 3 | C48: Geprek Dada/Paha Atas | N48: =SUM(D48:M48) -> 0 | O48: =N48*S48 -> 0 | P48: =(O48/O112)*100 -> #DIV/0! | R48: =P48*Q48 -> #DIV/0! | S48: 22950 | U48: =D48*S48 -> 0 | V48: =E48*S48 -> 0 | W48: =F48*S48 -> 0 | X48: =G48*S48 -> 0 | Y48: =H48*S48 -> 0 | Z48: =I48*S48 -> 0 | AA48: =J48*S48 -> 0 | AB48: =K48*S48 -> 0 | AC48: =L48*S48 -> 0 | AD48: =M48*S48 -> 0
A49: 42 | B49: Geprek Sayap | C49: Sambel Geprek | N49: =SUM(D49:M49) -> 0 | O49: =N49*S49 -> 0 | P49: =(O49/O112)*100 -> #DIV/0! | R49: =P49*Q49 -> #DIV/0! | S49: 5400 | U49: =D49*S49 -> 0 | V49: =E49*S49 -> 0 | W49: =F49*S49 -> 0 | X49: =G49*S49 -> 0 | Y49: =H49*S49 -> 0 | Z49: =I49*S49 -> 0 | AA49: =J49*S49 -> 0 | AB49: =K49*S49 -> 0 | AC49: =L49*S49 -> 0 | AD49: =M49*S49 -> 0
A50: 43 | O50: =N50*S50 -> 0 | P50: =(O50/O112)*100 -> #DIV/0! | R50: =P50*Q50 -> #DIV/0! | U50: =D50*S50 -> 0 | V50: =E50*S50 -> 0 | W50: =F50*S50 -> 0 | X50: =G50*S50 -> 0 | Y50: =H50*S50 -> 0 | Z50: =I50*S50 -> 0 | AA50: =J50*S50 -> 0 | AB50: =K50*S50 -> 0 | AC50: =L50*S50 -> 0 | AD50: =M50*S50 -> 0
A51: 44 | B51: Geprek Paha Bawah | C51: Paket Panic 1 | N51: =SUM(D51:M51) -> 0 | O51: =N51*S51 -> 0 | P51: =(O51/O112)*100 -> #DIV/0! | R51: =P51*Q51 -> #DIV/0! | S51: 31050 | U51: =D51*S51 -> 0 | V51: =E51*S51 -> 0 | W51: =F51*S51 -> 0 | X51: =G51*S51 -> 0 | Y51: =H51*S51 -> 0 | Z51: =I51*S51 -> 0 | AA51: =J51*S51 -> 0 | AB51: =K51*S51 -> 0 | AC51: =L51*S51 -> 0 | AD51: =M51*S51 -> 0
A52: 45 | B52: Geprek Paha Atas / Dada | C52: Paket Panic 2 | N52: =SUM(D52:M52) -> 0 | O52: =N52*S52 -> 0 | P52: =(O52/O112)*100 -> #DIV/0! | R52: =P52*Q52 -> #DIV/0! | S52: 32400 | U52: =D52*S52 -> 0 | V52: =E52*S52 -> 0 | W52: =F52*S52 -> 0 | X52: =G52*S52 -> 0 | Y52: =H52*S52 -> 0 | Z52: =I52*S52 -> 0 | AA52: =J52*S52 -> 0 | AB52: =K52*S52 -> 0 | AC52: =L52*S52 -> 0 | AD52: =M52*S52 -> 0
A53: 46 | B53: Sambal Geprek | C53: Paket Panic 3 | N53: =SUM(D53:M53) -> 0 | O53: =N53*S53 -> 0 | P53: =(O53/O112)*100 -> #DIV/0! | R53: =P53*Q53 -> #DIV/0! | S53: 24300 | U53: =D53*S53 -> 0 | V53: =E53*S53 -> 0 | W53: =F53*S53 -> 0 | X53: =G53*S53 -> 0 | Y53: =H53*S53 -> 0 | Z53: =I53*S53 -> 0 | AA53: =J53*S53 -> 0 | AB53: =K53*S53 -> 0 | AC53: =L53*S53 -> 0 | AD53: =M53*S53 -> 0
A54: 47 | C54: Paket Panic 4 | N54: =SUM(D54:M54) -> 0 | O54: =N54*S54 -> 0 | P54: =(O54/O112)*100 -> #DIV/0! | R54: =P54*Q54 -> #DIV/0! | S54: 32400 | U54: =D54*S54 -> 0 | V54: =E54*S54 -> 0 | W54: =F54*S54 -> 0 | X54: =G54*S54 -> 0 | Y54: =H54*S54 -> 0 | Z54: =I54*S54 -> 0 | AA54: =J54*S54 -> 0 | AB54: =K54*S54 -> 0 | AC54: =L54*S54 -> 0 | AD54: =M54*S54 -> 0
A55: 48 | B55: Paket Geprek Matah 1 | O55: =N55*S55 -> 0 | P55: =(O55/O112)*100 -> #DIV/0! | R55: =P55*Q55 -> #DIV/0! | U55: =D55*S55 -> 0 | V55: =E55*S55 -> 0 | W55: =F55*S55 -> 0 | X55: =G55*S55 -> 0 | Y55: =H55*S55 -> 0 | Z55: =I55*S55 -> 0 | AA55: =J55*S55 -> 0 | AB55: =K55*S55 -> 0 | AC55: =L55*S55 -> 0 | AD55: =M55*S55 -> 0
A56: 49 | B56: Paket Geprek Matah 2 | C56: Cattring 1 | N56: =SUM(D56:M56) -> 0 | O56: =N56*S56 -> 0 | P56: =(O56/O112)*100 -> #DIV/0! | R56: =P56*Q56 -> #DIV/0! | S56: 15525 | U56: =D56*S56 -> 0 | V56: =E56*S56 -> 0 | W56: =F56*S56 -> 0 | X56: =G56*S56 -> 0 | Y56: =H56*S56 -> 0 | Z56: =I56*S56 -> 0 | AA56: =J56*S56 -> 0 | AB56: =K56*S56 -> 0 | AC56: =L56*S56 -> 0 | AD56: =M56*S56 -> 0
A57: 50 | B57: Paket Geprek Matah 3 | C57: Cattring 2 | N57: =SUM(D57:M57) -> 0 | O57: =N57*S57 -> 0 | P57: =(O57/O112)*100 -> #DIV/0! | R57: =P57*Q57 -> #DIV/0! | S57: 17550 | U57: =D57*S57 -> 0 | V57: =E57*S57 -> 0 | W57: =F57*S57 -> 0 | X57: =G57*S57 -> 0 | Y57: =H57*S57 -> 0 | Z57: =I57*S57 -> 0 | AA57: =J57*S57 -> 0 | AB57: =K57*S57 -> 0 | AC57: =L57*S57 -> 0 | AD57: =M57*S57 -> 0
A58: 51 | B58: Geprek Matah Sayap | C58: Cattring 3 | N58: =SUM(D58:M58) -> 0 | O58: =N58*S58 -> 0 | P58: =(O58/O112)*100 -> #DIV/0! | R58: =P58*Q58 -> #DIV/0! | S58: 21600 | U58: =D58*S58 -> 0 | V58: =E58*S58 -> 0 | W58: =F58*S58 -> 0 | X58: =G58*S58 -> 0 | Y58: =H58*S58 -> 0 | Z58: =I58*S58 -> 0 | AA58: =J58*S58 -> 0 | AB58: =K58*S58 -> 0 | AC58: =L58*S58 -> 0 | AD58: =M58*S58 -> 0
A59: 52 | B59: Geprek Matah Paha Bawah | O59: =N59*S59 -> 0 | P59: =(O59/O112)*100 -> #DIV/0! | R59: =P59*Q59 -> #DIV/0! | U59: =D59*S59 -> 0 | V59: =E59*S59 -> 0 | W59: =F59*S59 -> 0 | X59: =G59*S59 -> 0 | Y59: =H59*S59 -> 0 | Z59: =I59*S59 -> 0 | AA59: =J59*S59 -> 0 | AB59: =K59*S59 -> 0 | AC59: =L59*S59 -> 0 | AD59: =M59*S59 -> 0
A60: 53 | B60: Geprek Matah Paha Atas / Dada | C60: Super Sonic 1 | N60: =SUM(D60:M60) -> 0 | O60: =N60*S60 -> 0 | P60: =(O60/O112)*100 -> #DIV/0! | R60: =P60*Q60 -> #DIV/0! | S60: 101250 | U60: =D60*S60 -> 0 | V60: =E60*S60 -> 0 | W60: =F60*S60 -> 0 | X60: =G60*S60 -> 0 | Y60: =H60*S60 -> 0 | Z60: =I60*S60 -> 0 | AA60: =J60*S60 -> 0 | AB60: =K60*S60 -> 0 | AC60: =L60*S60 -> 0 | AD60: =M60*S60 -> 0
A61: 54 | B61: Sambal Geprek Matah | C61: Super Sonic 2 | N61: =SUM(D61:M61) -> 0 | O61: =N61*S61 -> 0 | P61: =(O61/O112)*100 -> #DIV/0! | R61: =P61*Q61 -> #DIV/0! | S61: 114750 | U61: =D61*S61 -> 0 | V61: =E61*S61 -> 0 | W61: =F61*S61 -> 0 | X61: =G61*S61 -> 0 | Y61: =H61*S61 -> 0 | Z61: =I61*S61 -> 0 | AA61: =J61*S61 -> 0 | AB61: =K61*S61 -> 0 | AC61: =L61*S61 -> 0 | AD61: =M61*S61 -> 0
A62: 55 | C62: Super Sonic 3 | N62: =SUM(D62:M62) -> 0 | O62: =N62*S62 -> 0 | P62: =(O62/O112)*100 -> #DIV/0! | R62: =P62*Q62 -> #DIV/0! | S62: 121500 | U62: =D62*S62 -> 0 | V62: =E62*S62 -> 0 | W62: =F62*S62 -> 0 | X62: =G62*S62 -> 0 | Y62: =H62*S62 -> 0 | Z62: =I62*S62 -> 0 | AA62: =J62*S62 -> 0 | AB62: =K62*S62 -> 0 | AC62: =L62*S62 -> 0 | AD62: =M62*S62 -> 0
A63: 56 | B63: Paket Geprek Terasi 1 | C63: Super Sonic 4 | N63: =SUM(D63:M63) -> 0 | O63: =N63*S63 -> 0 | P63: =(O63/O112)*100 -> #DIV/0! | R63: =P63*Q63 -> #DIV/0! | S63: 135000 | U63: =D63*S63 -> 0 | V63: =E63*S63 -> 0 | W63: =F63*S63 -> 0 | X63: =G63*S63 -> 0 | Y63: =H63*S63 -> 0 | Z63: =I63*S63 -> 0 | AA63: =J63*S63 -> 0 | AB63: =K63*S63 -> 0 | AC63: =L63*S63 -> 0 | AD63: =M63*S63 -> 0
A64: 57 | B64: Paket Geprek Terasi 2 | O64: =N64*S64 -> 0 | P64: =(O64/O112)*100 -> #DIV/0! | R64: =P64*Q64 -> #DIV/0! | U64: =D64*S64 -> 0 | V64: =E64*S64 -> 0 | W64: =F64*S64 -> 0 | X64: =G64*S64 -> 0 | Y64: =H64*S64 -> 0 | Z64: =I64*S64 -> 0 | AA64: =J64*S64 -> 0 | AB64: =K64*S64 -> 0 | AC64: =L64*S64 -> 0 | AD64: =M64*S64 -> 0
A65: 58 | B65: Paket Geprek Terasi 3 | C65: Paket Ceria 1 | N65: =SUM(D65:M65) -> 0 | O65: =N65*S65 -> 0 | P65: =(O65/O112)*100 -> #DIV/0! | R65: =P65*Q65 -> #DIV/0! | S65: 14850 | U65: =D65*S65 -> 0 | V65: =E65*S65 -> 0 | W65: =F65*S65 -> 0 | X65: =G65*S65 -> 0 | Y65: =H65*S65 -> 0 | Z65: =I65*S65 -> 0 | AA65: =J65*S65 -> 0 | AB65: =K65*S65 -> 0 | AC65: =L65*S65 -> 0 | AD65: =M65*S65 -> 0
A66: 59 | C66: Paket Ceria 2 | N66: =SUM(D66:M66) -> 0 | O66: =N66*S66 -> 0 | P66: =(O66/O112)*100 -> #DIV/0! | R66: =P66*Q66 -> #DIV/0! | S66: 16200 | U66: =D66*S66 -> 0 | V66: =E66*S66 -> 0 | W66: =F66*S66 -> 0 | X66: =G66*S66 -> 0 | Y66: =H66*S66 -> 0 | Z66: =I66*S66 -> 0 | AA66: =J66*S66 -> 0 | AB66: =K66*S66 -> 0 | AC66: =L66*S66 -> 0 | AD66: =M66*S66 -> 0
A67: 60 | C67: Paket Ceria 3 | N67: =SUM(D67:M67) -> 0 | O67: =N67*S67 -> 0 | P67: =(O67/O112)*100 -> #DIV/0! | R67: =P67*Q67 -> #DIV/0! | S67: 17550 | U67: =D67*S67 -> 0 | V67: =E67*S67 -> 0 | W67: =F67*S67 -> 0 | X67: =G67*S67 -> 0 | Y67: =H67*S67 -> 0 | Z67: =I67*S67 -> 0 | AA67: =J67*S67 -> 0 | AB67: =K67*S67 -> 0 | AC67: =L67*S67 -> 0 | AD67: =M67*S67 -> 0
A68: 61 | C68: Paket Ceria 4 | N68: =SUM(D68:M68) -> 0 | O68: =N68*S68 -> 0 | P68: =(O68/O112)*100 -> #DIV/0! | R68: =P68*Q68 -> #DIV/0! | S68: 20250 | U68: =D68*S68 -> 0 | V68: =E68*S68 -> 0 | W68: =F68*S68 -> 0 | X68: =G68*S68 -> 0 | Y68: =H68*S68 -> 0 | Z68: =I68*S68 -> 0 | AA68: =J68*S68 -> 0 | AB68: =K68*S68 -> 0 | AC68: =L68*S68 -> 0 | AD68: =M68*S68 -> 0
A69: 62 | O69: =N69*S69 -> 0 | P69: =(O69/O112)*100 -> #DIV/0! | R69: =P69*Q69 -> #DIV/0! | U69: =D69*S69 -> 0 | V69: =E69*S69 -> 0 | W69: =F69*S69 -> 0 | X69: =G69*S69 -> 0 | Y69: =H69*S69 -> 0 | Z69: =I69*S69 -> 0 | AA69: =J69*S69 -> 0 | AB69: =K69*S69 -> 0 | AC69: =L69*S69 -> 0 | AD69: =M69*S69 -> 0
A70: 63 | C70: CFD 1 | N70: =SUM(D70:M70) -> 0 | O70: =N70*S70 -> 0 | P70: =(O70/O112)*100 -> #DIV/0! | R70: =P70*Q70 -> #DIV/0! | S70: 10800 | U70: =D70*S70 -> 0 | V70: =E70*S70 -> 0 | W70: =F70*S70 -> 0 | X70: =G70*S70 -> 0 | Y70: =H70*S70 -> 0 | Z70: =I70*S70 -> 0 | AA70: =J70*S70 -> 0 | AB70: =K70*S70 -> 0 | AC70: =L70*S70 -> 0 | AD70: =M70*S70 -> 0
A71: 64 | C71: CFD 2 | N71: =SUM(D71:M71) -> 0 | O71: =N71*S71 -> 0 | P71: =(O71/O112)*100 -> #DIV/0! | R71: =P71*Q71 -> #DIV/0! | S71: 16200 | U71: =D71*S71 -> 0 | V71: =E71*S71 -> 0 | W71: =F71*S71 -> 0 | X71: =G71*S71 -> 0 | Y71: =H71*S71 -> 0 | Z71: =I71*S71 -> 0 | AA71: =J71*S71 -> 0 | AB71: =K71*S71 -> 0 | AC71: =L71*S71 -> 0 | AD71: =M71*S71 -> 0
A72: 65 | C72: CFD 3 | N72: =SUM(D72:M72) -> 0 | O72: =N72*S72 -> 0 | P72: =(O72/O112)*100 -> #DIV/0! | R72: =P72*Q72 -> #DIV/0! | S72: 20250 | U72: =D72*S72 -> 0 | V72: =E72*S72 -> 0 | W72: =F72*S72 -> 0 | X72: =G72*S72 -> 0 | Y72: =H72*S72 -> 0 | Z72: =I72*S72 -> 0 | AA72: =J72*S72 -> 0 | AB72: =K72*S72 -> 0 | AC72: =L72*S72 -> 0 | AD72: =M72*S72 -> 0
A73: 66 | N73: =SUM(D73:M73) -> 0 | O73: =N73*S73 -> 0 | P73: =(O73/O112)*100 -> #DIV/0! | R73: =P73*Q73 -> #DIV/0! | U73: =D73*S73 -> 0 | V73: =E73*S73 -> 0 | W73: =F73*S73 -> 0 | X73: =G73*S73 -> 0 | Y73: =H73*S73 -> 0 | Z73: =I73*S73 -> 0 | AA73: =J73*S73 -> 0 | AB73: =K73*S73 -> 0 | AC73: =L73*S73 -> 0 | AD73: =M73*S73 -> 0
A74: 67 | C74: Telor Ceplok | N74: =SUM(D74:M74) -> 0 | O74: =N74*S74 -> 0 | P74: =(O74/O112)*100 -> #DIV/0! | R74: =P74*Q74 -> #DIV/0! | S74: 6750 | U74: =D74*S74 -> 0 | V74: =E74*S74 -> 0 | W74: =F74*S74 -> 0 | X74: =G74*S74 -> 0 | Y74: =H74*S74 -> 0 | Z74: =I74*S74 -> 0 | AA74: =J74*S74 -> 0 | AB74: =K74*S74 -> 0 | AC74: =L74*S74 -> 0 | AD74: =M74*S74 -> 0
A75: 68 | N75: =SUM(D75:M75) -> 0 | O75: =N75*S75 -> 0 | P75: =(O75/O112)*100 -> #DIV/0! | R75: =P75*Q75 -> #DIV/0! | U75: =D75*S75 -> 0 | V75: =E75*S75 -> 0 | W75: =F75*S75 -> 0 | X75: =G75*S75 -> 0 | Y75: =H75*S75 -> 0 | Z75: =I75*S75 -> 0 | AA75: =J75*S75 -> 0 | AB75: =K75*S75 -> 0 | AC75: =L75*S75 -> 0 | AD75: =M75*S75 -> 0
A76: 69 | C76: Paket C.Steak Blackpepper | N76: =SUM(D76:M76) -> 0 | O76: =N76*S76 -> 0 | P76: =(O76/O112)*100 -> #DIV/0! | R76: =P76*Q76 -> #DIV/0! | S76: 31050 | U76: =D76*S76 -> 0 | V76: =E76*S76 -> 0 | W76: =F76*S76 -> 0 | X76: =G76*S76 -> 0 | Y76: =H76*S76 -> 0 | Z76: =I76*S76 -> 0 | AA76: =J76*S76 -> 0 | AB76: =K76*S76 -> 0 | AC76: =L76*S76 -> 0 | AD76: =M76*S76 -> 0
A77: 70 | C77: Paket C.Steak Es Teh | N77: =SUM(D77:M77) -> 0 | O77: =N77*S77 -> 0 | P77: =(O77/O112)*100 -> #DIV/0! | R77: =P77*Q77 -> #DIV/0! | S77: 28350 | U77: =D77*S77 -> 0 | V77: =E77*S77 -> 0 | W77: =F77*S77 -> 0 | X77: =G77*S77 -> 0 | Y77: =H77*S77 -> 0 | Z77: =I77*S77 -> 0 | AA77: =J77*S77 -> 0 | AB77: =K77*S77 -> 0 | AC77: =L77*S77 -> 0 | AD77: =M77*S77 -> 0
A78: 71 | N78: =SUM(D78:M78) -> 0 | O78: =N78*S78 -> 0 | P78: =(O78/O112)*100 -> #DIV/0! | R78: =P78*Q78 -> #DIV/0! | U78: =D78*S78 -> 0 | V78: =E78*S78 -> 0 | W78: =F78*S78 -> 0 | X78: =G78*S78 -> 0 | Y78: =H78*S78 -> 0 | Z78: =I78*S78 -> 0 | AA78: =J78*S78 -> 0 | AB78: =K78*S78 -> 0 | AC78: =L78*S78 -> 0 | AD78: =M78*S78 -> 0
A79: 72 | C79: Paket Skin TN | N79: =SUM(D79:M79) -> 0 | O79: =N79*S79 -> 0 | P79: =(O79/O112)*100 -> #DIV/0! | R79: =P79*Q79 -> #DIV/0! | S79: 16200 | U79: =D79*S79 -> 0 | V79: =E79*S79 -> 0 | W79: =F79*S79 -> 0 | X79: =G79*S79 -> 0 | Y79: =H79*S79 -> 0 | Z79: =I79*S79 -> 0 | AA79: =J79*S79 -> 0 | AB79: =K79*S79 -> 0 | AC79: =L79*S79 -> 0 | AD79: =M79*S79 -> 0
A80: 73 | C80: Paket Skin PN | N80: =SUM(D80:M80) -> 0 | O80: =N80*S80 -> 0 | P80: =(O80/O112)*100 -> #DIV/0! | R80: =P80*Q80 -> #DIV/0! | S80: 20250 | U80: =D80*S80 -> 0 | V80: =E80*S80 -> 0 | W80: =F80*S80 -> 0 | X80: =G80*S80 -> 0 | Y80: =H80*S80 -> 0 | Z80: =I80*S80 -> 0 | AA80: =J80*S80 -> 0 | AB80: =K80*S80 -> 0 | AC80: =L80*S80 -> 0 | AD80: =M80*S80 -> 0
A81: 74 | N81: =SUM(D81:M81) -> 0 | O81: =N81*S81 -> 0 | P81: =(O81/O112)*100 -> #DIV/0! | R81: =P81*Q81 -> #DIV/0! | U81: =D81*S81 -> 0 | V81: =E81*S81 -> 0 | W81: =F81*S81 -> 0 | X81: =G81*S81 -> 0 | Y81: =H81*S81 -> 0 | Z81: =I81*S81 -> 0 | AA81: =J81*S81 -> 0 | AB81: =K81*S81 -> 0 | AC81: =L81*S81 -> 0 | AD81: =M81*S81 -> 0
A82: 75 | N82: =SUM(D82:M82) -> 0 | O82: =N82*S82 -> 0 | P82: =(O82/O112)*100 -> #DIV/0! | R82: =P82*Q82 -> #DIV/0! | U82: =D82*S82 -> 0 | V82: =E82*S82 -> 0 | W82: =F82*S82 -> 0 | X82: =G82*S82 -> 0 | Y82: =H82*S82 -> 0 | Z82: =I82*S82 -> 0 | AA82: =J82*S82 -> 0 | AB82: =K82*S82 -> 0 | AC82: =L82*S82 -> 0 | AD82: =M82*S82 -> 0
B83: TOTAL FOOD | C83: =B83 -> TOTAL FOOD | D83: =U83 -> 0 | E83: =V83 -> 0 | F83: =W83 -> 0 | G83: =X83 -> 0 | H83: =Y83 -> 0 | I83: =Z83 -> 0 | J83: =AA83 -> 0 | K83: =AB83 -> 0 | ... M83: =AD83 -> 0 | O83: =SUM(D83:M83) -> 0 | P83: =SUM(P8:P82)/100 -> #DIV/0! | R83: =SUM(R8:R82)/100 -> #DIV/0! | U83: =SUM(U8:U82) -> 0 | V83: =SUM(V8:V82) -> 0 | W83: =SUM(W8:W82) -> 0 | X83: =SUM(X8:X82) -> 0 | Y83: =SUM(Y8:Y82) -> 0 | Z83: =SUM(Z8:Z82) -> 0 | AA83: =SUM(AA8:AA82) -> 0 | AB83: =SUM(AB8:AB82) -> 0 | ... AD83: =SUM(AD8:AD82) -> 0
A85: NO | B85: BEVERAGES | C85: =B85 -> BEVERAGES
A86: 1 | B86: Air Mineral Botol | C86: =B86 -> Air Mineral Botol | N86: =SUM(D86:M86) -> 0 | O86: =N86*S86 -> 0 | P86: =(O86/O112)*100 -> #DIV/0! | R86: =P86*Q86 -> #DIV/0! | S86: 5400 | U86: =D86*S86 -> 0 | V86: =E86*S86 -> 0 | W86: =F86*S86 -> 0 | X86: =G86*S86 -> 0 | Y86: =H86*S86 -> 0 | Z86: =I86*S86 -> 0 | AA86: =J86*S86 -> 0 | AB86: =K86*S86 -> 0 | AC86: =L86*S86 -> 0 | AD86: =M86*S86 -> 0
A87: 2 | B87: Air Mineral Cup | C87: =B87 -> Air Mineral Cup | N87: =SUM(D87:M87) -> 0 | O87: =N87*S87 -> 0 | P87: =(O87/O112)*100 -> #DIV/0! | R87: =P87*Q87 -> #DIV/0! | S87: 2700 | U87: =D87*S87 -> 0 | V87: =E87*S87 -> 0 | W87: =F87*S87 -> 0 | X87: =G87*S87 -> 0 | Y87: =H87*S87 -> 0 | Z87: =I87*S87 -> 0 | AA87: =J87*S87 -> 0 | AB87: =K87*S87 -> 0 | AC87: =L87*S87 -> 0 | AD87: =M87*S87 -> 0
A88: 3 | B88: Teh Botol | C88: =B88 -> Teh Botol | N88: =SUM(D88:M88) -> 0 | O88: =N88*S88 -> 0 | P88: =(O88/O112)*100 -> #DIV/0! | R88: =P88*Q88 -> #DIV/0! | S88: 8100 | U88: =D88*S88 -> 0 | V88: =E88*S88 -> 0 | W88: =F88*S88 -> 0 | X88: =G88*S88 -> 0 | Y88: =H88*S88 -> 0 | Z88: =I88*S88 -> 0 | AA88: =J88*S88 -> 0 | AB88: =K88*S88 -> 0 | AC88: =L88*S88 -> 0 | AD88: =M88*S88 -> 0
A89: 4 | B89: Teh Sosro Genggam | C89: =B89 -> Teh Sosro Genggam | N89: =SUM(D89:M89) -> 0 | O89: =N89*S89 -> 0 | P89: =(O89/O112)*100 -> #DIV/0! | R89: =P89*Q89 -> #DIV/0! | S89: 8100 | U89: =D89*S89 -> 0 | V89: =E89*S89 -> 0 | W89: =F89*S89 -> 0 | X89: =G89*S89 -> 0 | Y89: =H89*S89 -> 0 | Z89: =I89*S89 -> 0 | AA89: =J89*S89 -> 0 | AB89: =K89*S89 -> 0 | AC89: =L89*S89 -> 0 | AD89: =M89*S89 -> 0
A90: 5 | B90: Fruit Tea Botol | N90: =SUM(D90:M90) -> 0 | O90: =N90*S90 -> 0 | P90: =(O90/O112)*100 -> #DIV/0! | R90: =P90*Q90 -> #DIV/0! | U90: =D90*S90 -> 0 | V90: =E90*S90 -> 0 | W90: =F90*S90 -> 0 | X90: =G90*S90 -> 0 | Y90: =H90*S90 -> 0 | Z90: =I90*S90 -> 0 | AA90: =J90*S90 -> 0 | AB90: =K90*S90 -> 0 | AC90: =L90*S90 -> 0 | AD90: =M90*S90 -> 0
A91: 6 | B91: Fuit Tea Genggam | C91: S-tee | N91: =SUM(D91:M91) -> 0 | O91: =N91*S91 -> 0 | P91: =(O91/O112)*100 -> #DIV/0! | R91: =P91*Q91 -> #DIV/0! | S91: 4050 | U91: =D91*S91 -> 0 | V91: =E91*S91 -> 0 | W91: =F91*S91 -> 0 | X91: =G91*S91 -> 0 | Y91: =H91*S91 -> 0 | Z91: =I91*S91 -> 0 | AA91: =J91*S91 -> 0 | AB91: =K91*S91 -> 0 | AC91: =L91*S91 -> 0 | AD91: =M91*S91 -> 0
B92: Tebs | O92: =N92*S92 -> 0 | P92: =(O92/O112)*100 -> #DIV/0! | R92: =P92*Q92 -> #DIV/0! | U92: =D92*S92 -> 0 | V92: =E92*S92 -> 0 | W92: =F92*S92 -> 0 | X92: =G92*S92 -> 0 | Y92: =H92*S92 -> 0 | Z92: =I92*S92 -> 0 | AA92: =J92*S92 -> 0 | AB92: =K92*S92 -> 0 | AC92: =L92*S92 -> 0 | AD92: =M92*S92 -> 0
A93: 7 | B93: STEE | C93: Millo | N93: =SUM(D93:M93) -> 0 | O93: =N93*S93 -> 0 | P93: =(O93/O112)*100 -> #DIV/0! | R93: =P93*Q93 -> #DIV/0! | S93: 12150 | U93: =D93*S93 -> 0 | V93: =E93*S93 -> 0 | W93: =F93*S93 -> 0 | X93: =G93*S93 -> 0 | Y93: =H93*S93 -> 0 | Z93: =I93*S93 -> 0 | AA93: =J93*S93 -> 0 | AB93: =K93*S93 -> 0 | AC93: =L93*S93 -> 0 | AD93: =M93*S93 -> 0
A94: 8 | C94: Nestea | N94: =SUM(D94:M94) -> 0 | O94: =N94*S94 -> 0 | P94: =(O94/O112)*100 -> #DIV/0! | R94: =P94*Q94 -> #DIV/0! | S94: 10800 | U94: =D94*S94 -> 0 | V94: =E94*S94 -> 0 | W94: =F94*S94 -> 0 | X94: =G94*S94 -> 0 | Y94: =H94*S94 -> 0 | Z94: =I94*S94 -> 0 | AA94: =J94*S94 -> 0 | AB94: =K94*S94 -> 0 | AC94: =L94*S94 -> 0 | AD94: =M94*S94 -> 0
A95: 9 | B95: Juice Durian Float | C95: Orange Juice | N95: =SUM(D95:M95) -> 0 | O95: =N95*S95 -> 0 | P95: =(O95/O112)*100 -> #DIV/0! | R95: =P95*Q95 -> #DIV/0! | S95: 9450 | U95: =D95*S95 -> 0 | V95: =E95*S95 -> 0 | W95: =F95*S95 -> 0 | X95: =G95*S95 -> 0 | Y95: =H95*S95 -> 0 | Z95: =I95*S95 -> 0 | AA95: =J95*S95 -> 0 | AB95: =K95*S95 -> 0 | AC95: =L95*S95 -> 0 | AD95: =M95*S95 -> 0
A96: 10 | B96: Juice Durian | C96: Orange Float | N96: =SUM(D96:M96) -> 0 | O96: =N96*S96 -> 0 | P96: =(O96/O112)*100 -> #DIV/0! | R96: =P96*Q96 -> #DIV/0! | S96: 12150 | U96: =D96*S96 -> 0 | V96: =E96*S96 -> 0 | W96: =F96*S96 -> 0 | X96: =G96*S96 -> 0 | Y96: =H96*S96 -> 0 | Z96: =I96*S96 -> 0 | AA96: =J96*S96 -> 0 | AB96: =K96*S96 -> 0 | AC96: =L96*S96 -> 0 | AD96: =M96*S96 -> 0
A97: 11 | B97: Juice Melon Float | C97: Avocado Float | N97: =SUM(D97:M97) -> 0 | O97: =N97*S97 -> 0 | P97: =(O97/O112)*100 -> #DIV/0! | R97: =P97*Q97 -> #DIV/0! | S97: 20250 | U97: =D97*S97 -> 0 | V97: =E97*S97 -> 0 | W97: =F97*S97 -> 0 | X97: =G97*S97 -> 0 | Y97: =H97*S97 -> 0 | Z97: =I97*S97 -> 0 | AA97: =J97*S97 -> 0 | AB97: =K97*S97 -> 0 | AC97: =L97*S97 -> 0 | AD97: =M97*S97 -> 0
A98: 12 | B98: Juice Melon | N98: =SUM(D98:M98) -> 0 | O98: =N98*S98 -> 0 | P98: =(O98/O112)*100 -> #DIV/0! | R98: =P98*Q98 -> #DIV/0! | U98: =D98*S98 -> 0 | V98: =E98*S98 -> 0 | W98: =F98*S98 -> 0 | X98: =G98*S98 -> 0 | Y98: =H98*S98 -> 0 | Z98: =I98*S98 -> 0 | AA98: =J98*S98 -> 0 | AB98: =K98*S98 -> 0 | AC98: =L98*S98 -> 0 | AD98: =M98*S98 -> 0
A99: 13 | B99: Juice Strawberry Float | C99: Es Teh | N99: =SUM(D99:M99) -> 0 | O99: =N99*S99 -> 0 | P99: =(O99/O112)*100 -> #DIV/0! | R99: =P99*Q99 -> #DIV/0! | S99: 6740 | U99: =D99*S99 -> 0 | V99: =E99*S99 -> 0 | W99: =F99*S99 -> 0 | X99: =G99*S99 -> 0 | Y99: =H99*S99 -> 0 | Z99: =I99*S99 -> 0 | AA99: =J99*S99 -> 0 | AB99: =K99*S99 -> 0 | AC99: =L99*S99 -> 0 | AD99: =M99*S99 -> 0
A100: 14 | B100: Juice Stawbery | C100: Air Mineral Botol 600ml | N100: =SUM(D100:M100) -> 0 | O100: =N100*S100 -> 0 | P100: =(O100/O112)*100 -> #DIV/0! | R100: =P100*Q100 -> #DIV/0! | U100: =D100*S100 -> 0 | V100: =E100*S100 -> 0 | W100: =F100*S100 -> 0 | X100: =G100*S100 -> 0 | Y100: =H100*S100 -> 0 | Z100: =I100*S100 -> 0 | AA100: =J100*S100 -> 0 | AB100: =K100*S100 -> 0 | AC100: =L100*S100 -> 0 | AD100: =M100*S100 -> 0
A101: 15 | B101: Juice Mangga Float | N101: =SUM(D101:M101) -> 0 | O101: =N101*S101 -> 0 | P101: =(O101/O112)*100 -> #DIV/0! | R101: =P101*Q101 -> #DIV/0! | U101: =D101*S101 -> 0 | V101: =E101*S101 -> 0 | W101: =F101*S101 -> 0 | X101: =G101*S101 -> 0 | Y101: =H101*S101 -> 0 | Z101: =I101*S101 -> 0 | AA101: =J101*S101 -> 0 | AB101: =K101*S101 -> 0 | AC101: =L101*S101 -> 0 | AD101: =M101*S101 -> 0
A102: 16 | B102: Juice Mangga | N102: =SUM(D102:M102) -> 0 | O102: =N102*S102 -> 0 | P102: =(O102/O112)*100 -> #DIV/0! | R102: =P102*Q102 -> #DIV/0! | U102: =D102*S102 -> 0 | V102: =E102*S102 -> 0 | W102: =F102*S102 -> 0 | X102: =G102*S102 -> 0 | Y102: =H102*S102 -> 0 | Z102: =I102*S102 -> 0 | AA102: =J102*S102 -> 0 | AB102: =K102*S102 -> 0 | AC102: =L102*S102 -> 0 | AD102: =M102*S102 -> 0
B103: Juice Jambu Float | N103: =SUM(D103:M103) -> 0 | O103: =N103*S103 -> 0 | P103: =(O103/O112)*100 -> #DIV/0! | R103: =P103*Q103 -> #DIV/0! | U103: =D103*S103 -> 0 | V103: =E103*S103 -> 0 | W103: =F103*S103 -> 0 | X103: =G103*S103 -> 0 | Y103: =H103*S103 -> 0 | Z103: =I103*S103 -> 0 | AA103: =J103*S103 -> 0 | AB103: =K103*S103 -> 0 | AC103: =L103*S103 -> 0 | AD103: =M103*S103 -> 0
...

Sheet LAP. PENJUALAN GOFOOD
A2: LAPORAN PENJUALAN GOFOOD
M3: Cabang : | O3: =LPKK!Q4 -> SC MARABAHAN
M4: Periode : | O4: =LPKK!Q5 -> 1-7 JULI 2026
A6: NO | B6: PRODUCT | C6: =B6 -> PRODUCT | D6: ='LAP. PENJUALAN REGULER'!D6 -> 1 | E6: ='LAP. PENJUALAN REGULER'!E6 -> 2 | F6: ='LAP. PENJUALAN REGULER'!F6 -> 3 | G6: ='LAP. PENJUALAN REGULER'!G6 -> 4 | H6: ='LAP. PENJUALAN REGULER'!H6 -> 5 | I6: ='LAP. PENJUALAN REGULER'!I6 -> 6 | J6: ='LAP. PENJUALAN REGULER'!J6 -> 7 | K6: ='LAP. PENJUALAN REGULER'!K6 -> 0 | ... M6: ='LAP. PENJUALAN REGULER'!M6 -> 0 | N6: TOTAL | P6: % | Q6: FC ITEM | R6: CON FC | S6: Harga
D7: ='LAP. PENJUALAN REGULER'!D7 -> Rabu | E7: ='LAP. PENJUALAN REGULER'!E7 -> Kamis | F7: ='LAP. PENJUALAN REGULER'!F7 -> Jum`at | G7: ='LAP. PENJUALAN REGULER'!G7 -> Sabtu | H7: ='LAP. PENJUALAN REGULER'!H7 -> Minggu | I7: ='LAP. PENJUALAN REGULER'!I7 -> Senin | J7: ='LAP. PENJUALAN REGULER'!J7 -> Sabtu | K7: ='LAP. PENJUALAN REGULER'!K7 -> 0 | ... M7: ='LAP. PENJUALAN REGULER'!M7 -> 0 | N7: UNIT | O7: ( Rp ) | S7: ( Unit )
A8: 1 | B8: Dada | C8: =B8 -> Dada | N8: =SUM(D8:M8) -> 0 | O8: =N8*S8 -> 0 | P8: =(O8/O112)*100 -> #DIV/0! | R8: =P8*Q8 -> #DIV/0! | S8: 19575 | U8: =D8*S8 -> 0 | V8: =E8*S8 -> 0 | W8: =F8*S8 -> 0 | X8: =G8*S8 -> 0 | Y8: =H8*S8 -> 0 | Z8: =I8*S8 -> 0 | AA8: =J8*S8 -> 0 | AB8: =K8*S8 -> 0 | AC8: =L8*S8 -> 0 | AD8: =M8*S8 -> 0
A9: 2 | B9: Paha Atas | C9: =B9 -> Paha Atas | N9: =SUM(D9:M9) -> 0 | O9: =N9*S9 -> 0 | P9: =(O9/O112)*100 -> #DIV/0! | R9: =P9*Q9 -> #DIV/0! | S9: 19575 | U9: =D9*S9 -> 0 | V9: =E9*S9 -> 0 | W9: =F9*S9 -> 0 | X9: =G9*S9 -> 0 | Y9: =H9*S9 -> 0 | Z9: =I9*S9 -> 0 | AA9: =J9*S9 -> 0 | AB9: =K9*S9 -> 0 | AC9: =L9*S9 -> 0 | AD9: =M9*S9 -> 0
A10: 3 | B10: Paha Bawah | C10: =B10 -> Paha Bawah | N10: =SUM(D10:M10) -> 0 | O10: =N10*S10 -> 0 | P10: =(O10/O112)*100 -> #DIV/0! | R10: =P10*Q10 -> #DIV/0! | S10: 17550 | U10: =D10*S10 -> 0 | V10: =E10*S10 -> 0 | W10: =F10*S10 -> 0 | X10: =G10*S10 -> 0 | Y10: =H10*S10 -> 0 | Z10: =I10*S10 -> 0 | AA10: =J10*S10 -> 0 | AB10: =K10*S10 -> 0 | AC10: =L10*S10 -> 0 | AD10: =M10*S10 -> 0
A11: 4 | B11: Sayap | C11: =B11 -> Sayap | N11: =SUM(D11:M11) -> 0 | O11: =N11*S11 -> 0 | P11: =(O11/O112)*100 -> #DIV/0! | R11: =P11*Q11 -> #DIV/0! | S11: 16200 | U11: =D11*S11 -> 0 | V11: =E11*S11 -> 0 | W11: =F11*S11 -> 0 | X11: =G11*S11 -> 0 | Y11: =H11*S11 -> 0 | Z11: =I11*S11 -> 0 | AA11: =J11*S11 -> 0 | AB11: =K11*S11 -> 0 | AC11: =L11*S11 -> 0 | AD11: =M11*S11 -> 0
A12: 5 | B12: Chicken Strips | C12: =B12 -> Chicken Strips | N12: =SUM(D12:M12) -> 0 | O12: =N12*S12 -> 0 | P12: =(O12/O112)*100 -> #DIV/0! | R12: =P12*Q12 -> #DIV/0! | S12: 16200 | U12: =D12*S12 -> 0 | V12: =E12*S12 -> 0 | W12: =F12*S12 -> 0 | X12: =G12*S12 -> 0 | Y12: =H12*S12 -> 0 | Z12: =I12*S12 -> 0 | AA12: =J12*S12 -> 0 | AB12: =K12*S12 -> 0 | AC12: =L12*S12 -> 0 | AD12: =M12*S12 -> 0
A13: 6 | B13: Chicken Steak | C13: =B13 -> Chicken Steak | N13: =SUM(D13:M13) -> 0 | O13: =N13*S13 -> 0 | P13: =(O13/O112)*100 -> #DIV/0! | R13: =P13*Q13 -> #DIV/0! | S13: 17550 | U13: =D13*S13 -> 0 | V13: =E13*S13 -> 0 | W13: =F13*S13 -> 0 | X13: =G13*S13 -> 0 | Y13: =H13*S13 -> 0 | Z13: =I13*S13 -> 0 | AA13: =J13*S13 -> 0 | AB13: =K13*S13 -> 0 | AC13: =L13*S13 -> 0 | AD13: =M13*S13 -> 0
A14: 7 | C14: Dada Lembut | N14: =SUM(D14:M14) -> 0 | O14: =N14*S14 -> 0 | P14: =(O14/O112)*100 -> #DIV/0! | R14: =P14*Q14 -> #DIV/0! | S14: 19575 | U14: =D14*S14 -> 0 | V14: =E14*S14 -> 0 | W14: =F14*S14 -> 0 | X14: =G14*S14 -> 0 | Y14: =H14*S14 -> 0 | Z14: =I14*S14 -> 0 | AA14: =J14*S14 -> 0 | AB14: =K14*S14 -> 0 | AC14: =L14*S14 -> 0 | AD14: =M14*S14 -> 0
A15: 8 | B15: French Fries | C15: =B15 -> French Fries | N15: =SUM(D15:M15) -> 0 | O15: =N15*S15 -> 0 | P15: =(O15/O112)*100 -> #DIV/0! | R15: =P15*Q15 -> #DIV/0! | S15: 14850 | U15: =D15*S15 -> 0 | V15: =E15*S15 -> 0 | W15: =F15*S15 -> 0 | X15: =G15*S15 -> 0 | Y15: =H15*S15 -> 0 | Z15: =I15*S15 -> 0 | AA15: =J15*S15 -> 0 | AB15: =K15*S15 -> 0 | AC15: =L15*S15 -> 0 | AD15: =M15*S15 -> 0
A16: 9 | B16: Nasi | C16: =B16 -> Nasi | N16: =SUM(D16:M16) -> 0 | O16: =N16*S16 -> 0 | P16: =(O16/O112)*100 -> #DIV/0! | R16: =P16*Q16 -> #DIV/0! | S16: 6750 | U16: =D16*S16 -> 0 | V16: =E16*S16 -> 0 | W16: =F16*S16 -> 0 | X16: =G16*S16 -> 0 | Y16: =H16*S16 -> 0 | Z16: =I16*S16 -> 0 | AA16: =J16*S16 -> 0 | AB16: =K16*S16 -> 0 | AC16: =L16*S16 -> 0 | AD16: =M16*S16 -> 0
A17: 10 | B17: Perkedel | C17: =B17 -> Perkedel | N17: =SUM(D17:M17) -> 0 | O17: =N17*S17 -> 0 | P17: =(O17/O112)*100 -> #DIV/0! | R17: =P17*Q17 -> #DIV/0! | S17: 6750 | U17: =D17*S17 -> 0 | V17: =E17*S17 -> 0 | W17: =F17*S17 -> 0 | X17: =G17*S17 -> 0 | Y17: =H17*S17 -> 0 | Z17: =I17*S17 -> 0 | AA17: =J17*S17 -> 0 | AB17: =K17*S17 -> 0 | AC17: =L17*S17 -> 0 | AD17: =M17*S17 -> 0
A18: 11 | B18: Chicken Burger | C18: =B18 -> Chicken Burger | N18: =SUM(D18:M18) -> 0 | O18: =N18*S18 -> 0 | P18: =(O18/O112)*100 -> #DIV/0! | R18: =P18*Q18 -> #DIV/0! | S18: 20250 | U18: =D18*S18 -> 0 | V18: =E18*S18 -> 0 | W18: =F18*S18 -> 0 | X18: =G18*S18 -> 0 | Y18: =H18*S18 -> 0 | Z18: =I18*S18 -> 0 | AA18: =J18*S18 -> 0 | AB18: =K18*S18 -> 0 | AC18: =L18*S18 -> 0 | AD18: =M18*S18 -> 0
A19: 12 | B19: Cheese Burger | C19: =B19 -> Cheese Burger | N19: =SUM(D19:M19) -> 0 | O19: =N19*S19 -> 0 | P19: =(O19/O112)*100 -> #DIV/0! | R19: =P19*Q19 -> #DIV/0! | S19: 22950 | U19: =D19*S19 -> 0 | V19: =E19*S19 -> 0 | W19: =F19*S19 -> 0 | X19: =G19*S19 -> 0 | Y19: =H19*S19 -> 0 | Z19: =I19*S19 -> 0 | AA19: =J19*S19 -> 0 | AB19: =K19*S19 -> 0 | AC19: =L19*S19 -> 0 | AD19: =M19*S19 -> 0
A20: 13 | B20: Nasi Goreng | C20: =B20 -> Nasi Goreng | N20: =SUM(D20:M20) -> 0 | O20: =N20*S20 -> 0 | P20: =(O20/O112)*100 -> #DIV/0! | R20: =P20*Q20 -> #DIV/0! | S20: 21600 | U20: =D20*S20 -> 0 | V20: =E20*S20 -> 0 | W20: =F20*S20 -> 0 | X20: =G20*S20 -> 0 | Y20: =H20*S20 -> 0 | Z20: =I20*S20 -> 0 | AA20: =J20*S20 -> 0 | AB20: =K20*S20 -> 0 | AC20: =L20*S20 -> 0 | AD20: =M20*S20 -> 0
A21: 14 | B21: Telor Ceplok | C21: Nasi Goreng Spesial | N21: =SUM(D21:M21) -> 0 | O21: =N21*S21 -> 0 | P21: =(O21/O112)*100 -> #DIV/0! | R21: =P21*Q21 -> #DIV/0! | S21: 25650 | U21: =D21*S21 -> 0 | V21: =E21*S21 -> 0 | W21: =F21*S21 -> 0 | X21: =G21*S21 -> 0 | Y21: =H21*S21 -> 0 | Z21: =I21*S21 -> 0 | AA21: =J21*S21 -> 0 | AB21: =K21*S21 -> 0 | AC21: =L21*S21 -> 0 | AD21: =M21*S21 -> 0
A22: 15 | B22: Nasi Goreng Telor Ceplok | C22: Mie Goreng | N22: =SUM(D22:M22) -> 0 | O22: =N22*S22 -> 0 | P22: =(O22/O112)*100 -> #DIV/0! | R22: =P22*Q22 -> #DIV/0! | S22: 21600 | U22: =D22*S22 -> 0 | V22: =E22*S22 -> 0 | W22: =F22*S22 -> 0 | X22: =G22*S22 -> 0 | Y22: =H22*S22 -> 0 | Z22: =I22*S22 -> 0 | AA22: =J22*S22 -> 0 | AB22: =K22*S22 -> 0 | AC22: =L22*S22 -> 0 | AD22: =M22*S22 -> 0
A23: 16 | C23: Chicken 2 Pcs | N23: =SUM(D23:M23) -> 0 | O23: =N23*S23 -> 0 | P23: =(O23/O112)*100 -> #DIV/0! | R23: =P23*Q23 -> #DIV/0! | S23: 33750 | U23: =D23*S23 -> 0 | V23: =E23*S23 -> 0 | W23: =F23*S23 -> 0 | X23: =G23*S23 -> 0 | Y23: =H23*S23 -> 0 | Z23: =I23*S23 -> 0 | AA23: =J23*S23 -> 0 | AB23: =K23*S23 -> 0 | AC23: =L23*S23 -> 0 | AD23: =M23*S23 -> 0
A24: 17 | N24: =SUM(D24:M24) -> 0 | O24: =N24*S24 -> 0 | P24: =(O24/O112)*100 -> #DIV/0! | R24: =P24*Q24 -> #DIV/0! | S24: 20250 | U24: =D24*S24 -> 0 | V24: =E24*S24 -> 0 | W24: =F24*S24 -> 0 | X24: =G24*S24 -> 0 | Y24: =H24*S24 -> 0 | Z24: =I24*S24 -> 0 | AA24: =J24*S24 -> 0 | AB24: =K24*S24 -> 0 | AC24: =L24*S24 -> 0 | AD24: =M24*S24 -> 0
A25: 18 | N25: =SUM(D25:M25) -> 0 | O25: =N25*S25 -> 0 | P25: =(O25/O112)*100 -> #DIV/0! | R25: =P25*Q25 -> #DIV/0! | U25: =D25*S25 -> 0 | V25: =E25*S25 -> 0 | W25: =F25*S25 -> 0 | X25: =G25*S25 -> 0 | Y25: =H25*S25 -> 0 | Z25: =I25*S25 -> 0 | AA25: =J25*S25 -> 0 | AB25: =K25*S25 -> 0 | AC25: =L25*S25 -> 0 | AD25: =M25*S25 -> 0
A26: 19 | B26: Paket Rocket 1 | C26: Paket Sonic 1 | N26: =SUM(D26:M26) -> 0 | O26: =N26*S26 -> 0 | P26: =(O26/O112)*100 -> #DIV/0! | R26: =P26*Q26 -> #DIV/0! | S26: 17550 | U26: =D26*S26 -> 0 | V26: =E26*S26 -> 0 | W26: =F26*S26 -> 0 | X26: =G26*S26 -> 0 | Y26: =H26*S26 -> 0 | Z26: =I26*S26 -> 0 | AA26: =J26*S26 -> 0 | AB26: =K26*S26 -> 0 | AC26: =L26*S26 -> 0 | AD26: =M26*S26 -> 0
A27: 20 | B27: Paket Rocket 2 | C27: Paket Sonic 2 | N27: =SUM(D27:M27) -> 0 | O27: =N27*S27 -> 0 | P27: =(O27/O112)*100 -> #DIV/0! | R27: =P27*Q27 -> #DIV/0! | S27: 20250 | U27: =D27*S27 -> 0 | V27: =E27*S27 -> 0 | W27: =F27*S27 -> 0 | X27: =G27*S27 -> 0 | Y27: =H27*S27 -> 0 | Z27: =I27*S27 -> 0 | AA27: =J27*S27 -> 0 | AB27: =K27*S27 -> 0 | AC27: =L27*S27 -> 0 | AD27: =M27*S27 -> 0
A28: 21 | B28: Paket Rocket 3 | C28: Paket Sonic 3 | N28: =SUM(D28:M28) -> 0 | O28: =N28*S28 -> 0 | P28: =(O28/O112)*100 -> #DIV/0! | R28: =P28*Q28 -> #DIV/0! | S28: 32400 | U28: =D28*S28 -> 0 | V28: =E28*S28 -> 0 | W28: =F28*S28 -> 0 | X28: =G28*S28 -> 0 | Y28: =H28*S28 -> 0 | Z28: =I28*S28 -> 0 | AA28: =J28*S28 -> 0 | AB28: =K28*S28 -> 0 | AC28: =L28*S28 -> 0 | AD28: =M28*S28 -> 0
A29: 22 | B29: Paket Rocket 4 | C29: Paket Sonic 4 | N29: =SUM(D29:M29) -> 0 | O29: =N29*S29 -> 0 | P29: =(O29/O112)*100 -> #DIV/0! | R29: =P29*Q29 -> #DIV/0! | S29: 32400 | U29: =D29*S29 -> 0 | V29: =E29*S29 -> 0 | W29: =F29*S29 -> 0 | X29: =G29*S29 -> 0 | Y29: =H29*S29 -> 0 | Z29: =I29*S29 -> 0 | AA29: =J29*S29 -> 0 | AB29: =K29*S29 -> 0 | AC29: =L29*S29 -> 0 | AD29: =M29*S29 -> 0
A30: 23 | B30: Paket Rocket 5 | C30: Paket Sonic 5 | N30: =SUM(D30:M30) -> 0 | O30: =N30*S30 -> 0 | P30: =(O30/O112)*100 -> #DIV/0! | R30: =P30*Q30 -> #DIV/0! | S30: 32400 | U30: =D30*S30 -> 0 | V30: =E30*S30 -> 0 | W30: =F30*S30 -> 0 | X30: =G30*S30 -> 0 | Y30: =H30*S30 -> 0 | Z30: =I30*S30 -> 0 | AA30: =J30*S30 -> 0 | AB30: =K30*S30 -> 0 | AC30: =L30*S30 -> 0 | AD30: =M30*S30 -> 0
A31: 24 | B31: Paket Rocket 6 | C31: Paket Sonic 6 | N31: =SUM(D31:M31) -> 0 | O31: =N31*S31 -> 0 | P31: =(O31/O112)*100 -> #DIV/0! | R31: =P31*Q31 -> #DIV/0! | S31: 37800 | U31: =D31*S31 -> 0 | V31: =E31*S31 -> 0 | W31: =F31*S31 -> 0 | X31: =G31*S31 -> 0 | Y31: =H31*S31 -> 0 | Z31: =I31*S31 -> 0 | AA31: =J31*S31 -> 0 | AB31: =K31*S31 -> 0 | AC31: =L31*S31 -> 0 | AD31: =M31*S31 -> 0
A32: 25 | B32: Paket Rocket 7 | C32: Paket Sonic 7 | N32: =SUM(D32:M32) -> 0 | O32: =N32*S32 -> 0 | P32: =(O32/O112)*100 -> #DIV/0! | R32: =P32*Q32 -> #DIV/0! | S32: 27000 | U32: =D32*S32 -> 0 | V32: =E32*S32 -> 0 | W32: =F32*S32 -> 0 | X32: =G32*S32 -> 0 | Y32: =H32*S32 -> 0 | Z32: =I32*S32 -> 0 | AA32: =J32*S32 -> 0 | AB32: =K32*S32 -> 0 | AC32: =L32*S32 -> 0 | AD32: =M32*S32 -> 0
A33: 26 | C33: Paket Sonic 8 | N33: =SUM(D33:M33) -> 0 | O33: =N33*S33 -> 0 | P33: =(O33/O112)*100 -> #DIV/0! | R33: =P33*Q33 -> #DIV/0! | S33: 32400 | U33: =D33*S33 -> 0 | V33: =E33*S33 -> 0 | W33: =F33*S33 -> 0 | X33: =G33*S33 -> 0 | Y33: =H33*S33 -> 0 | Z33: =I33*S33 -> 0 | AA33: =J33*S33 -> 0 | AB33: =K33*S33 -> 0 | AC33: =L33*S33 -> 0 | AD33: =M33*S33 -> 0
A34: 27 | B34: Paket Rocket 8 | C34: Paket Sonic 9 | N34: =SUM(D34:M34) -> 0 | O34: =N34*S34 -> 0 | P34: =(O34/O112)*100 -> #DIV/0! | R34: =P34*Q34 -> #DIV/0! | U34: =D34*S34 -> 0 | V34: =E34*S34 -> 0 | W34: =F34*S34 -> 0 | X34: =G34*S34 -> 0 | Y34: =H34*S34 -> 0 | Z34: =I34*S34 -> 0 | AA34: =J34*S34 -> 0 | AB34: =K34*S34 -> 0 | AC34: =L34*S34 -> 0 | AD34: =M34*S34 -> 0
A35: 28 | O35: =N35*S35 -> 0 | P35: =(O35/O112)*100 -> #DIV/0! | R35: =P35*Q35 -> #DIV/0! | U35: =D35*S35 -> 0 | V35: =E35*S35 -> 0 | W35: =F35*S35 -> 0 | X35: =G35*S35 -> 0 | Y35: =H35*S35 -> 0 | Z35: =I35*S35 -> 0 | AA35: =J35*S35 -> 0 | AB35: =K35*S35 -> 0 | AC35: =L35*S35 -> 0 | AD35: =M35*S35 -> 0
A36: 29 | B36: Paket Rocket 9 | C36: Paket Gepso 1 | N36: =SUM(D36:M36) -> 0 | O36: =N36*S36 -> 0 | P36: =(O36/O112)*100 -> #DIV/0! | R36: =P36*Q36 -> #DIV/0! | S36: 28350 | U36: =D36*S36 -> 0 | V36: =E36*S36 -> 0 | W36: =F36*S36 -> 0 | X36: =G36*S36 -> 0 | Y36: =H36*S36 -> 0 | Z36: =I36*S36 -> 0 | AA36: =J36*S36 -> 0 | AB36: =K36*S36 -> 0 | AC36: =L36*S36 -> 0 | AD36: =M36*S36 -> 0
A37: 30 | B37: Paket Rocket 10 | C37: Paket Gepso 2 | N37: =SUM(D37:M37) -> 0 | O37: =N37*S37 -> 0 | P37: =(O37/O112)*100 -> #DIV/0! | R37: =P37*Q37 -> #DIV/0! | S37: 31050 | U37: =D37*S37 -> 0 | V37: =E37*S37 -> 0 | W37: =F37*S37 -> 0 | X37: =G37*S37 -> 0 | Y37: =H37*S37 -> 0 | Z37: =I37*S37 -> 0 | AA37: =J37*S37 -> 0 | AB37: =K37*S37 -> 0 | AC37: =L37*S37 -> 0 | AD37: =M37*S37 -> 0
A38: 31 | C38: Paket Gepso 3 | N38: =SUM(D38:M38) -> 0 | O38: =N38*S38 -> 0 | P38: =(O38/O112)*100 -> #DIV/0! | R38: =P38*Q38 -> #DIV/0! | S38: 33750 | U38: =D38*S38 -> 0 | V38: =E38*S38 -> 0 | W38: =F38*S38 -> 0 | X38: =G38*S38 -> 0 | Y38: =H38*S38 -> 0 | Z38: =I38*S38 -> 0 | AA38: =J38*S38 -> 0 | AB38: =K38*S38 -> 0 | AC38: =L38*S38 -> 0 | AD38: =M38*S38 -> 0
A39: 32 | C39: Paket Gepso 4 | N39: =SUM(D39:M39) -> 0 | O39: =N39*S39 -> 0 | P39: =(O39/O112)*100 -> #DIV/0! | R39: =P39*Q39 -> #DIV/0! | S39: 33750 | U39: =D39*S39 -> 0 | V39: =E39*S39 -> 0 | W39: =F39*S39 -> 0 | X39: =G39*S39 -> 0 | Y39: =H39*S39 -> 0 | Z39: =I39*S39 -> 0 | AA39: =J39*S39 -> 0 | AB39: =K39*S39 -> 0 | AC39: =L39*S39 -> 0 | AD39: =M39*S39 -> 0
A40: 33 | B40: Paket Roma 1 | O40: =N40*S40 -> 0 | P40: =(O40/O112)*100 -> #DIV/0! | R40: =P40*Q40 -> #DIV/0! | U40: =D40*S40 -> 0 | V40: =E40*S40 -> 0 | W40: =F40*S40 -> 0 | X40: =G40*S40 -> 0 | Y40: =H40*S40 -> 0 | Z40: =I40*S40 -> 0 | AA40: =J40*S40 -> 0 | AB40: =K40*S40 -> 0 | AC40: =L40*S40 -> 0 | AD40: =M40*S40 -> 0
A41: 34 | B41: Paket Roma 2 | C41: Paket Prenic 1 | N41: =SUM(D41:M41) -> 0 | O41: =N41*S41 -> 0 | P41: =(O41/O112)*100 -> #DIV/0! | R41: =P41*Q41 -> #DIV/0! | S41: 32400 | U41: =D41*S41 -> 0 | V41: =E41*S41 -> 0 | W41: =F41*S41 -> 0 | X41: =G41*S41 -> 0 | Y41: =H41*S41 -> 0 | Z41: =I41*S41 -> 0 | AA41: =J41*S41 -> 0 | AB41: =K41*S41 -> 0 | AC41: =L41*S41 -> 0 | AD41: =M41*S41 -> 0
A42: 35 | B42: Paket Roma 3 | C42: Paket Prenic 2 | N42: =SUM(D42:M42) -> 0 | O42: =N42*S42 -> 0 | P42: =(O42/O112)*100 -> #DIV/0! | R42: =P42*Q42 -> #DIV/0! | S42: 33750 | U42: =D42*S42 -> 0 | V42: =E42*S42 -> 0 | W42: =F42*S42 -> 0 | X42: =G42*S42 -> 0 | Y42: =H42*S42 -> 0 | Z42: =I42*S42 -> 0 | AA42: =J42*S42 -> 0 | AB42: =K42*S42 -> 0 | AC42: =L42*S42 -> 0 | AD42: =M42*S42 -> 0
A43: 36 | B43: Paket Roma 4 | C43: Paket Prenic 3 | N43: =SUM(D43:M43) -> 0 | O43: =N43*S43 -> 0 | P43: =(O43/O112)*100 -> #DIV/0! | R43: =P43*Q43 -> #DIV/0! | S43: 32400 | U43: =D43*S43 -> 0 | V43: =E43*S43 -> 0 | W43: =F43*S43 -> 0 | X43: =G43*S43 -> 0 | Y43: =H43*S43 -> 0 | Z43: =I43*S43 -> 0 | AA43: =J43*S43 -> 0 | AB43: =K43*S43 -> 0 | AC43: =L43*S43 -> 0 | AD43: =M43*S43 -> 0
A44: 37 | B44: Paket Roma 5 | C44: Paket Prenic 4 | N44: =SUM(D44:M44) -> 0 | O44: =N44*S44 -> 0 | P44: =(O44/O112)*100 -> #DIV/0! | R44: =P44*Q44 -> #DIV/0! | S44: 29700 | U44: =D44*S44 -> 0 | V44: =E44*S44 -> 0 | W44: =F44*S44 -> 0 | X44: =G44*S44 -> 0 | Y44: =H44*S44 -> 0 | Z44: =I44*S44 -> 0 | AA44: =J44*S44 -> 0 | AB44: =K44*S44 -> 0 | AC44: =L44*S44 -> 0 | AD44: =M44*S44 -> 0
A45: 38 | O45: =N45*S45 -> 0 | P45: =(O45/O112)*100 -> #DIV/0! | R45: =P45*Q45 -> #DIV/0! | U45: =D45*S45 -> 0 | V45: =E45*S45 -> 0 | W45: =F45*S45 -> 0 | X45: =G45*S45 -> 0 | Y45: =H45*S45 -> 0 | Z45: =I45*S45 -> 0 | AA45: =J45*S45 -> 0 | AB45: =K45*S45 -> 0 | AC45: =L45*S45 -> 0 | AD45: =M45*S45 -> 0
A46: 39 | B46: Paket Geprek 1 | C46: Geprek Sayap | N46: =SUM(D46:M46) -> 0 | O46: =N46*S46 -> 0 | P46: =(O46/O112)*100 -> #DIV/0! | R46: =P46*Q46 -> #DIV/0! | S46: 18900 | U46: =D46*S46 -> 0 | V46: =E46*S46 -> 0 | W46: =F46*S46 -> 0 | X46: =G46*S46 -> 0 | Y46: =H46*S46 -> 0 | Z46: =I46*S46 -> 0 | AA46: =J46*S46 -> 0 | AB46: =K46*S46 -> 0 | AC46: =L46*S46 -> 0 | AD46: =M46*S46 -> 0
A47: 40 | B47: Paket Geprek 2 | C47: Geprek Paha Bawah | N47: =SUM(D47:M47) -> 0 | O47: =N47*S47 -> 0 | P47: =(O47/O112)*100 -> #DIV/0! | R47: =P47*Q47 -> #DIV/0! | S47: 20250 | U47: =D47*S47 -> 0 | V47: =E47*S47 -> 0 | W47: =F47*S47 -> 0 | X47: =G47*S47 -> 0 | Y47: =H47*S47 -> 0 | Z47: =I47*S47 -> 0 | AA47: =J47*S47 -> 0 | AB47: =K47*S47 -> 0 | AC47: =L47*S47 -> 0 | AD47: =M47*S47 -> 0
A48: 41 | B48: Paket Geprek 3 | C48: Geprek Dada/Paha Atas | N48: =SUM(D48:M48) -> 0 | O48: =N48*S48 -> 0 | P48: =(O48/O112)*100 -> #DIV/0! | R48: =P48*Q48 -> #DIV/0! | S48: 22950 | U48: =D48*S48 -> 0 | V48: =E48*S48 -> 0 | W48: =F48*S48 -> 0 | X48: =G48*S48 -> 0 | Y48: =H48*S48 -> 0 | Z48: =I48*S48 -> 0 | AA48: =J48*S48 -> 0 | AB48: =K48*S48 -> 0 | AC48: =L48*S48 -> 0 | AD48: =M48*S48 -> 0
A49: 42 | B49: Geprek Sayap | C49: Sambel Geprek | N49: =SUM(D49:M49) -> 0 | O49: =N49*S49 -> 0 | P49: =(O49/O112)*100 -> #DIV/0! | R49: =P49*Q49 -> #DIV/0! | S49: 5400 | U49: =D49*S49 -> 0 | V49: =E49*S49 -> 0 | W49: =F49*S49 -> 0 | X49: =G49*S49 -> 0 | Y49: =H49*S49 -> 0 | Z49: =I49*S49 -> 0 | AA49: =J49*S49 -> 0 | AB49: =K49*S49 -> 0 | AC49: =L49*S49 -> 0 | AD49: =M49*S49 -> 0
A50: 43 | O50: =N50*S50 -> 0 | P50: =(O50/O112)*100 -> #DIV/0! | R50: =P50*Q50 -> #DIV/0! | U50: =D50*S50 -> 0 | V50: =E50*S50 -> 0 | W50: =F50*S50 -> 0 | X50: =G50*S50 -> 0 | Y50: =H50*S50 -> 0 | Z50: =I50*S50 -> 0 | AA50: =J50*S50 -> 0 | AB50: =K50*S50 -> 0 | AC50: =L50*S50 -> 0 | AD50: =M50*S50 -> 0
A51: 44 | B51: Geprek Paha Bawah | C51: Paket Panic 1 | N51: =SUM(D51:M51) -> 0 | O51: =N51*S51 -> 0 | P51: =(O51/O112)*100 -> #DIV/0! | R51: =P51*Q51 -> #DIV/0! | S51: 31050 | U51: =D51*S51 -> 0 | V51: =E51*S51 -> 0 | W51: =F51*S51 -> 0 | X51: =G51*S51 -> 0 | Y51: =H51*S51 -> 0 | Z51: =I51*S51 -> 0 | AA51: =J51*S51 -> 0 | AB51: =K51*S51 -> 0 | AC51: =L51*S51 -> 0 | AD51: =M51*S51 -> 0
A52: 45 | B52: Geprek Paha Atas / Dada | C52: Paket Panic 2 | N52: =SUM(D52:M52) -> 0 | O52: =N52*S52 -> 0 | P52: =(O52/O112)*100 -> #DIV/0! | R52: =P52*Q52 -> #DIV/0! | S52: 32400 | U52: =D52*S52 -> 0 | V52: =E52*S52 -> 0 | W52: =F52*S52 -> 0 | X52: =G52*S52 -> 0 | Y52: =H52*S52 -> 0 | Z52: =I52*S52 -> 0 | AA52: =J52*S52 -> 0 | AB52: =K52*S52 -> 0 | AC52: =L52*S52 -> 0 | AD52: =M52*S52 -> 0
A53: 46 | B53: Sambal Geprek | C53: Paket Panic 3 | N53: =SUM(D53:M53) -> 0 | O53: =N53*S53 -> 0 | P53: =(O53/O112)*100 -> #DIV/0! | R53: =P53*Q53 -> #DIV/0! | S53: 24300 | U53: =D53*S53 -> 0 | V53: =E53*S53 -> 0 | W53: =F53*S53 -> 0 | X53: =G53*S53 -> 0 | Y53: =H53*S53 -> 0 | Z53: =I53*S53 -> 0 | AA53: =J53*S53 -> 0 | AB53: =K53*S53 -> 0 | AC53: =L53*S53 -> 0 | AD53: =M53*S53 -> 0
A54: 47 | C54: Paket Panic 4 | N54: =SUM(D54:M54) -> 0 | O54: =N54*S54 -> 0 | P54: =(O54/O112)*100 -> #DIV/0! | R54: =P54*Q54 -> #DIV/0! | S54: 32400 | U54: =D54*S54 -> 0 | V54: =E54*S54 -> 0 | W54: =F54*S54 -> 0 | X54: =G54*S54 -> 0 | Y54: =H54*S54 -> 0 | Z54: =I54*S54 -> 0 | AA54: =J54*S54 -> 0 | AB54: =K54*S54 -> 0 | AC54: =L54*S54 -> 0 | AD54: =M54*S54 -> 0
A55: 48 | B55: Paket Geprek Matah 1 | O55: =N55*S55 -> 0 | P55: =(O55/O112)*100 -> #DIV/0! | R55: =P55*Q55 -> #DIV/0! | U55: =D55*S55 -> 0 | V55: =E55*S55 -> 0 | W55: =F55*S55 -> 0 | X55: =G55*S55 -> 0 | Y55: =H55*S55 -> 0 | Z55: =I55*S55 -> 0 | AA55: =J55*S55 -> 0 | AB55: =K55*S55 -> 0 | AC55: =L55*S55 -> 0 | AD55: =M55*S55 -> 0
A56: 49 | B56: Paket Geprek Matah 2 | C56: Cattring 1 | N56: =SUM(D56:M56) -> 0 | O56: =N56*S56 -> 0 | P56: =(O56/O112)*100 -> #DIV/0! | R56: =P56*Q56 -> #DIV/0! | S56: 15525 | U56: =D56*S56 -> 0 | V56: =E56*S56 -> 0 | W56: =F56*S56 -> 0 | X56: =G56*S56 -> 0 | Y56: =H56*S56 -> 0 | Z56: =I56*S56 -> 0 | AA56: =J56*S56 -> 0 | AB56: =K56*S56 -> 0 | AC56: =L56*S56 -> 0 | AD56: =M56*S56 -> 0
A57: 50 | B57: Paket Geprek Matah 3 | C57: Cattring 2 | N57: =SUM(D57:M57) -> 0 | O57: =N57*S57 -> 0 | P57: =(O57/O112)*100 -> #DIV/0! | R57: =P57*Q57 -> #DIV/0! | S57: 17550 | U57: =D57*S57 -> 0 | V57: =E57*S57 -> 0 | W57: =F57*S57 -> 0 | X57: =G57*S57 -> 0 | Y57: =H57*S57 -> 0 | Z57: =I57*S57 -> 0 | AA57: =J57*S57 -> 0 | AB57: =K57*S57 -> 0 | AC57: =L57*S57 -> 0 | AD57: =M57*S57 -> 0
A58: 51 | B58: Geprek Matah Sayap | C58: Cattring 3 | N58: =SUM(D58:M58) -> 0 | O58: =N58*S58 -> 0 | P58: =(O58/O112)*100 -> #DIV/0! | R58: =P58*Q58 -> #DIV/0! | S58: 21600 | U58: =D58*S58 -> 0 | V58: =E58*S58 -> 0 | W58: =F58*S58 -> 0 | X58: =G58*S58 -> 0 | Y58: =H58*S58 -> 0 | Z58: =I58*S58 -> 0 | AA58: =J58*S58 -> 0 | AB58: =K58*S58 -> 0 | AC58: =L58*S58 -> 0 | AD58: =M58*S58 -> 0
A59: 52 | B59: Geprek Matah Paha Bawah | O59: =N59*S59 -> 0 | P59: =(O59/O112)*100 -> #DIV/0! | R59: =P59*Q59 -> #DIV/0! | U59: =D59*S59 -> 0 | V59: =E59*S59 -> 0 | W59: =F59*S59 -> 0 | X59: =G59*S59 -> 0 | Y59: =H59*S59 -> 0 | Z59: =I59*S59 -> 0 | AA59: =J59*S59 -> 0 | AB59: =K59*S59 -> 0 | AC59: =L59*S59 -> 0 | AD59: =M59*S59 -> 0
A60: 53 | B60: Geprek Matah Paha Atas / Dada | C60: Super Sonic 1 | N60: =SUM(D60:M60) -> 0 | O60: =N60*S60 -> 0 | P60: =(O60/O112)*100 -> #DIV/0! | R60: =P60*Q60 -> #DIV/0! | S60: 101250 | U60: =D60*S60 -> 0 | V60: =E60*S60 -> 0 | W60: =F60*S60 -> 0 | X60: =G60*S60 -> 0 | Y60: =H60*S60 -> 0 | Z60: =I60*S60 -> 0 | AA60: =J60*S60 -> 0 | AB60: =K60*S60 -> 0 | AC60: =L60*S60 -> 0 | AD60: =M60*S60 -> 0
A61: 54 | B61: Sambal Geprek Matah | C61: Super Sonic 2 | N61: =SUM(D61:M61) -> 0 | O61: =N61*S61 -> 0 | P61: =(O61/O112)*100 -> #DIV/0! | R61: =P61*Q61 -> #DIV/0! | S61: 114750 | U61: =D61*S61 -> 0 | V61: =E61*S61 -> 0 | W61: =F61*S61 -> 0 | X61: =G61*S61 -> 0 | Y61: =H61*S61 -> 0 | Z61: =I61*S61 -> 0 | AA61: =J61*S61 -> 0 | AB61: =K61*S61 -> 0 | AC61: =L61*S61 -> 0 | AD61: =M61*S61 -> 0
A62: 55 | C62: Super Sonic 3 | N62: =SUM(D62:M62) -> 0 | O62: =N62*S62 -> 0 | P62: =(O62/O112)*100 -> #DIV/0! | R62: =P62*Q62 -> #DIV/0! | S62: 121500 | U62: =D62*S62 -> 0 | V62: =E62*S62 -> 0 | W62: =F62*S62 -> 0 | X62: =G62*S62 -> 0 | Y62: =H62*S62 -> 0 | Z62: =I62*S62 -> 0 | AA62: =J62*S62 -> 0 | AB62: =K62*S62 -> 0 | AC62: =L62*S62 -> 0 | AD62: =M62*S62 -> 0
A63: 56 | B63: Paket Geprek Terasi 1 | C63: Super Sonic 4 | N63: =SUM(D63:M63) -> 0 | O63: =N63*S63 -> 0 | P63: =(O63/O112)*100 -> #DIV/0! | R63: =P63*Q63 -> #DIV/0! | S63: 135000 | U63: =D63*S63 -> 0 | V63: =E63*S63 -> 0 | W63: =F63*S63 -> 0 | X63: =G63*S63 -> 0 | Y63: =H63*S63 -> 0 | Z63: =I63*S63 -> 0 | AA63: =J63*S63 -> 0 | AB63: =K63*S63 -> 0 | AC63: =L63*S63 -> 0 | AD63: =M63*S63 -> 0
A64: 57 | B64: Paket Geprek Terasi 2 | O64: =N64*S64 -> 0 | P64: =(O64/O112)*100 -> #DIV/0! | R64: =P64*Q64 -> #DIV/0! | U64: =D64*S64 -> 0 | V64: =E64*S64 -> 0 | W64: =F64*S64 -> 0 | X64: =G64*S64 -> 0 | Y64: =H64*S64 -> 0 | Z64: =I64*S64 -> 0 | AA64: =J64*S64 -> 0 | AB64: =K64*S64 -> 0 | AC64: =L64*S64 -> 0 | AD64: =M64*S64 -> 0
A65: 58 | B65: Paket Geprek Terasi 3 | C65: Paket Ceria 1 | N65: =SUM(D65:M65) -> 0 | O65: =N65*S65 -> 0 | P65: =(O65/O112)*100 -> #DIV/0! | R65: =P65*Q65 -> #DIV/0! | S65: 14850 | U65: =D65*S65 -> 0 | V65: =E65*S65 -> 0 | W65: =F65*S65 -> 0 | X65: =G65*S65 -> 0 | Y65: =H65*S65 -> 0 | Z65: =I65*S65 -> 0 | AA65: =J65*S65 -> 0 | AB65: =K65*S65 -> 0 | AC65: =L65*S65 -> 0 | AD65: =M65*S65 -> 0
A66: 59 | C66: Paket Ceria 2 | N66: =SUM(D66:M66) -> 0 | O66: =N66*S66 -> 0 | P66: =(O66/O112)*100 -> #DIV/0! | R66: =P66*Q66 -> #DIV/0! | S66: 16200 | U66: =D66*S66 -> 0 | V66: =E66*S66 -> 0 | W66: =F66*S66 -> 0 | X66: =G66*S66 -> 0 | Y66: =H66*S66 -> 0 | Z66: =I66*S66 -> 0 | AA66: =J66*S66 -> 0 | AB66: =K66*S66 -> 0 | AC66: =L66*S66 -> 0 | AD66: =M66*S66 -> 0
A67: 60 | C67: Paket Ceria 3 | N67: =SUM(D67:M67) -> 0 | O67: =N67*S67 -> 0 | P67: =(O67/O112)*100 -> #DIV/0! | R67: =P67*Q67 -> #DIV/0! | S67: 17550 | U67: =D67*S67 -> 0 | V67: =E67*S67 -> 0 | W67: =F67*S67 -> 0 | X67: =G67*S67 -> 0 | Y67: =H67*S67 -> 0 | Z67: =I67*S67 -> 0 | AA67: =J67*S67 -> 0 | AB67: =K67*S67 -> 0 | AC67: =L67*S67 -> 0 | AD67: =M67*S67 -> 0
A68: 61 | C68: Paket Ceria 4 | N68: =SUM(D68:M68) -> 0 | O68: =N68*S68 -> 0 | P68: =(O68/O112)*100 -> #DIV/0! | R68: =P68*Q68 -> #DIV/0! | S68: 20250 | U68: =D68*S68 -> 0 | V68: =E68*S68 -> 0 | W68: =F68*S68 -> 0 | X68: =G68*S68 -> 0 | Y68: =H68*S68 -> 0 | Z68: =I68*S68 -> 0 | AA68: =J68*S68 -> 0 | AB68: =K68*S68 -> 0 | AC68: =L68*S68 -> 0 | AD68: =M68*S68 -> 0
A69: 62 | O69: =N69*S69 -> 0 | P69: =(O69/O112)*100 -> #DIV/0! | R69: =P69*Q69 -> #DIV/0! | U69: =D69*S69 -> 0 | V69: =E69*S69 -> 0 | W69: =F69*S69 -> 0 | X69: =G69*S69 -> 0 | Y69: =H69*S69 -> 0 | Z69: =I69*S69 -> 0 | AA69: =J69*S69 -> 0 | AB69: =K69*S69 -> 0 | AC69: =L69*S69 -> 0 | AD69: =M69*S69 -> 0
A70: 63 | C70: CFD 1 | N70: =SUM(D70:M70) -> 0 | O70: =N70*S70 -> 0 | P70: =(O70/O112)*100 -> #DIV/0! | R70: =P70*Q70 -> #DIV/0! | S70: 10800 | U70: =D70*S70 -> 0 | V70: =E70*S70 -> 0 | W70: =F70*S70 -> 0 | X70: =G70*S70 -> 0 | Y70: =H70*S70 -> 0 | Z70: =I70*S70 -> 0 | AA70: =J70*S70 -> 0 | AB70: =K70*S70 -> 0 | AC70: =L70*S70 -> 0 | AD70: =M70*S70 -> 0
A71: 64 | C71: CFD 2 | N71: =SUM(D71:M71) -> 0 | O71: =N71*S71 -> 0 | P71: =(O71/O112)*100 -> #DIV/0! | R71: =P71*Q71 -> #DIV/0! | S71: 16200 | U71: =D71*S71 -> 0 | V71: =E71*S71 -> 0 | W71: =F71*S71 -> 0 | X71: =G71*S71 -> 0 | Y71: =H71*S71 -> 0 | Z71: =I71*S71 -> 0 | AA71: =J71*S71 -> 0 | AB71: =K71*S71 -> 0 | AC71: =L71*S71 -> 0 | AD71: =M71*S71 -> 0
A72: 65 | C72: CFD 3 | N72: =SUM(D72:M72) -> 0 | O72: =N72*S72 -> 0 | P72: =(O72/O112)*100 -> #DIV/0! | R72: =P72*Q72 -> #DIV/0! | S72: 20250 | U72: =D72*S72 -> 0 | V72: =E72*S72 -> 0 | W72: =F72*S72 -> 0 | X72: =G72*S72 -> 0 | Y72: =H72*S72 -> 0 | Z72: =I72*S72 -> 0 | AA72: =J72*S72 -> 0 | AB72: =K72*S72 -> 0 | AC72: =L72*S72 -> 0 | AD72: =M72*S72 -> 0
A73: 66 | N73: =SUM(D73:M73) -> 0 | O73: =N73*S73 -> 0 | P73: =(O73/O112)*100 -> #DIV/0! | R73: =P73*Q73 -> #DIV/0! | U73: =D73*S73 -> 0 | V73: =E73*S73 -> 0 | W73: =F73*S73 -> 0 | X73: =G73*S73 -> 0 | Y73: =H73*S73 -> 0 | Z73: =I73*S73 -> 0 | AA73: =J73*S73 -> 0 | AB73: =K73*S73 -> 0 | AC73: =L73*S73 -> 0 | AD73: =M73*S73 -> 0
A74: 67 | C74: Telor Ceplok | N74: =SUM(D74:M74) -> 0 | O74: =N74*S74 -> 0 | P74: =(O74/O112)*100 -> #DIV/0! | R74: =P74*Q74 -> #DIV/0! | S74: 6750 | U74: =D74*S74 -> 0 | V74: =E74*S74 -> 0 | W74: =F74*S74 -> 0 | X74: =G74*S74 -> 0 | Y74: =H74*S74 -> 0 | Z74: =I74*S74 -> 0 | AA74: =J74*S74 -> 0 | AB74: =K74*S74 -> 0 | AC74: =L74*S74 -> 0 | AD74: =M74*S74 -> 0
A75: 68 | N75: =SUM(D75:M75) -> 0 | O75: =N75*S75 -> 0 | P75: =(O75/O112)*100 -> #DIV/0! | R75: =P75*Q75 -> #DIV/0! | U75: =D75*S75 -> 0 | V75: =E75*S75 -> 0 | W75: =F75*S75 -> 0 | X75: =G75*S75 -> 0 | Y75: =H75*S75 -> 0 | Z75: =I75*S75 -> 0 | AA75: =J75*S75 -> 0 | AB75: =K75*S75 -> 0 | AC75: =L75*S75 -> 0 | AD75: =M75*S75 -> 0
A76: 69 | N76: =SUM(D76:M76) -> 0 | O76: =N76*S76 -> 0 | P76: =(O76/O112)*100 -> #DIV/0! | R76: =P76*Q76 -> #DIV/0! | S76: 31050 | U76: =D76*S76 -> 0 | V76: =E76*S76 -> 0 | W76: =F76*S76 -> 0 | X76: =G76*S76 -> 0 | Y76: =H76*S76 -> 0 | Z76: =I76*S76 -> 0 | AA76: =J76*S76 -> 0 | AB76: =K76*S76 -> 0 | AC76: =L76*S76 -> 0 | AD76: =M76*S76 -> 0
A77: 70 | N77: =SUM(D77:M77) -> 0 | O77: =N77*S77 -> 0 | P77: =(O77/O112)*100 -> #DIV/0! | R77: =P77*Q77 -> #DIV/0! | S77: 28350 | U77: =D77*S77 -> 0 | V77: =E77*S77 -> 0 | W77: =F77*S77 -> 0 | X77: =G77*S77 -> 0 | Y77: =H77*S77 -> 0 | Z77: =I77*S77 -> 0 | AA77: =J77*S77 -> 0 | AB77: =K77*S77 -> 0 | AC77: =L77*S77 -> 0 | AD77: =M77*S77 -> 0
A78: 71 | N78: =SUM(D78:M78) -> 0 | O78: =N78*S78 -> 0 | P78: =(O78/O112)*100 -> #DIV/0! | R78: =P78*Q78 -> #DIV/0! | U78: =D78*S78 -> 0 | V78: =E78*S78 -> 0 | W78: =F78*S78 -> 0 | X78: =G78*S78 -> 0 | Y78: =H78*S78 -> 0 | Z78: =I78*S78 -> 0 | AA78: =J78*S78 -> 0 | AB78: =K78*S78 -> 0 | AC78: =L78*S78 -> 0 | AD78: =M78*S78 -> 0
A79: 72 | N79: =SUM(D79:M79) -> 0 | O79: =N79*S79 -> 0 | P79: =(O79/O112)*100 -> #DIV/0! | R79: =P79*Q79 -> #DIV/0! | S79: 16200 | U79: =D79*S79 -> 0 | V79: =E79*S79 -> 0 | W79: =F79*S79 -> 0 | X79: =G79*S79 -> 0 | Y79: =H79*S79 -> 0 | Z79: =I79*S79 -> 0 | AA79: =J79*S79 -> 0 | AB79: =K79*S79 -> 0 | AC79: =L79*S79 -> 0 | AD79: =M79*S79 -> 0
A80: 73 | N80: =SUM(D80:M80) -> 0 | O80: =N80*S80 -> 0 | P80: =(O80/O112)*100 -> #DIV/0! | R80: =P80*Q80 -> #DIV/0! | S80: 20250 | U80: =D80*S80 -> 0 | V80: =E80*S80 -> 0 | W80: =F80*S80 -> 0 | X80: =G80*S80 -> 0 | Y80: =H80*S80 -> 0 | Z80: =I80*S80 -> 0 | AA80: =J80*S80 -> 0 | AB80: =K80*S80 -> 0 | AC80: =L80*S80 -> 0 | AD80: =M80*S80 -> 0
A81: 74 | N81: =SUM(D81:M81) -> 0 | O81: =N81*S81 -> 0 | P81: =(O81/O112)*100 -> #DIV/0! | R81: =P81*Q81 -> #DIV/0! | U81: =D81*S81 -> 0 | V81: =E81*S81 -> 0 | W81: =F81*S81 -> 0 | X81: =G81*S81 -> 0 | Y81: =H81*S81 -> 0 | Z81: =I81*S81 -> 0 | AA81: =J81*S81 -> 0 | AB81: =K81*S81 -> 0 | AC81: =L81*S81 -> 0 | AD81: =M81*S81 -> 0
A82: 75 | N82: =SUM(D82:M82) -> 0 | O82: =N82*S82 -> 0 | P82: =(O82/O112)*100 -> #DIV/0! | R82: =P82*Q82 -> #DIV/0! | U82: =D82*S82 -> 0 | V82: =E82*S82 -> 0 | W82: =F82*S82 -> 0 | X82: =G82*S82 -> 0 | Y82: =H82*S82 -> 0 | Z82: =I82*S82 -> 0 | AA82: =J82*S82 -> 0 | AB82: =K82*S82 -> 0 | AC82: =L82*S82 -> 0 | AD82: =M82*S82 -> 0
B83: TOTAL FOOD | C83: =B83 -> TOTAL FOOD | D83: =U83 -> 0 | E83: =V83 -> 0 | F83: =W83 -> 0 | G83: =X83 -> 0 | H83: =Y83 -> 0 | I83: =Z83 -> 0 | J83: =AA83 -> 0 | K83: =AB83 -> 0 | ... M83: =AD83 -> 0 | O83: =SUM(D83:M83) -> 0 | P83: =SUM(P8:P82)/100 -> #DIV/0! | R83: =SUM(R8:R82)/100 -> #DIV/0! | U83: =SUM(U8:U82) -> 0 | V83: =SUM(V8:V82) -> 0 | W83: =SUM(W8:W82) -> 0 | X83: =SUM(X8:X82) -> 0 | Y83: =SUM(Y8:Y82) -> 0 | Z83: =SUM(Z8:Z82) -> 0 | AA83: =SUM(AA8:AA82) -> 0 | AB83: =SUM(AB8:AB82) -> 0 | ... AD83: =SUM(AD8:AD82) -> 0
A85: NO | B85: BEVERAGES | C85: =B85 -> BEVERAGES
A86: 1 | B86: Air Mineral Botol | C86: =B86 -> Air Mineral Botol | N86: =SUM(D86:M86) -> 0 | O86: =N86*S86 -> 0 | P86: =(O86/O112)*100 -> #DIV/0! | R86: =P86*Q86 -> #DIV/0! | S86: 5400 | U86: =D86*S86 -> 0 | V86: =E86*S86 -> 0 | W86: =F86*S86 -> 0 | X86: =G86*S86 -> 0 | Y86: =H86*S86 -> 0 | Z86: =I86*S86 -> 0 | AA86: =J86*S86 -> 0 | AB86: =K86*S86 -> 0 | AC86: =L86*S86 -> 0 | AD86: =M86*S86 -> 0
A87: 2 | B87: Air Mineral Cup | C87: =B87 -> Air Mineral Cup | N87: =SUM(D87:M87) -> 0 | O87: =N87*S87 -> 0 | P87: =(O87/O112)*100 -> #DIV/0! | R87: =P87*Q87 -> #DIV/0! | S87: 2700 | U87: =D87*S87 -> 0 | V87: =E87*S87 -> 0 | W87: =F87*S87 -> 0 | X87: =G87*S87 -> 0 | Y87: =H87*S87 -> 0 | Z87: =I87*S87 -> 0 | AA87: =J87*S87 -> 0 | AB87: =K87*S87 -> 0 | AC87: =L87*S87 -> 0 | AD87: =M87*S87 -> 0
A88: 3 | B88: Teh Botol | C88: =B88 -> Teh Botol | N88: =SUM(D88:M88) -> 0 | O88: =N88*S88 -> 0 | P88: =(O88/O112)*100 -> #DIV/0! | R88: =P88*Q88 -> #DIV/0! | S88: 8100 | U88: =D88*S88 -> 0 | V88: =E88*S88 -> 0 | W88: =F88*S88 -> 0 | X88: =G88*S88 -> 0 | Y88: =H88*S88 -> 0 | Z88: =I88*S88 -> 0 | AA88: =J88*S88 -> 0 | AB88: =K88*S88 -> 0 | AC88: =L88*S88 -> 0 | AD88: =M88*S88 -> 0
A89: 4 | B89: Teh Sosro Genggam | C89: =B89 -> Teh Sosro Genggam | N89: =SUM(D89:M89) -> 0 | O89: =N89*S89 -> 0 | P89: =(O89/O112)*100 -> #DIV/0! | R89: =P89*Q89 -> #DIV/0! | S89: 8100 | U89: =D89*S89 -> 0 | V89: =E89*S89 -> 0 | W89: =F89*S89 -> 0 | X89: =G89*S89 -> 0 | Y89: =H89*S89 -> 0 | Z89: =I89*S89 -> 0 | AA89: =J89*S89 -> 0 | AB89: =K89*S89 -> 0 | AC89: =L89*S89 -> 0 | AD89: =M89*S89 -> 0
A90: 5 | B90: Fruit Tea Botol | N90: =SUM(D90:M90) -> 0 | O90: =N90*S90 -> 0 | P90: =(O90/O112)*100 -> #DIV/0! | R90: =P90*Q90 -> #DIV/0! | U90: =D90*S90 -> 0 | V90: =E90*S90 -> 0 | W90: =F90*S90 -> 0 | X90: =G90*S90 -> 0 | Y90: =H90*S90 -> 0 | Z90: =I90*S90 -> 0 | AA90: =J90*S90 -> 0 | AB90: =K90*S90 -> 0 | AC90: =L90*S90 -> 0 | AD90: =M90*S90 -> 0
A91: 6 | B91: Fuit Tea Genggam | C91: S-tee | N91: =SUM(D91:M91) -> 0 | O91: =N91*S91 -> 0 | P91: =(O91/O112)*100 -> #DIV/0! | R91: =P91*Q91 -> #DIV/0! | S91: 4050 | U91: =D91*S91 -> 0 | V91: =E91*S91 -> 0 | W91: =F91*S91 -> 0 | X91: =G91*S91 -> 0 | Y91: =H91*S91 -> 0 | Z91: =I91*S91 -> 0 | AA91: =J91*S91 -> 0 | AB91: =K91*S91 -> 0 | AC91: =L91*S91 -> 0 | AD91: =M91*S91 -> 0
B92: Tebs | O92: =N92*S92 -> 0 | P92: =(O92/O112)*100 -> #DIV/0! | R92: =P92*Q92 -> #DIV/0! | U92: =D92*S92 -> 0 | V92: =E92*S92 -> 0 | W92: =F92*S92 -> 0 | X92: =G92*S92 -> 0 | Y92: =H92*S92 -> 0 | Z92: =I92*S92 -> 0 | AA92: =J92*S92 -> 0 | AB92: =K92*S92 -> 0 | AC92: =L92*S92 -> 0 | AD92: =M92*S92 -> 0
A93: 7 | B93: STEE | C93: Millo | N93: =SUM(D93:M93) -> 0 | O93: =N93*S93 -> 0 | P93: =(O93/O112)*100 -> #DIV/0! | R93: =P93*Q93 -> #DIV/0! | S93: 12150 | U93: =D93*S93 -> 0 | V93: =E93*S93 -> 0 | W93: =F93*S93 -> 0 | X93: =G93*S93 -> 0 | Y93: =H93*S93 -> 0 | Z93: =I93*S93 -> 0 | AA93: =J93*S93 -> 0 | AB93: =K93*S93 -> 0 | AC93: =L93*S93 -> 0 | AD93: =M93*S93 -> 0
A94: 8 | C94: Nestea | N94: =SUM(D94:M94) -> 0 | O94: =N94*S94 -> 0 | P94: =(O94/O112)*100 -> #DIV/0! | R94: =P94*Q94 -> #DIV/0! | S94: 10800 | U94: =D94*S94 -> 0 | V94: =E94*S94 -> 0 | W94: =F94*S94 -> 0 | X94: =G94*S94 -> 0 | Y94: =H94*S94 -> 0 | Z94: =I94*S94 -> 0 | AA94: =J94*S94 -> 0 | AB94: =K94*S94 -> 0 | AC94: =L94*S94 -> 0 | AD94: =M94*S94 -> 0
A95: 9 | B95: Juice Durian Float | C95: Orange Juice | N95: =SUM(D95:M95) -> 0 | O95: =N95*S95 -> 0 | P95: =(O95/O112)*100 -> #DIV/0! | R95: =P95*Q95 -> #DIV/0! | S95: 9450 | U95: =D95*S95 -> 0 | V95: =E95*S95 -> 0 | W95: =F95*S95 -> 0 | X95: =G95*S95 -> 0 | Y95: =H95*S95 -> 0 | Z95: =I95*S95 -> 0 | AA95: =J95*S95 -> 0 | AB95: =K95*S95 -> 0 | AC95: =L95*S95 -> 0 | AD95: =M95*S95 -> 0
A96: 10 | B96: Juice Durian | C96: Orange Float | N96: =SUM(D96:M96) -> 0 | O96: =N96*S96 -> 0 | P96: =(O96/O112)*100 -> #DIV/0! | R96: =P96*Q96 -> #DIV/0! | S96: 12150 | U96: =D96*S96 -> 0 | V96: =E96*S96 -> 0 | W96: =F96*S96 -> 0 | X96: =G96*S96 -> 0 | Y96: =H96*S96 -> 0 | Z96: =I96*S96 -> 0 | AA96: =J96*S96 -> 0 | AB96: =K96*S96 -> 0 | AC96: =L96*S96 -> 0 | AD96: =M96*S96 -> 0
A97: 11 | B97: Juice Melon Float | C97: Avocado Float | N97: =SUM(D97:M97) -> 0 | O97: =N97*S97 -> 0 | P97: =(O97/O112)*100 -> #DIV/0! | R97: =P97*Q97 -> #DIV/0! | S97: 20250 | U97: =D97*S97 -> 0 | V97: =E97*S97 -> 0 | W97: =F97*S97 -> 0 | X97: =G97*S97 -> 0 | Y97: =H97*S97 -> 0 | Z97: =I97*S97 -> 0 | AA97: =J97*S97 -> 0 | AB97: =K97*S97 -> 0 | AC97: =L97*S97 -> 0 | AD97: =M97*S97 -> 0
A98: 12 | B98: Juice Melon | N98: =SUM(D98:M98) -> 0 | O98: =N98*S98 -> 0 | P98: =(O98/O112)*100 -> #DIV/0! | R98: =P98*Q98 -> #DIV/0! | U98: =D98*S98 -> 0 | V98: =E98*S98 -> 0 | W98: =F98*S98 -> 0 | X98: =G98*S98 -> 0 | Y98: =H98*S98 -> 0 | Z98: =I98*S98 -> 0 | AA98: =J98*S98 -> 0 | AB98: =K98*S98 -> 0 | AC98: =L98*S98 -> 0 | AD98: =M98*S98 -> 0
A99: 13 | B99: Juice Strawberry Float | C99: Es Teh | N99: =SUM(D99:M99) -> 0 | O99: =N99*S99 -> 0 | P99: =(O99/O112)*100 -> #DIV/0! | R99: =P99*Q99 -> #DIV/0! | S99: 6740 | U99: =D99*S99 -> 0 | V99: =E99*S99 -> 0 | W99: =F99*S99 -> 0 | X99: =G99*S99 -> 0 | Y99: =H99*S99 -> 0 | Z99: =I99*S99 -> 0 | AA99: =J99*S99 -> 0 | AB99: =K99*S99 -> 0 | AC99: =L99*S99 -> 0 | AD99: =M99*S99 -> 0
A100: 14 | B100: Juice Stawbery | N100: =SUM(D100:M100) -> 0 | O100: =N100*S100 -> 0 | P100: =(O100/O112)*100 -> #DIV/0! | R100: =P100*Q100 -> #DIV/0! | U100: =D100*S100 -> 0 | V100: =E100*S100 -> 0 | W100: =F100*S100 -> 0 | X100: =G100*S100 -> 0 | Y100: =H100*S100 -> 0 | Z100: =I100*S100 -> 0 | AA100: =J100*S100 -> 0 | AB100: =K100*S100 -> 0 | AC100: =L100*S100 -> 0 | AD100: =M100*S100 -> 0
A101: 15 | B101: Juice Mangga Float | N101: =SUM(D101:M101) -> 0 | O101: =N101*S101 -> 0 | P101: =(O101/O112)*100 -> #DIV/0! | R101: =P101*Q101 -> #DIV/0! | U101: =D101*S101 -> 0 | V101: =E101*S101 -> 0 | W101: =F101*S101 -> 0 | X101: =G101*S101 -> 0 | Y101: =H101*S101 -> 0 | Z101: =I101*S101 -> 0 | AA101: =J101*S101 -> 0 | AB101: =K101*S101 -> 0 | AC101: =L101*S101 -> 0 | AD101: =M101*S101 -> 0
A102: 16 | B102: Juice Mangga | N102: =SUM(D102:M102) -> 0 | O102: =N102*S102 -> 0 | P102: =(O102/O112)*100 -> #DIV/0! | R102: =P102*Q102 -> #DIV/0! | U102: =D102*S102 -> 0 | V102: =E102*S102 -> 0 | W102: =F102*S102 -> 0 | X102: =G102*S102 -> 0 | Y102: =H102*S102 -> 0 | Z102: =I102*S102 -> 0 | AA102: =J102*S102 -> 0 | AB102: =K102*S102 -> 0 | AC102: =L102*S102 -> 0 | AD102: =M102*S102 -> 0
B103: Juice Jambu Float | N103: =SUM(D103:M103) -> 0 | O103: =N103*S103 -> 0 | P103: =(O103/O112)*100 -> #DIV/0! | R103: =P103*Q103 -> #DIV/0! | U103: =D103*S103 -> 0 | V103: =E103*S103 -> 0 | W103: =F103*S103 -> 0 | X103: =G103*S103 -> 0 | Y103: =H103*S103 -> 0 | Z103: =I103*S103 -> 0 | AA103: =J103*S103 -> 0 | AB103: =K103*S103 -> 0 | AC103: =L103*S103 -> 0 | AD103: =M103*S103 -> 0
...

Sheet LAP. PENJUALAN SHOPEFOOD
A2: LAPORAN PENJUALAN SHOPEEFOOD
M3: Cabang : | O3: =LPKK!Q4 -> SC MARABAHAN
M4: Periode : | O4: =LPKK!Q5 -> 1-7 JULI 2026
A6: NO | B6: PRODUCT | C6: =B6 -> PRODUCT | D6: ='LAP. PENJUALAN REGULER'!D6 -> 1 | E6: ='LAP. PENJUALAN REGULER'!E6 -> 2 | F6: ='LAP. PENJUALAN REGULER'!F6 -> 3 | G6: ='LAP. PENJUALAN REGULER'!G6 -> 4 | H6: ='LAP. PENJUALAN REGULER'!H6 -> 5 | I6: ='LAP. PENJUALAN REGULER'!I6 -> 6 | J6: ='LAP. PENJUALAN REGULER'!J6 -> 7 | K6: ='LAP. PENJUALAN REGULER'!K6 -> 0 | ... M6: ='LAP. PENJUALAN REGULER'!M6 -> 0 | N6: TOTAL | P6: % | Q6: FC ITEM | R6: CON FC | S6: Harga
D7: ='LAP. PENJUALAN REGULER'!D7 -> Rabu | E7: ='LAP. PENJUALAN REGULER'!E7 -> Kamis | F7: ='LAP. PENJUALAN REGULER'!F7 -> Jum`at | G7: ='LAP. PENJUALAN REGULER'!G7 -> Sabtu | H7: ='LAP. PENJUALAN REGULER'!H7 -> Minggu | I7: ='LAP. PENJUALAN REGULER'!I7 -> Senin | J7: ='LAP. PENJUALAN REGULER'!J7 -> Sabtu | K7: ='LAP. PENJUALAN REGULER'!K7 -> 0 | ... M7: ='LAP. PENJUALAN REGULER'!M7 -> 0 | N7: UNIT | O7: ( Rp ) | S7: ( Unit )
A8: 1 | B8: Dada | C8: =B8 -> Dada | N8: =SUM(D8:M8) -> 0 | O8: =N8*S8 -> 0 | P8: =(O8/O112)*100 -> #DIV/0! | R8: =P8*Q8 -> #DIV/0! | S8: 19575 | U8: =D8*S8 -> 0 | V8: =E8*S8 -> 0 | W8: =F8*S8 -> 0 | X8: =G8*S8 -> 0 | Y8: =H8*S8 -> 0 | Z8: =I8*S8 -> 0 | AA8: =J8*S8 -> 0 | AB8: =K8*S8 -> 0 | AC8: =L8*S8 -> 0 | AD8: =M8*S8 -> 0
A9: 2 | B9: Paha Atas | C9: =B9 -> Paha Atas | N9: =SUM(D9:M9) -> 0 | O9: =N9*S9 -> 0 | P9: =(O9/O112)*100 -> #DIV/0! | R9: =P9*Q9 -> #DIV/0! | S9: 19575 | U9: =D9*S9 -> 0 | V9: =E9*S9 -> 0 | W9: =F9*S9 -> 0 | X9: =G9*S9 -> 0 | Y9: =H9*S9 -> 0 | Z9: =I9*S9 -> 0 | AA9: =J9*S9 -> 0 | AB9: =K9*S9 -> 0 | AC9: =L9*S9 -> 0 | AD9: =M9*S9 -> 0
A10: 3 | B10: Paha Bawah | C10: =B10 -> Paha Bawah | N10: =SUM(D10:M10) -> 0 | O10: =N10*S10 -> 0 | P10: =(O10/O112)*100 -> #DIV/0! | R10: =P10*Q10 -> #DIV/0! | S10: 17550 | U10: =D10*S10 -> 0 | V10: =E10*S10 -> 0 | W10: =F10*S10 -> 0 | X10: =G10*S10 -> 0 | Y10: =H10*S10 -> 0 | Z10: =I10*S10 -> 0 | AA10: =J10*S10 -> 0 | AB10: =K10*S10 -> 0 | AC10: =L10*S10 -> 0 | AD10: =M10*S10 -> 0
A11: 4 | B11: Sayap | C11: =B11 -> Sayap | N11: =SUM(D11:M11) -> 0 | O11: =N11*S11 -> 0 | P11: =(O11/O112)*100 -> #DIV/0! | R11: =P11*Q11 -> #DIV/0! | S11: 16200 | U11: =D11*S11 -> 0 | V11: =E11*S11 -> 0 | W11: =F11*S11 -> 0 | X11: =G11*S11 -> 0 | Y11: =H11*S11 -> 0 | Z11: =I11*S11 -> 0 | AA11: =J11*S11 -> 0 | AB11: =K11*S11 -> 0 | AC11: =L11*S11 -> 0 | AD11: =M11*S11 -> 0
A12: 5 | B12: Chicken Strips | C12: =B12 -> Chicken Strips | N12: =SUM(D12:M12) -> 0 | O12: =N12*S12 -> 0 | P12: =(O12/O112)*100 -> #DIV/0! | R12: =P12*Q12 -> #DIV/0! | S12: 16200 | U12: =D12*S12 -> 0 | V12: =E12*S12 -> 0 | W12: =F12*S12 -> 0 | X12: =G12*S12 -> 0 | Y12: =H12*S12 -> 0 | Z12: =I12*S12 -> 0 | AA12: =J12*S12 -> 0 | AB12: =K12*S12 -> 0 | AC12: =L12*S12 -> 0 | AD12: =M12*S12 -> 0
A13: 6 | B13: Chicken Steak | C13: =B13 -> Chicken Steak | N13: =SUM(D13:M13) -> 0 | O13: =N13*S13 -> 0 | P13: =(O13/O112)*100 -> #DIV/0! | R13: =P13*Q13 -> #DIV/0! | S13: 17550 | U13: =D13*S13 -> 0 | V13: =E13*S13 -> 0 | W13: =F13*S13 -> 0 | X13: =G13*S13 -> 0 | Y13: =H13*S13 -> 0 | Z13: =I13*S13 -> 0 | AA13: =J13*S13 -> 0 | AB13: =K13*S13 -> 0 | AC13: =L13*S13 -> 0 | AD13: =M13*S13 -> 0
A14: 7 | C14: Dada Lembut | N14: =SUM(D14:M14) -> 0 | O14: =N14*S14 -> 0 | P14: =(O14/O112)*100 -> #DIV/0! | R14: =P14*Q14 -> #DIV/0! | S14: 19575 | U14: =D14*S14 -> 0 | V14: =E14*S14 -> 0 | W14: =F14*S14 -> 0 | X14: =G14*S14 -> 0 | Y14: =H14*S14 -> 0 | Z14: =I14*S14 -> 0 | AA14: =J14*S14 -> 0 | AB14: =K14*S14 -> 0 | AC14: =L14*S14 -> 0 | AD14: =M14*S14 -> 0
A15: 8 | B15: French Fries | C15: =B15 -> French Fries | N15: =SUM(D15:M15) -> 0 | O15: =N15*S15 -> 0 | P15: =(O15/O112)*100 -> #DIV/0! | R15: =P15*Q15 -> #DIV/0! | S15: 14850 | U15: =D15*S15 -> 0 | V15: =E15*S15 -> 0 | W15: =F15*S15 -> 0 | X15: =G15*S15 -> 0 | Y15: =H15*S15 -> 0 | Z15: =I15*S15 -> 0 | AA15: =J15*S15 -> 0 | AB15: =K15*S15 -> 0 | AC15: =L15*S15 -> 0 | AD15: =M15*S15 -> 0
A16: 9 | B16: Nasi | C16: =B16 -> Nasi | N16: =SUM(D16:M16) -> 0 | O16: =N16*S16 -> 0 | P16: =(O16/O112)*100 -> #DIV/0! | R16: =P16*Q16 -> #DIV/0! | S16: 6750 | U16: =D16*S16 -> 0 | V16: =E16*S16 -> 0 | W16: =F16*S16 -> 0 | X16: =G16*S16 -> 0 | Y16: =H16*S16 -> 0 | Z16: =I16*S16 -> 0 | AA16: =J16*S16 -> 0 | AB16: =K16*S16 -> 0 | AC16: =L16*S16 -> 0 | AD16: =M16*S16 -> 0
A17: 10 | B17: Perkedel | C17: =B17 -> Perkedel | N17: =SUM(D17:M17) -> 0 | O17: =N17*S17 -> 0 | P17: =(O17/O112)*100 -> #DIV/0! | R17: =P17*Q17 -> #DIV/0! | S17: 6750 | U17: =D17*S17 -> 0 | V17: =E17*S17 -> 0 | W17: =F17*S17 -> 0 | X17: =G17*S17 -> 0 | Y17: =H17*S17 -> 0 | Z17: =I17*S17 -> 0 | AA17: =J17*S17 -> 0 | AB17: =K17*S17 -> 0 | AC17: =L17*S17 -> 0 | AD17: =M17*S17 -> 0
A18: 11 | B18: Chicken Burger | C18: =B18 -> Chicken Burger | N18: =SUM(D18:M18) -> 0 | O18: =N18*S18 -> 0 | P18: =(O18/O112)*100 -> #DIV/0! | R18: =P18*Q18 -> #DIV/0! | S18: 20250 | U18: =D18*S18 -> 0 | V18: =E18*S18 -> 0 | W18: =F18*S18 -> 0 | X18: =G18*S18 -> 0 | Y18: =H18*S18 -> 0 | Z18: =I18*S18 -> 0 | AA18: =J18*S18 -> 0 | AB18: =K18*S18 -> 0 | AC18: =L18*S18 -> 0 | AD18: =M18*S18 -> 0
A19: 12 | B19: Cheese Burger | C19: =B19 -> Cheese Burger | N19: =SUM(D19:M19) -> 0 | O19: =N19*S19 -> 0 | P19: =(O19/O112)*100 -> #DIV/0! | R19: =P19*Q19 -> #DIV/0! | S19: 22950 | U19: =D19*S19 -> 0 | V19: =E19*S19 -> 0 | W19: =F19*S19 -> 0 | X19: =G19*S19 -> 0 | Y19: =H19*S19 -> 0 | Z19: =I19*S19 -> 0 | AA19: =J19*S19 -> 0 | AB19: =K19*S19 -> 0 | AC19: =L19*S19 -> 0 | AD19: =M19*S19 -> 0
A20: 13 | B20: Nasi Goreng | C20: =B20 -> Nasi Goreng | N20: =SUM(D20:M20) -> 0 | O20: =N20*S20 -> 0 | P20: =(O20/O112)*100 -> #DIV/0! | R20: =P20*Q20 -> #DIV/0! | S20: 21600 | U20: =D20*S20 -> 0 | V20: =E20*S20 -> 0 | W20: =F20*S20 -> 0 | X20: =G20*S20 -> 0 | Y20: =H20*S20 -> 0 | Z20: =I20*S20 -> 0 | AA20: =J20*S20 -> 0 | AB20: =K20*S20 -> 0 | AC20: =L20*S20 -> 0 | AD20: =M20*S20 -> 0
A21: 14 | B21: Telor Ceplok | C21: Nasi Goreng Spesial | N21: =SUM(D21:M21) -> 0 | O21: =N21*S21 -> 0 | P21: =(O21/O112)*100 -> #DIV/0! | R21: =P21*Q21 -> #DIV/0! | S21: 25650 | U21: =D21*S21 -> 0 | V21: =E21*S21 -> 0 | W21: =F21*S21 -> 0 | X21: =G21*S21 -> 0 | Y21: =H21*S21 -> 0 | Z21: =I21*S21 -> 0 | AA21: =J21*S21 -> 0 | AB21: =K21*S21 -> 0 | AC21: =L21*S21 -> 0 | AD21: =M21*S21 -> 0
A22: 15 | B22: Nasi Goreng Telor Ceplok | C22: Mie Goreng | N22: =SUM(D22:M22) -> 0 | O22: =N22*S22 -> 0 | P22: =(O22/O112)*100 -> #DIV/0! | R22: =P22*Q22 -> #DIV/0! | S22: 21600 | U22: =D22*S22 -> 0 | V22: =E22*S22 -> 0 | W22: =F22*S22 -> 0 | X22: =G22*S22 -> 0 | Y22: =H22*S22 -> 0 | Z22: =I22*S22 -> 0 | AA22: =J22*S22 -> 0 | AB22: =K22*S22 -> 0 | AC22: =L22*S22 -> 0 | AD22: =M22*S22 -> 0
A23: 16 | C23: Chicken 2 Pcs | N23: =SUM(D23:M23) -> 0 | O23: =N23*S23 -> 0 | P23: =(O23/O112)*100 -> #DIV/0! | R23: =P23*Q23 -> #DIV/0! | S23: 33750 | U23: =D23*S23 -> 0 | V23: =E23*S23 -> 0 | W23: =F23*S23 -> 0 | X23: =G23*S23 -> 0 | Y23: =H23*S23 -> 0 | Z23: =I23*S23 -> 0 | AA23: =J23*S23 -> 0 | AB23: =K23*S23 -> 0 | AC23: =L23*S23 -> 0 | AD23: =M23*S23 -> 0
A24: 17 | N24: =SUM(D24:M24) -> 0 | O24: =N24*S24 -> 0 | P24: =(O24/O112)*100 -> #DIV/0! | R24: =P24*Q24 -> #DIV/0! | S24: 20250 | U24: =D24*S24 -> 0 | V24: =E24*S24 -> 0 | W24: =F24*S24 -> 0 | X24: =G24*S24 -> 0 | Y24: =H24*S24 -> 0 | Z24: =I24*S24 -> 0 | AA24: =J24*S24 -> 0 | AB24: =K24*S24 -> 0 | AC24: =L24*S24 -> 0 | AD24: =M24*S24 -> 0
A25: 18 | N25: =SUM(D25:M25) -> 0 | O25: =N25*S25 -> 0 | P25: =(O25/O112)*100 -> #DIV/0! | R25: =P25*Q25 -> #DIV/0! | U25: =D25*S25 -> 0 | V25: =E25*S25 -> 0 | W25: =F25*S25 -> 0 | X25: =G25*S25 -> 0 | Y25: =H25*S25 -> 0 | Z25: =I25*S25 -> 0 | AA25: =J25*S25 -> 0 | AB25: =K25*S25 -> 0 | AC25: =L25*S25 -> 0 | AD25: =M25*S25 -> 0
A26: 19 | B26: Paket Rocket 1 | C26: Paket Sonic 1 | N26: =SUM(D26:M26) -> 0 | O26: =N26*S26 -> 0 | P26: =(O26/O112)*100 -> #DIV/0! | R26: =P26*Q26 -> #DIV/0! | S26: 17550 | U26: =D26*S26 -> 0 | V26: =E26*S26 -> 0 | W26: =F26*S26 -> 0 | X26: =G26*S26 -> 0 | Y26: =H26*S26 -> 0 | Z26: =I26*S26 -> 0 | AA26: =J26*S26 -> 0 | AB26: =K26*S26 -> 0 | AC26: =L26*S26 -> 0 | AD26: =M26*S26 -> 0
A27: 20 | B27: Paket Rocket 2 | C27: Paket Sonic 2 | N27: =SUM(D27:M27) -> 0 | O27: =N27*S27 -> 0 | P27: =(O27/O112)*100 -> #DIV/0! | R27: =P27*Q27 -> #DIV/0! | S27: 20250 | U27: =D27*S27 -> 0 | V27: =E27*S27 -> 0 | W27: =F27*S27 -> 0 | X27: =G27*S27 -> 0 | Y27: =H27*S27 -> 0 | Z27: =I27*S27 -> 0 | AA27: =J27*S27 -> 0 | AB27: =K27*S27 -> 0 | AC27: =L27*S27 -> 0 | AD27: =M27*S27 -> 0
A28: 21 | B28: Paket Rocket 3 | C28: Paket Sonic 3 | N28: =SUM(D28:M28) -> 0 | O28: =N28*S28 -> 0 | P28: =(O28/O112)*100 -> #DIV/0! | R28: =P28*Q28 -> #DIV/0! | S28: 32400 | U28: =D28*S28 -> 0 | V28: =E28*S28 -> 0 | W28: =F28*S28 -> 0 | X28: =G28*S28 -> 0 | Y28: =H28*S28 -> 0 | Z28: =I28*S28 -> 0 | AA28: =J28*S28 -> 0 | AB28: =K28*S28 -> 0 | AC28: =L28*S28 -> 0 | AD28: =M28*S28 -> 0
A29: 22 | B29: Paket Rocket 4 | C29: Paket Sonic 4 | N29: =SUM(D29:M29) -> 0 | O29: =N29*S29 -> 0 | P29: =(O29/O112)*100 -> #DIV/0! | R29: =P29*Q29 -> #DIV/0! | S29: 32400 | U29: =D29*S29 -> 0 | V29: =E29*S29 -> 0 | W29: =F29*S29 -> 0 | X29: =G29*S29 -> 0 | Y29: =H29*S29 -> 0 | Z29: =I29*S29 -> 0 | AA29: =J29*S29 -> 0 | AB29: =K29*S29 -> 0 | AC29: =L29*S29 -> 0 | AD29: =M29*S29 -> 0
A30: 23 | B30: Paket Rocket 5 | C30: Paket Sonic 5 | N30: =SUM(D30:M30) -> 0 | O30: =N30*S30 -> 0 | P30: =(O30/O112)*100 -> #DIV/0! | R30: =P30*Q30 -> #DIV/0! | S30: 32400 | U30: =D30*S30 -> 0 | V30: =E30*S30 -> 0 | W30: =F30*S30 -> 0 | X30: =G30*S30 -> 0 | Y30: =H30*S30 -> 0 | Z30: =I30*S30 -> 0 | AA30: =J30*S30 -> 0 | AB30: =K30*S30 -> 0 | AC30: =L30*S30 -> 0 | AD30: =M30*S30 -> 0
A31: 24 | B31: Paket Rocket 6 | C31: Paket Sonic 6 | N31: =SUM(D31:M31) -> 0 | O31: =N31*S31 -> 0 | P31: =(O31/O112)*100 -> #DIV/0! | R31: =P31*Q31 -> #DIV/0! | S31: 37800 | U31: =D31*S31 -> 0 | V31: =E31*S31 -> 0 | W31: =F31*S31 -> 0 | X31: =G31*S31 -> 0 | Y31: =H31*S31 -> 0 | Z31: =I31*S31 -> 0 | AA31: =J31*S31 -> 0 | AB31: =K31*S31 -> 0 | AC31: =L31*S31 -> 0 | AD31: =M31*S31 -> 0
A32: 25 | B32: Paket Rocket 7 | C32: Paket Sonic 7 | N32: =SUM(D32:M32) -> 0 | O32: =N32*S32 -> 0 | P32: =(O32/O112)*100 -> #DIV/0! | R32: =P32*Q32 -> #DIV/0! | S32: 27000 | U32: =D32*S32 -> 0 | V32: =E32*S32 -> 0 | W32: =F32*S32 -> 0 | X32: =G32*S32 -> 0 | Y32: =H32*S32 -> 0 | Z32: =I32*S32 -> 0 | AA32: =J32*S32 -> 0 | AB32: =K32*S32 -> 0 | AC32: =L32*S32 -> 0 | AD32: =M32*S32 -> 0
A33: 26 | C33: Paket Sonic 8 | N33: =SUM(D33:M33) -> 0 | O33: =N33*S33 -> 0 | P33: =(O33/O112)*100 -> #DIV/0! | R33: =P33*Q33 -> #DIV/0! | S33: 32400 | U33: =D33*S33 -> 0 | V33: =E33*S33 -> 0 | W33: =F33*S33 -> 0 | X33: =G33*S33 -> 0 | Y33: =H33*S33 -> 0 | Z33: =I33*S33 -> 0 | AA33: =J33*S33 -> 0 | AB33: =K33*S33 -> 0 | AC33: =L33*S33 -> 0 | AD33: =M33*S33 -> 0
A34: 27 | B34: Paket Rocket 8 | C34: Paket Sonic 9 | N34: =SUM(D34:M34) -> 0 | O34: =N34*S34 -> 0 | P34: =(O34/O112)*100 -> #DIV/0! | R34: =P34*Q34 -> #DIV/0! | U34: =D34*S34 -> 0 | V34: =E34*S34 -> 0 | W34: =F34*S34 -> 0 | X34: =G34*S34 -> 0 | Y34: =H34*S34 -> 0 | Z34: =I34*S34 -> 0 | AA34: =J34*S34 -> 0 | AB34: =K34*S34 -> 0 | AC34: =L34*S34 -> 0 | AD34: =M34*S34 -> 0
A35: 28 | O35: =N35*S35 -> 0 | P35: =(O35/O112)*100 -> #DIV/0! | R35: =P35*Q35 -> #DIV/0! | U35: =D35*S35 -> 0 | V35: =E35*S35 -> 0 | W35: =F35*S35 -> 0 | X35: =G35*S35 -> 0 | Y35: =H35*S35 -> 0 | Z35: =I35*S35 -> 0 | AA35: =J35*S35 -> 0 | AB35: =K35*S35 -> 0 | AC35: =L35*S35 -> 0 | AD35: =M35*S35 -> 0
A36: 29 | B36: Paket Rocket 9 | C36: Paket Gepso 1 | N36: =SUM(D36:M36) -> 0 | O36: =N36*S36 -> 0 | P36: =(O36/O112)*100 -> #DIV/0! | R36: =P36*Q36 -> #DIV/0! | S36: 28350 | U36: =D36*S36 -> 0 | V36: =E36*S36 -> 0 | W36: =F36*S36 -> 0 | X36: =G36*S36 -> 0 | Y36: =H36*S36 -> 0 | Z36: =I36*S36 -> 0 | AA36: =J36*S36 -> 0 | AB36: =K36*S36 -> 0 | AC36: =L36*S36 -> 0 | AD36: =M36*S36 -> 0
A37: 30 | B37: Paket Rocket 10 | C37: Paket Gepso 2 | N37: =SUM(D37:M37) -> 0 | O37: =N37*S37 -> 0 | P37: =(O37/O112)*100 -> #DIV/0! | R37: =P37*Q37 -> #DIV/0! | S37: 31050 | U37: =D37*S37 -> 0 | V37: =E37*S37 -> 0 | W37: =F37*S37 -> 0 | X37: =G37*S37 -> 0 | Y37: =H37*S37 -> 0 | Z37: =I37*S37 -> 0 | AA37: =J37*S37 -> 0 | AB37: =K37*S37 -> 0 | AC37: =L37*S37 -> 0 | AD37: =M37*S37 -> 0
A38: 31 | C38: Paket Gepso 3 | N38: =SUM(D38:M38) -> 0 | O38: =N38*S38 -> 0 | P38: =(O38/O112)*100 -> #DIV/0! | R38: =P38*Q38 -> #DIV/0! | S38: 33750 | U38: =D38*S38 -> 0 | V38: =E38*S38 -> 0 | W38: =F38*S38 -> 0 | X38: =G38*S38 -> 0 | Y38: =H38*S38 -> 0 | Z38: =I38*S38 -> 0 | AA38: =J38*S38 -> 0 | AB38: =K38*S38 -> 0 | AC38: =L38*S38 -> 0 | AD38: =M38*S38 -> 0
A39: 32 | C39: Paket Gepso 4 | N39: =SUM(D39:M39) -> 0 | O39: =N39*S39 -> 0 | P39: =(O39/O112)*100 -> #DIV/0! | R39: =P39*Q39 -> #DIV/0! | S39: 33750 | U39: =D39*S39 -> 0 | V39: =E39*S39 -> 0 | W39: =F39*S39 -> 0 | X39: =G39*S39 -> 0 | Y39: =H39*S39 -> 0 | Z39: =I39*S39 -> 0 | AA39: =J39*S39 -> 0 | AB39: =K39*S39 -> 0 | AC39: =L39*S39 -> 0 | AD39: =M39*S39 -> 0
A40: 33 | B40: Paket Roma 1 | O40: =N40*S40 -> 0 | P40: =(O40/O112)*100 -> #DIV/0! | R40: =P40*Q40 -> #DIV/0! | U40: =D40*S40 -> 0 | V40: =E40*S40 -> 0 | W40: =F40*S40 -> 0 | X40: =G40*S40 -> 0 | Y40: =H40*S40 -> 0 | Z40: =I40*S40 -> 0 | AA40: =J40*S40 -> 0 | AB40: =K40*S40 -> 0 | AC40: =L40*S40 -> 0 | AD40: =M40*S40 -> 0
A41: 34 | B41: Paket Roma 2 | C41: Paket Prenic 1 | N41: =SUM(D41:M41) -> 0 | O41: =N41*S41 -> 0 | P41: =(O41/O112)*100 -> #DIV/0! | R41: =P41*Q41 -> #DIV/0! | S41: 32400 | U41: =D41*S41 -> 0 | V41: =E41*S41 -> 0 | W41: =F41*S41 -> 0 | X41: =G41*S41 -> 0 | Y41: =H41*S41 -> 0 | Z41: =I41*S41 -> 0 | AA41: =J41*S41 -> 0 | AB41: =K41*S41 -> 0 | AC41: =L41*S41 -> 0 | AD41: =M41*S41 -> 0
A42: 35 | B42: Paket Roma 3 | C42: Paket Prenic 2 | N42: =SUM(D42:M42) -> 0 | O42: =N42*S42 -> 0 | P42: =(O42/O112)*100 -> #DIV/0! | R42: =P42*Q42 -> #DIV/0! | S42: 33750 | U42: =D42*S42 -> 0 | V42: =E42*S42 -> 0 | W42: =F42*S42 -> 0 | X42: =G42*S42 -> 0 | Y42: =H42*S42 -> 0 | Z42: =I42*S42 -> 0 | AA42: =J42*S42 -> 0 | AB42: =K42*S42 -> 0 | AC42: =L42*S42 -> 0 | AD42: =M42*S42 -> 0
A43: 36 | B43: Paket Roma 4 | C43: Paket Prenic 3 | N43: =SUM(D43:M43) -> 0 | O43: =N43*S43 -> 0 | P43: =(O43/O112)*100 -> #DIV/0! | R43: =P43*Q43 -> #DIV/0! | S43: 32400 | U43: =D43*S43 -> 0 | V43: =E43*S43 -> 0 | W43: =F43*S43 -> 0 | X43: =G43*S43 -> 0 | Y43: =H43*S43 -> 0 | Z43: =I43*S43 -> 0 | AA43: =J43*S43 -> 0 | AB43: =K43*S43 -> 0 | AC43: =L43*S43 -> 0 | AD43: =M43*S43 -> 0
A44: 37 | B44: Paket Roma 5 | C44: Paket Prenic 4 | N44: =SUM(D44:M44) -> 0 | O44: =N44*S44 -> 0 | P44: =(O44/O112)*100 -> #DIV/0! | R44: =P44*Q44 -> #DIV/0! | S44: 29700 | U44: =D44*S44 -> 0 | V44: =E44*S44 -> 0 | W44: =F44*S44 -> 0 | X44: =G44*S44 -> 0 | Y44: =H44*S44 -> 0 | Z44: =I44*S44 -> 0 | AA44: =J44*S44 -> 0 | AB44: =K44*S44 -> 0 | AC44: =L44*S44 -> 0 | AD44: =M44*S44 -> 0
A45: 38 | O45: =N45*S45 -> 0 | P45: =(O45/O112)*100 -> #DIV/0! | R45: =P45*Q45 -> #DIV/0! | U45: =D45*S45 -> 0 | V45: =E45*S45 -> 0 | W45: =F45*S45 -> 0 | X45: =G45*S45 -> 0 | Y45: =H45*S45 -> 0 | Z45: =I45*S45 -> 0 | AA45: =J45*S45 -> 0 | AB45: =K45*S45 -> 0 | AC45: =L45*S45 -> 0 | AD45: =M45*S45 -> 0
A46: 39 | B46: Paket Geprek 1 | C46: Geprek Sayap | N46: =SUM(D46:M46) -> 0 | O46: =N46*S46 -> 0 | P46: =(O46/O112)*100 -> #DIV/0! | R46: =P46*Q46 -> #DIV/0! | S46: 18900 | U46: =D46*S46 -> 0 | V46: =E46*S46 -> 0 | W46: =F46*S46 -> 0 | X46: =G46*S46 -> 0 | Y46: =H46*S46 -> 0 | Z46: =I46*S46 -> 0 | AA46: =J46*S46 -> 0 | AB46: =K46*S46 -> 0 | AC46: =L46*S46 -> 0 | AD46: =M46*S46 -> 0
A47: 40 | B47: Paket Geprek 2 | C47: Geprek Paha Bawah | N47: =SUM(D47:M47) -> 0 | O47: =N47*S47 -> 0 | P47: =(O47/O112)*100 -> #DIV/0! | R47: =P47*Q47 -> #DIV/0! | S47: 20250 | U47: =D47*S47 -> 0 | V47: =E47*S47 -> 0 | W47: =F47*S47 -> 0 | X47: =G47*S47 -> 0 | Y47: =H47*S47 -> 0 | Z47: =I47*S47 -> 0 | AA47: =J47*S47 -> 0 | AB47: =K47*S47 -> 0 | AC47: =L47*S47 -> 0 | AD47: =M47*S47 -> 0
A48: 41 | B48: Paket Geprek 3 | C48: Geprek Dada/Paha Atas | N48: =SUM(D48:M48) -> 0 | O48: =N48*S48 -> 0 | P48: =(O48/O112)*100 -> #DIV/0! | R48: =P48*Q48 -> #DIV/0! | S48: 22950 | U48: =D48*S48 -> 0 | V48: =E48*S48 -> 0 | W48: =F48*S48 -> 0 | X48: =G48*S48 -> 0 | Y48: =H48*S48 -> 0 | Z48: =I48*S48 -> 0 | AA48: =J48*S48 -> 0 | AB48: =K48*S48 -> 0 | AC48: =L48*S48 -> 0 | AD48: =M48*S48 -> 0
A49: 42 | B49: Geprek Sayap | C49: Sambel Geprek | N49: =SUM(D49:M49) -> 0 | O49: =N49*S49 -> 0 | P49: =(O49/O112)*100 -> #DIV/0! | R49: =P49*Q49 -> #DIV/0! | S49: 5400 | U49: =D49*S49 -> 0 | V49: =E49*S49 -> 0 | W49: =F49*S49 -> 0 | X49: =G49*S49 -> 0 | Y49: =H49*S49 -> 0 | Z49: =I49*S49 -> 0 | AA49: =J49*S49 -> 0 | AB49: =K49*S49 -> 0 | AC49: =L49*S49 -> 0 | AD49: =M49*S49 -> 0
